package com.google.android.gms.ads.internal.renderer;

import android.content.Context;
import com.google.android.gms.ads.internal.az;
import com.google.android.gms.ads.internal.g.l;
import com.google.android.gms.ads.internal.request.AdResponseParcel;
import com.google.android.gms.ads.internal.util.ax;
import com.google.android.gms.ads.internal.zxxz.aa;
import java.util.concurrent.Future;

@com.google.android.gms.ads.internal.q.a.a
public final class m
  extends com.google.android.gms.ads.internal.util.a
{
  public final f a;
  private final AdResponseParcel b;
  private Future c;
  private final Object d = new Object();
  private final com.google.android.gms.ads.internal.renderer.a.b e;
  private final com.google.android.gms.ads.internal.v.b f;
  
  public m(Context paramContext, az paramaz, com.google.android.gms.ads.internal.v.b paramb, aa paramaa, f paramf, l paraml)
  {
    this(paramb, paramf, new com.google.android.gms.ads.internal.renderer.a.b(paramContext, paramaz, new ax(paramContext), paramaa, paramb, paraml));
  }
  
  private m(com.google.android.gms.ads.internal.v.b paramb, f paramf, com.google.android.gms.ads.internal.renderer.a.b paramb1)
  {
    this.f = paramb;
    this.b = paramb.e;
    this.a = paramf;
    this.e = paramb1;
  }
  
  /* Error */
  public final void a()
  {
    // Byte code:
    //   0: aload_0
    //   1: getfield 41	com/google/android/gms/ads/internal/renderer/m:d	Ljava/lang/Object;
    //   4: astore 13
    //   6: aload 13
    //   8: monitorenter
    //   9: aload_0
    //   10: aload_0
    //   11: getfield 53	com/google/android/gms/ads/internal/renderer/m:e	Lcom/google/android/gms/ads/internal/renderer/a/b;
    //   14: invokestatic 66	com/google/android/gms/ads/internal/util/l:a	(Ljava/util/concurrent/Callable;)Lcom/google/android/gms/ads/internal/util/a/v;
    //   17: putfield 68	com/google/android/gms/ads/internal/renderer/m:c	Ljava/util/concurrent/Future;
    //   20: aload 13
    //   22: monitorexit
    //   23: aload_0
    //   24: getfield 68	com/google/android/gms/ads/internal/renderer/m:c	Ljava/util/concurrent/Future;
    //   27: ldc2_w 69
    //   30: getstatic 76	java/util/concurrent/TimeUnit:MILLISECONDS	Ljava/util/concurrent/TimeUnit;
    //   33: invokeinterface 82 4 0
    //   38: checkcast 84	com/google/android/gms/ads/internal/v/a
    //   41: astore 13
    //   43: bipush -2
    //   45: istore_1
    //   46: aload 13
    //   48: astore 14
    //   50: aload 13
    //   52: ifnonnull +221 -> 273
    //   55: aload_0
    //   56: getfield 43	com/google/android/gms/ads/internal/renderer/m:f	Lcom/google/android/gms/ads/internal/v/b;
    //   59: astore 19
    //   61: aload 19
    //   63: getfield 87	com/google/android/gms/ads/internal/v/b:d	Lcom/google/android/gms/ads/internal/request/AdRequestInfoParcel;
    //   66: astore 14
    //   68: aload 14
    //   70: getfield 92	com/google/android/gms/ads/internal/request/AdRequestInfoParcel:b	Lcom/google/android/gms/ads/internal/client/AdRequestParcel;
    //   73: astore 13
    //   75: aload_0
    //   76: getfield 49	com/google/android/gms/ads/internal/renderer/m:b	Lcom/google/android/gms/ads/internal/request/AdResponseParcel;
    //   79: astore 20
    //   81: aload 20
    //   83: getfield 98	com/google/android/gms/ads/internal/request/AdResponseParcel:K	I
    //   86: istore_2
    //   87: aload 20
    //   89: getfield 102	com/google/android/gms/ads/internal/request/AdResponseParcel:M	J
    //   92: lstore_3
    //   93: aload 14
    //   95: getfield 106	com/google/android/gms/ads/internal/request/AdRequestInfoParcel:X	Ljava/lang/String;
    //   98: astore 14
    //   100: aload 20
    //   102: getfield 109	com/google/android/gms/ads/internal/request/AdResponseParcel:G	J
    //   105: lstore 5
    //   107: aload 19
    //   109: getfield 113	com/google/android/gms/ads/internal/v/b:g	Lcom/google/android/gms/ads/internal/client/AdSizeParcel;
    //   112: astore 15
    //   114: aload 20
    //   116: getfield 116	com/google/android/gms/ads/internal/request/AdResponseParcel:r	J
    //   119: lstore 5
    //   121: aload 19
    //   123: getfield 118	com/google/android/gms/ads/internal/v/b:f	J
    //   126: lstore 5
    //   128: aload 20
    //   130: getfield 121	com/google/android/gms/ads/internal/request/AdResponseParcel:o	J
    //   133: lstore 7
    //   135: aload 20
    //   137: getfield 124	com/google/android/gms/ads/internal/request/AdResponseParcel:k	Ljava/lang/String;
    //   140: astore 16
    //   142: aload 19
    //   144: getfield 127	com/google/android/gms/ads/internal/v/b:a	Lorg/json/JSONObject;
    //   147: astore 17
    //   149: aload 19
    //   151: getfield 47	com/google/android/gms/ads/internal/v/b:e	Lcom/google/android/gms/ads/internal/request/AdResponseParcel;
    //   154: astore 18
    //   156: aload 18
    //   158: getfield 131	com/google/android/gms/ads/internal/request/AdResponseParcel:E	Z
    //   161: istore 9
    //   163: aload 18
    //   165: getfield 134	com/google/android/gms/ads/internal/request/AdResponseParcel:d	Lcom/google/android/gms/ads/internal/request/AutoClickProtectionConfigurationParcel;
    //   168: astore 21
    //   170: aload 20
    //   172: getfield 137	com/google/android/gms/ads/internal/request/AdResponseParcel:l	Ljava/lang/String;
    //   175: astore 20
    //   177: aload 19
    //   179: getfield 140	com/google/android/gms/ads/internal/v/b:c	Lcom/google/android/gms/ads/internal/d/a;
    //   182: astore 19
    //   184: aload 18
    //   186: getfield 143	com/google/android/gms/ads/internal/request/AdResponseParcel:u	Z
    //   189: istore 10
    //   191: aload 18
    //   193: getfield 146	com/google/android/gms/ads/internal/request/AdResponseParcel:C	Z
    //   196: istore 11
    //   198: aload 18
    //   200: getfield 149	com/google/android/gms/ads/internal/request/AdResponseParcel:t	Z
    //   203: istore 12
    //   205: aload 18
    //   207: getfield 151	com/google/android/gms/ads/internal/request/AdResponseParcel:J	Ljava/lang/String;
    //   210: astore 21
    //   212: new 84	com/google/android/gms/ads/internal/v/a
    //   215: dup
    //   216: aload 13
    //   218: aconst_null
    //   219: aconst_null
    //   220: iload_1
    //   221: aconst_null
    //   222: aconst_null
    //   223: iload_2
    //   224: lload_3
    //   225: aload 14
    //   227: iconst_0
    //   228: aconst_null
    //   229: aconst_null
    //   230: aconst_null
    //   231: aconst_null
    //   232: aconst_null
    //   233: aload 15
    //   235: lload 5
    //   237: lload 7
    //   239: aload 16
    //   241: aload 17
    //   243: aconst_null
    //   244: aconst_null
    //   245: aconst_null
    //   246: aconst_null
    //   247: iload 9
    //   249: aconst_null
    //   250: aconst_null
    //   251: aload 20
    //   253: aload 19
    //   255: iload 10
    //   257: iconst_0
    //   258: iload 11
    //   260: aconst_null
    //   261: iload 12
    //   263: aload 18
    //   265: getfield 154	com/google/android/gms/ads/internal/request/AdResponseParcel:S	Z
    //   268: invokespecial 157	com/google/android/gms/ads/internal/v/a:<init>	(Lcom/google/android/gms/ads/internal/client/AdRequestParcel;Lcom/google/android/gms/ads/internal/webview/i;Ljava/util/List;ILjava/util/List;Ljava/util/List;IJLjava/lang/String;ZLcom/google/android/gms/ads/internal/mediation/b;Lcom/google/android/gms/ads/internal/mediation/client/e;Ljava/lang/String;Lcom/google/android/gms/ads/internal/mediation/c;Lcom/google/android/gms/ads/internal/mediation/e;Lcom/google/android/gms/ads/internal/client/AdSizeParcel;JJLjava/lang/String;Lorg/json/JSONObject;Lcom/google/android/gms/ads/internal/formats/v;Lcom/google/android/gms/ads/internal/reward/mediation/client/RewardItemParcel;Ljava/util/List;Ljava/util/List;ZLjava/lang/String;Ljava/util/List;Ljava/lang/String;Lcom/google/android/gms/ads/internal/d/a;ZZZLjava/util/List;ZZ)V
    //   271: astore 14
    //   273: getstatic 162	com/google/android/gms/ads/internal/util/n:a	Landroid/os/Handler;
    //   276: new 164	com/google/android/gms/ads/internal/renderer/n
    //   279: dup
    //   280: aload_0
    //   281: aload 14
    //   283: invokespecial 167	com/google/android/gms/ads/internal/renderer/n:<init>	(Lcom/google/android/gms/ads/internal/renderer/m;Lcom/google/android/gms/ads/internal/v/a;)V
    //   286: invokevirtual 173	android/os/Handler:post	(Ljava/lang/Runnable;)Z
    //   289: pop
    //   290: return
    //   291: astore 13
    //   293: ldc -81
    //   295: invokestatic 180	com/google/android/gms/ads/internal/util/e:e	(Ljava/lang/String;)V
    //   298: aload_0
    //   299: getfield 68	com/google/android/gms/ads/internal/renderer/m:c	Ljava/util/concurrent/Future;
    //   302: iconst_1
    //   303: invokeinterface 184 2 0
    //   308: pop
    //   309: iconst_2
    //   310: istore_1
    //   311: aconst_null
    //   312: astore 13
    //   314: goto -268 -> 46
    //   317: astore 13
    //   319: iconst_0
    //   320: istore_1
    //   321: aconst_null
    //   322: astore 13
    //   324: goto -278 -> 46
    //   327: astore 13
    //   329: iconst_0
    //   330: istore_1
    //   331: aconst_null
    //   332: astore 13
    //   334: goto -288 -> 46
    //   337: astore 13
    //   339: iconst_0
    //   340: istore_1
    //   341: aconst_null
    //   342: astore 13
    //   344: goto -298 -> 46
    //   347: astore 14
    //   349: aload 13
    //   351: monitorexit
    //   352: aload 14
    //   354: athrow
    // Local variable table:
    //   start	length	slot	name	signature
    //   0	355	0	this	m
    //   45	296	1	i	int
    //   86	138	2	j	int
    //   92	133	3	l1	long
    //   105	131	5	l2	long
    //   133	105	7	l3	long
    //   161	87	9	bool1	boolean
    //   189	67	10	bool2	boolean
    //   196	63	11	bool3	boolean
    //   203	59	12	bool4	boolean
    //   291	1	13	localTimeoutException	java.util.concurrent.TimeoutException
    //   312	1	13	localObject2	Object
    //   317	1	13	localExecutionException	java.util.concurrent.ExecutionException
    //   322	1	13	localObject3	Object
    //   327	1	13	localInterruptedException	InterruptedException
    //   332	1	13	localObject4	Object
    //   337	1	13	localCancellationException	java.util.concurrent.CancellationException
    //   342	8	13	localObject5	Object
    //   48	234	14	localObject6	Object
    //   347	6	14	localObject7	Object
    //   112	122	15	localAdSizeParcel	com.google.android.gms.ads.internal.client.AdSizeParcel
    //   140	100	16	str	String
    //   147	95	17	localJSONObject	org.json.JSONObject
    //   154	110	18	localAdResponseParcel	AdResponseParcel
    //   59	195	19	localObject8	Object
    //   79	173	20	localObject9	Object
    //   168	43	21	localObject10	Object
    // Exception table:
    //   from	to	target	type
    //   0	9	291	java/util/concurrent/TimeoutException
    //   23	43	291	java/util/concurrent/TimeoutException
    //   352	355	291	java/util/concurrent/TimeoutException
    //   0	9	317	java/util/concurrent/ExecutionException
    //   23	43	317	java/util/concurrent/ExecutionException
    //   352	355	317	java/util/concurrent/ExecutionException
    //   0	9	327	java/lang/InterruptedException
    //   23	43	327	java/lang/InterruptedException
    //   352	355	327	java/lang/InterruptedException
    //   0	9	337	java/util/concurrent/CancellationException
    //   23	43	337	java/util/concurrent/CancellationException
    //   352	355	337	java/util/concurrent/CancellationException
    //   9	23	347	finally
    //   349	352	347	finally
  }
  
  public final void be_()
  {
    synchronized (this.d)
    {
      Future localFuture = this.c;
      if (localFuture != null) {
        localFuture.cancel(true);
      }
      return;
    }
  }
}


/* Location:              /home/chengjian/CM_test/gp/apk/a.jar!/com/google/android/gms/ads/internal/renderer/m.class
 * Java compiler version: 6 (50.0)
 * JD-Core Version:       0.7.1
 */