package com.tencent.mm.app;

import android.content.ComponentName;
import android.content.ServiceConnection;
import android.os.IBinder;
import com.tencent.gmtrace.GMTrace;
import com.tencent.mm.kernel.a;
import com.tencent.mm.kernel.b;
import com.tencent.mm.kernel.h;
import com.tencent.mm.network.g.a;
import com.tencent.mm.network.r.a;
import com.tencent.mm.sdk.platformtools.aa;
import com.tencent.mm.sdk.platformtools.ae;
import com.tencent.mm.sdk.platformtools.v;
import com.tencent.mm.u.ad;
import com.tencent.mm.y.n;
import java.util.concurrent.locks.ReentrantLock;

public final class d
  implements ServiceConnection
{
  private static boolean fvH;
  private static Object lock;
  public ReentrantLock fvI;
  private boolean fvJ;
  public IBinder fvK;
  private Runnable fvL;
  
  static
  {
    GMTrace.i(13714099011584L, 102178);
    fvH = false;
    lock = new Object();
    GMTrace.o(13714099011584L, 102178);
  }
  
  public d()
  {
    GMTrace.i(13713293705216L, 102172);
    this.fvI = new ReentrantLock();
    this.fvJ = false;
    this.fvK = null;
    this.fvL = new Runnable()
    {
      private int fvP;
      
      /* Error */
      public final void run()
      {
        // Byte code:
        //   0: ldc2_w 38
        //   3: ldc 40
        //   5: invokestatic 28	com/tencent/gmtrace/GMTrace:i	(JI)V
        //   8: aload_0
        //   9: getfield 16	com/tencent/mm/app/d$3:fvM	Lcom/tencent/mm/app/d;
        //   12: getfield 44	com/tencent/mm/app/d:fvI	Ljava/util/concurrent/locks/ReentrantLock;
        //   15: invokevirtual 49	java/util/concurrent/locks/ReentrantLock:lock	()V
        //   18: aload_0
        //   19: getfield 16	com/tencent/mm/app/d$3:fvM	Lcom/tencent/mm/app/d;
        //   22: getfield 53	com/tencent/mm/app/d:fvK	Landroid/os/IBinder;
        //   25: ifnull +78 -> 103
        //   28: aload_0
        //   29: getfield 16	com/tencent/mm/app/d$3:fvM	Lcom/tencent/mm/app/d;
        //   32: getfield 53	com/tencent/mm/app/d:fvK	Landroid/os/IBinder;
        //   35: invokeinterface 59 1 0
        //   40: ifeq +63 -> 103
        //   43: iconst_1
        //   44: istore_2
        //   45: ldc 61
        //   47: ldc 63
        //   49: iconst_2
        //   50: anewarray 4	java/lang/Object
        //   53: dup
        //   54: iconst_0
        //   55: aload_0
        //   56: getfield 16	com/tencent/mm/app/d$3:fvM	Lcom/tencent/mm/app/d;
        //   59: getfield 53	com/tencent/mm/app/d:fvK	Landroid/os/IBinder;
        //   62: aastore
        //   63: dup
        //   64: iconst_1
        //   65: iload_2
        //   66: invokestatic 69	java/lang/Boolean:valueOf	(Z)Ljava/lang/Boolean;
        //   69: aastore
        //   70: invokestatic 74	com/tencent/mm/sdk/platformtools/v:i	(Ljava/lang/String;Ljava/lang/String;[Ljava/lang/Object;)V
        //   73: iload_2
        //   74: ifeq +34 -> 108
        //   77: ldc 61
        //   79: ldc 76
        //   81: invokestatic 80	com/tencent/mm/sdk/platformtools/v:w	(Ljava/lang/String;Ljava/lang/String;)V
        //   84: aload_0
        //   85: getfield 16	com/tencent/mm/app/d$3:fvM	Lcom/tencent/mm/app/d;
        //   88: getfield 44	com/tencent/mm/app/d:fvI	Ljava/util/concurrent/locks/ReentrantLock;
        //   91: invokevirtual 83	java/util/concurrent/locks/ReentrantLock:unlock	()V
        //   94: ldc2_w 38
        //   97: ldc 40
        //   99: invokestatic 33	com/tencent/gmtrace/GMTrace:o	(JI)V
        //   102: return
        //   103: iconst_0
        //   104: istore_2
        //   105: goto -60 -> 45
        //   108: aload_0
        //   109: getfield 16	com/tencent/mm/app/d$3:fvM	Lcom/tencent/mm/app/d;
        //   112: getfield 44	com/tencent/mm/app/d:fvI	Ljava/util/concurrent/locks/ReentrantLock;
        //   115: invokevirtual 83	java/util/concurrent/locks/ReentrantLock:unlock	()V
        //   118: ldc 61
        //   120: ldc 85
        //   122: iconst_1
        //   123: anewarray 4	java/lang/Object
        //   126: dup
        //   127: iconst_0
        //   128: aload_0
        //   129: getfield 30	com/tencent/mm/app/d$3:fvP	I
        //   132: invokestatic 90	java/lang/Integer:valueOf	(I)Ljava/lang/Integer;
        //   135: aastore
        //   136: invokestatic 96	java/lang/String:format	(Ljava/lang/String;[Ljava/lang/Object;)Ljava/lang/String;
        //   139: invokestatic 99	com/tencent/mm/sdk/platformtools/v:e	(Ljava/lang/String;Ljava/lang/String;)V
        //   142: aload_0
        //   143: getfield 30	com/tencent/mm/app/d$3:fvP	I
        //   146: iconst_1
        //   147: if_icmpne +42 -> 189
        //   150: ldc 101
        //   152: invokestatic 105	com/tencent/mm/app/d:bh	(Ljava/lang/String;)I
        //   155: istore_1
        //   156: iload_1
        //   157: iconst_m1
        //   158: if_icmpeq +154 -> 312
        //   161: ldc 61
        //   163: ldc 107
        //   165: iconst_1
        //   166: anewarray 4	java/lang/Object
        //   169: dup
        //   170: iconst_0
        //   171: iload_1
        //   172: invokestatic 90	java/lang/Integer:valueOf	(I)Ljava/lang/Integer;
        //   175: aastore
        //   176: invokestatic 96	java/lang/String:format	(Ljava/lang/String;[Ljava/lang/Object;)Ljava/lang/String;
        //   179: invokestatic 109	com/tencent/mm/sdk/platformtools/v:i	(Ljava/lang/String;Ljava/lang/String;)V
        //   182: invokestatic 112	com/tencent/mm/sdk/platformtools/v:bIF	()V
        //   185: iload_1
        //   186: invokestatic 118	android/os/Process:killProcess	(I)V
        //   189: invokestatic 124	com/tencent/mm/sdk/platformtools/aa:getContext	()Landroid/content/Context;
        //   192: astore_3
        //   193: new 126	android/content/Intent
        //   196: dup
        //   197: aload_3
        //   198: ldc -128
        //   200: invokespecial 131	android/content/Intent:<init>	(Landroid/content/Context;Ljava/lang/Class;)V
        //   203: astore 4
        //   205: ldc 61
        //   207: ldc -123
        //   209: invokestatic 109	com/tencent/mm/sdk/platformtools/v:i	(Ljava/lang/String;Ljava/lang/String;)V
        //   212: aload_3
        //   213: aload_0
        //   214: getfield 16	com/tencent/mm/app/d$3:fvM	Lcom/tencent/mm/app/d;
        //   217: invokevirtual 139	android/content/Context:unbindService	(Landroid/content/ServiceConnection;)V
        //   220: aload_3
        //   221: aload 4
        //   223: invokevirtual 143	android/content/Context:stopService	(Landroid/content/Intent;)Z
        //   226: pop
        //   227: aload_3
        //   228: aload 4
        //   230: aload_0
        //   231: getfield 16	com/tencent/mm/app/d$3:fvM	Lcom/tencent/mm/app/d;
        //   234: iconst_1
        //   235: invokevirtual 147	android/content/Context:bindService	(Landroid/content/Intent;Landroid/content/ServiceConnection;I)Z
        //   238: pop
        //   239: aload_3
        //   240: aload 4
        //   242: invokevirtual 151	android/content/Context:startService	(Landroid/content/Intent;)Landroid/content/ComponentName;
        //   245: pop
        //   246: aload_0
        //   247: getfield 30	com/tencent/mm/app/d$3:fvP	I
        //   250: iconst_1
        //   251: if_icmpne +133 -> 384
        //   254: aload_0
        //   255: iconst_0
        //   256: putfield 30	com/tencent/mm/app/d$3:fvP	I
        //   259: aload_0
        //   260: ldc2_w 152
        //   263: invokestatic 159	com/tencent/mm/sdk/platformtools/ae:f	(Ljava/lang/Runnable;J)V
        //   266: ldc 61
        //   268: ldc -95
        //   270: iconst_1
        //   271: anewarray 4	java/lang/Object
        //   274: dup
        //   275: iconst_0
        //   276: aload_0
        //   277: getfield 30	com/tencent/mm/app/d$3:fvP	I
        //   280: invokestatic 90	java/lang/Integer:valueOf	(I)Ljava/lang/Integer;
        //   283: aastore
        //   284: invokestatic 96	java/lang/String:format	(Ljava/lang/String;[Ljava/lang/Object;)Ljava/lang/String;
        //   287: invokestatic 109	com/tencent/mm/sdk/platformtools/v:i	(Ljava/lang/String;Ljava/lang/String;)V
        //   290: ldc2_w 38
        //   293: ldc 40
        //   295: invokestatic 33	com/tencent/gmtrace/GMTrace:o	(JI)V
        //   298: return
        //   299: astore_3
        //   300: aload_0
        //   301: getfield 16	com/tencent/mm/app/d$3:fvM	Lcom/tencent/mm/app/d;
        //   304: getfield 44	com/tencent/mm/app/d:fvI	Ljava/util/concurrent/locks/ReentrantLock;
        //   307: invokevirtual 83	java/util/concurrent/locks/ReentrantLock:unlock	()V
        //   310: aload_3
        //   311: athrow
        //   312: ldc 61
        //   314: ldc -93
        //   316: invokestatic 109	com/tencent/mm/sdk/platformtools/v:i	(Ljava/lang/String;Ljava/lang/String;)V
        //   319: goto -130 -> 189
        //   322: astore 5
        //   324: aload_3
        //   325: aload 4
        //   327: invokevirtual 143	android/content/Context:stopService	(Landroid/content/Intent;)Z
        //   330: pop
        //   331: aload_3
        //   332: aload 4
        //   334: aload_0
        //   335: getfield 16	com/tencent/mm/app/d$3:fvM	Lcom/tencent/mm/app/d;
        //   338: iconst_1
        //   339: invokevirtual 147	android/content/Context:bindService	(Landroid/content/Intent;Landroid/content/ServiceConnection;I)Z
        //   342: pop
        //   343: aload_3
        //   344: aload 4
        //   346: invokevirtual 151	android/content/Context:startService	(Landroid/content/Intent;)Landroid/content/ComponentName;
        //   349: pop
        //   350: goto -104 -> 246
        //   353: astore 5
        //   355: aload_3
        //   356: aload 4
        //   358: invokevirtual 143	android/content/Context:stopService	(Landroid/content/Intent;)Z
        //   361: pop
        //   362: aload_3
        //   363: aload 4
        //   365: aload_0
        //   366: getfield 16	com/tencent/mm/app/d$3:fvM	Lcom/tencent/mm/app/d;
        //   369: iconst_1
        //   370: invokevirtual 147	android/content/Context:bindService	(Landroid/content/Intent;Landroid/content/ServiceConnection;I)Z
        //   373: pop
        //   374: aload_3
        //   375: aload 4
        //   377: invokevirtual 151	android/content/Context:startService	(Landroid/content/Intent;)Landroid/content/ComponentName;
        //   380: pop
        //   381: aload 5
        //   383: athrow
        //   384: aload_0
        //   385: aload_0
        //   386: getfield 30	com/tencent/mm/app/d$3:fvP	I
        //   389: iconst_1
        //   390: iadd
        //   391: putfield 30	com/tencent/mm/app/d$3:fvP	I
        //   394: goto -135 -> 259
        // Local variable table:
        //   start	length	slot	name	signature
        //   0	397	0	this	3
        //   155	31	1	i	int
        //   44	61	2	bool	boolean
        //   192	48	3	localContext	android.content.Context
        //   299	76	3	localObject1	Object
        //   203	173	4	localIntent	android.content.Intent
        //   322	1	5	localException	Exception
        //   353	29	5	localObject2	Object
        // Exception table:
        //   from	to	target	type
        //   8	43	299	finally
        //   45	73	299	finally
        //   77	84	299	finally
        //   205	220	322	java/lang/Exception
        //   205	220	353	finally
      }
    };
    GMTrace.o(13713293705216L, 102172);
  }
  
  /* Error */
  public static int bh(String paramString)
  {
    // Byte code:
    //   0: iconst_m1
    //   1: istore_1
    //   2: ldc2_w 69
    //   5: ldc 71
    //   7: invokestatic 36	com/tencent/gmtrace/GMTrace:i	(JI)V
    //   10: new 73	java/io/File
    //   13: dup
    //   14: ldc 75
    //   16: invokespecial 78	java/io/File:<init>	(Ljava/lang/String;)V
    //   19: invokevirtual 82	java/io/File:listFiles	()[Ljava/io/File;
    //   22: astore 9
    //   24: aload 9
    //   26: arraylength
    //   27: istore 4
    //   29: iconst_0
    //   30: istore_2
    //   31: aconst_null
    //   32: astore 7
    //   34: iload_1
    //   35: istore_3
    //   36: iload_2
    //   37: iload 4
    //   39: if_icmpge +196 -> 235
    //   42: aload 9
    //   44: iload_2
    //   45: aaload
    //   46: astore 8
    //   48: aload 8
    //   50: invokevirtual 86	java/io/File:getName	()Ljava/lang/String;
    //   53: iconst_m1
    //   54: invokestatic 92	com/tencent/mm/sdk/platformtools/bf:getInt	(Ljava/lang/String;I)I
    //   57: istore_3
    //   58: iload_3
    //   59: istore_1
    //   60: aload 7
    //   62: astore 6
    //   64: new 73	java/io/File
    //   67: dup
    //   68: aload 8
    //   70: ldc 94
    //   72: invokespecial 97	java/io/File:<init>	(Ljava/io/File;Ljava/lang/String;)V
    //   75: astore 8
    //   77: aload 7
    //   79: astore 6
    //   81: aload 8
    //   83: invokevirtual 101	java/io/File:canRead	()Z
    //   86: istore 5
    //   88: iload 5
    //   90: ifne +61 -> 151
    //   93: iload_1
    //   94: istore_3
    //   95: aload 7
    //   97: astore 6
    //   99: aload 7
    //   101: ifnull +13 -> 114
    //   104: aload 7
    //   106: invokevirtual 106	java/io/BufferedReader:close	()V
    //   109: aconst_null
    //   110: astore 6
    //   112: iload_1
    //   113: istore_3
    //   114: iload_2
    //   115: iconst_1
    //   116: iadd
    //   117: istore_2
    //   118: iload_3
    //   119: istore_1
    //   120: aload 6
    //   122: astore 7
    //   124: goto -90 -> 34
    //   127: astore 6
    //   129: ldc 108
    //   131: aload 6
    //   133: ldc 110
    //   135: iconst_0
    //   136: anewarray 4	java/lang/Object
    //   139: invokestatic 116	com/tencent/mm/sdk/platformtools/v:printErrStackTrace	(Ljava/lang/String;Ljava/lang/Throwable;Ljava/lang/String;[Ljava/lang/Object;)V
    //   142: iload_1
    //   143: istore_3
    //   144: aload 7
    //   146: astore 6
    //   148: goto -34 -> 114
    //   151: aload 7
    //   153: astore 6
    //   155: new 103	java/io/BufferedReader
    //   158: dup
    //   159: new 118	java/io/FileReader
    //   162: dup
    //   163: aload 8
    //   165: invokespecial 121	java/io/FileReader:<init>	(Ljava/io/File;)V
    //   168: invokespecial 124	java/io/BufferedReader:<init>	(Ljava/io/Reader;)V
    //   171: astore 8
    //   173: aload 8
    //   175: invokevirtual 127	java/io/BufferedReader:readLine	()Ljava/lang/String;
    //   178: astore 6
    //   180: aload 6
    //   182: ifnull +123 -> 305
    //   185: aload 6
    //   187: aload_0
    //   188: invokevirtual 133	java/lang/String:startsWith	(Ljava/lang/String;)Z
    //   191: ifeq +114 -> 305
    //   194: aload 6
    //   196: invokevirtual 137	java/lang/String:length	()I
    //   199: aload_0
    //   200: invokevirtual 137	java/lang/String:length	()I
    //   203: if_icmpne +42 -> 245
    //   206: ldc 108
    //   208: ldc -117
    //   210: iconst_2
    //   211: anewarray 4	java/lang/Object
    //   214: dup
    //   215: iconst_0
    //   216: aload_0
    //   217: aastore
    //   218: dup
    //   219: iconst_1
    //   220: iload_1
    //   221: invokestatic 145	java/lang/Integer:valueOf	(I)Ljava/lang/Integer;
    //   224: aastore
    //   225: invokestatic 148	com/tencent/mm/sdk/platformtools/v:i	(Ljava/lang/String;Ljava/lang/String;[Ljava/lang/Object;)V
    //   228: aload 8
    //   230: invokevirtual 106	java/io/BufferedReader:close	()V
    //   233: iload_1
    //   234: istore_3
    //   235: ldc2_w 69
    //   238: ldc 71
    //   240: invokestatic 46	com/tencent/gmtrace/GMTrace:o	(JI)V
    //   243: iload_3
    //   244: ireturn
    //   245: aload 6
    //   247: aload_0
    //   248: invokevirtual 137	java/lang/String:length	()I
    //   251: invokevirtual 152	java/lang/String:charAt	(I)C
    //   254: istore_3
    //   255: iload_3
    //   256: bipush 32
    //   258: if_icmple +9 -> 267
    //   261: iload_3
    //   262: bipush 127
    //   264: if_icmplt +41 -> 305
    //   267: ldc 108
    //   269: ldc -117
    //   271: iconst_2
    //   272: anewarray 4	java/lang/Object
    //   275: dup
    //   276: iconst_0
    //   277: aload_0
    //   278: aastore
    //   279: dup
    //   280: iconst_1
    //   281: iload_1
    //   282: invokestatic 145	java/lang/Integer:valueOf	(I)Ljava/lang/Integer;
    //   285: aastore
    //   286: invokestatic 148	com/tencent/mm/sdk/platformtools/v:i	(Ljava/lang/String;Ljava/lang/String;[Ljava/lang/Object;)V
    //   289: aload 8
    //   291: invokevirtual 106	java/io/BufferedReader:close	()V
    //   294: iload_1
    //   295: istore_3
    //   296: goto -61 -> 235
    //   299: astore_0
    //   300: iload_1
    //   301: istore_3
    //   302: goto -67 -> 235
    //   305: aload 8
    //   307: invokevirtual 106	java/io/BufferedReader:close	()V
    //   310: aconst_null
    //   311: astore 6
    //   313: iload_1
    //   314: istore_3
    //   315: goto -201 -> 114
    //   318: astore 6
    //   320: aload 8
    //   322: astore 7
    //   324: aload 6
    //   326: astore 8
    //   328: aload 7
    //   330: astore 6
    //   332: ldc 108
    //   334: aload 8
    //   336: ldc -102
    //   338: iconst_0
    //   339: anewarray 4	java/lang/Object
    //   342: invokestatic 116	com/tencent/mm/sdk/platformtools/v:printErrStackTrace	(Ljava/lang/String;Ljava/lang/Throwable;Ljava/lang/String;[Ljava/lang/Object;)V
    //   345: aload 7
    //   347: astore 6
    //   349: invokestatic 157	com/tencent/mm/sdk/platformtools/v:bIF	()V
    //   352: iload_1
    //   353: istore_3
    //   354: aload 7
    //   356: astore 6
    //   358: aload 7
    //   360: ifnull -246 -> 114
    //   363: aload 7
    //   365: invokevirtual 106	java/io/BufferedReader:close	()V
    //   368: aconst_null
    //   369: astore 6
    //   371: iload_1
    //   372: istore_3
    //   373: goto -259 -> 114
    //   376: astore_0
    //   377: aload 8
    //   379: ifnull +8 -> 387
    //   382: aload 8
    //   384: invokevirtual 106	java/io/BufferedReader:close	()V
    //   387: aload_0
    //   388: athrow
    //   389: astore 6
    //   391: goto -282 -> 109
    //   394: astore_0
    //   395: iload_1
    //   396: istore_3
    //   397: goto -162 -> 235
    //   400: astore 6
    //   402: goto -92 -> 310
    //   405: astore 6
    //   407: goto -39 -> 368
    //   410: astore 6
    //   412: goto -25 -> 387
    //   415: astore_0
    //   416: aload 6
    //   418: astore 8
    //   420: goto -43 -> 377
    //   423: astore 8
    //   425: goto -97 -> 328
    // Local variable table:
    //   start	length	slot	name	signature
    //   0	428	0	paramString	String
    //   1	395	1	i	int
    //   30	88	2	j	int
    //   35	362	3	k	int
    //   27	13	4	m	int
    //   86	3	5	bool	boolean
    //   62	59	6	localObject1	Object
    //   127	5	6	localThrowable1	Throwable
    //   146	166	6	localObject2	Object
    //   318	7	6	localThrowable2	Throwable
    //   330	40	6	localObject3	Object
    //   389	1	6	localThrowable3	Throwable
    //   400	1	6	localThrowable4	Throwable
    //   405	1	6	localThrowable5	Throwable
    //   410	7	6	localThrowable6	Throwable
    //   32	332	7	localObject4	Object
    //   46	373	8	localObject5	Object
    //   423	1	8	localThrowable7	Throwable
    //   22	21	9	arrayOfFile	java.io.File[]
    // Exception table:
    //   from	to	target	type
    //   48	58	127	java/lang/Throwable
    //   289	294	299	java/lang/Throwable
    //   173	180	318	java/lang/Throwable
    //   185	228	318	java/lang/Throwable
    //   245	255	318	java/lang/Throwable
    //   267	289	318	java/lang/Throwable
    //   173	180	376	finally
    //   185	228	376	finally
    //   245	255	376	finally
    //   267	289	376	finally
    //   104	109	389	java/lang/Throwable
    //   228	233	394	java/lang/Throwable
    //   305	310	400	java/lang/Throwable
    //   363	368	405	java/lang/Throwable
    //   382	387	410	java/lang/Throwable
    //   64	77	415	finally
    //   81	88	415	finally
    //   155	173	415	finally
    //   332	345	415	finally
    //   349	352	415	finally
    //   64	77	423	java/lang/Throwable
    //   81	88	423	java/lang/Throwable
    //   155	173	423	java/lang/Throwable
  }
  
  /* Error */
  public final void ad(android.content.Context arg1)
  {
    // Byte code:
    //   0: iconst_0
    //   1: istore_3
    //   2: ldc2_w 160
    //   5: ldc -94
    //   7: invokestatic 36	com/tencent/gmtrace/GMTrace:i	(JI)V
    //   10: aload_0
    //   11: getfield 55	com/tencent/mm/app/d:fvI	Ljava/util/concurrent/locks/ReentrantLock;
    //   14: invokevirtual 164	java/util/concurrent/locks/ReentrantLock:lock	()V
    //   17: iload_3
    //   18: istore_2
    //   19: aload_0
    //   20: getfield 59	com/tencent/mm/app/d:fvK	Landroid/os/IBinder;
    //   23: ifnull +19 -> 42
    //   26: iload_3
    //   27: istore_2
    //   28: aload_0
    //   29: getfield 59	com/tencent/mm/app/d:fvK	Landroid/os/IBinder;
    //   32: invokeinterface 169 1 0
    //   37: ifeq +5 -> 42
    //   40: iconst_1
    //   41: istore_2
    //   42: ldc 108
    //   44: ldc -85
    //   46: iconst_2
    //   47: anewarray 4	java/lang/Object
    //   50: dup
    //   51: iconst_0
    //   52: aload_0
    //   53: getfield 57	com/tencent/mm/app/d:fvJ	Z
    //   56: invokestatic 176	java/lang/Boolean:valueOf	(Z)Ljava/lang/Boolean;
    //   59: aastore
    //   60: dup
    //   61: iconst_1
    //   62: iload_2
    //   63: invokestatic 176	java/lang/Boolean:valueOf	(Z)Ljava/lang/Boolean;
    //   66: aastore
    //   67: invokestatic 148	com/tencent/mm/sdk/platformtools/v:i	(Ljava/lang/String;Ljava/lang/String;[Ljava/lang/Object;)V
    //   70: aload_0
    //   71: getfield 57	com/tencent/mm/app/d:fvJ	Z
    //   74: ifne +7 -> 81
    //   77: iload_2
    //   78: ifeq +47 -> 125
    //   81: ldc 108
    //   83: ldc -78
    //   85: iconst_2
    //   86: anewarray 4	java/lang/Object
    //   89: dup
    //   90: iconst_0
    //   91: aload_0
    //   92: getfield 57	com/tencent/mm/app/d:fvJ	Z
    //   95: invokestatic 176	java/lang/Boolean:valueOf	(Z)Ljava/lang/Boolean;
    //   98: aastore
    //   99: dup
    //   100: iconst_1
    //   101: iload_2
    //   102: invokestatic 176	java/lang/Boolean:valueOf	(Z)Ljava/lang/Boolean;
    //   105: aastore
    //   106: invokestatic 181	com/tencent/mm/sdk/platformtools/v:w	(Ljava/lang/String;Ljava/lang/String;[Ljava/lang/Object;)V
    //   109: aload_0
    //   110: getfield 55	com/tencent/mm/app/d:fvI	Ljava/util/concurrent/locks/ReentrantLock;
    //   113: invokevirtual 184	java/util/concurrent/locks/ReentrantLock:unlock	()V
    //   116: ldc2_w 160
    //   119: ldc -94
    //   121: invokestatic 46	com/tencent/gmtrace/GMTrace:o	(JI)V
    //   124: return
    //   125: aload_0
    //   126: getfield 55	com/tencent/mm/app/d:fvI	Ljava/util/concurrent/locks/ReentrantLock;
    //   129: invokevirtual 184	java/util/concurrent/locks/ReentrantLock:unlock	()V
    //   132: aload_1
    //   133: ldc -70
    //   135: invokestatic 192	com/tencent/mm/booter/b:r	(Landroid/content/Context;Ljava/lang/String;)Z
    //   138: ifne +29 -> 167
    //   141: ldc 108
    //   143: ldc -62
    //   145: invokestatic 197	com/tencent/mm/sdk/platformtools/v:i	(Ljava/lang/String;Ljava/lang/String;)V
    //   148: ldc2_w 160
    //   151: ldc -94
    //   153: invokestatic 46	com/tencent/gmtrace/GMTrace:o	(JI)V
    //   156: return
    //   157: astore_1
    //   158: aload_0
    //   159: getfield 55	com/tencent/mm/app/d:fvI	Ljava/util/concurrent/locks/ReentrantLock;
    //   162: invokevirtual 184	java/util/concurrent/locks/ReentrantLock:unlock	()V
    //   165: aload_1
    //   166: athrow
    //   167: new 199	android/content/Intent
    //   170: dup
    //   171: aload_1
    //   172: ldc -55
    //   174: invokespecial 204	android/content/Intent:<init>	(Landroid/content/Context;Ljava/lang/Class;)V
    //   177: astore 4
    //   179: ldc 108
    //   181: ldc -50
    //   183: invokestatic 197	com/tencent/mm/sdk/platformtools/v:i	(Ljava/lang/String;Ljava/lang/String;)V
    //   186: aload_1
    //   187: aload 4
    //   189: aload_0
    //   190: iconst_1
    //   191: invokevirtual 212	android/content/Context:bindService	(Landroid/content/Intent;Landroid/content/ServiceConnection;I)Z
    //   194: ifne +19 -> 213
    //   197: ldc 108
    //   199: ldc -42
    //   201: invokestatic 217	com/tencent/mm/sdk/platformtools/v:e	(Ljava/lang/String;Ljava/lang/String;)V
    //   204: ldc2_w 160
    //   207: ldc -94
    //   209: invokestatic 46	com/tencent/gmtrace/GMTrace:o	(JI)V
    //   212: return
    //   213: aload_0
    //   214: getfield 55	com/tencent/mm/app/d:fvI	Ljava/util/concurrent/locks/ReentrantLock;
    //   217: invokevirtual 164	java/util/concurrent/locks/ReentrantLock:lock	()V
    //   220: aload_0
    //   221: iconst_1
    //   222: putfield 57	com/tencent/mm/app/d:fvJ	Z
    //   225: aload_0
    //   226: getfield 55	com/tencent/mm/app/d:fvI	Ljava/util/concurrent/locks/ReentrantLock;
    //   229: invokevirtual 184	java/util/concurrent/locks/ReentrantLock:unlock	()V
    //   232: getstatic 43	com/tencent/mm/app/d:lock	Ljava/lang/Object;
    //   235: astore_1
    //   236: aload_1
    //   237: monitorenter
    //   238: getstatic 38	com/tencent/mm/app/d:fvH	Z
    //   241: ifne +24 -> 265
    //   244: iconst_1
    //   245: putstatic 38	com/tencent/mm/app/d:fvH	Z
    //   248: ldc 108
    //   250: ldc -37
    //   252: invokestatic 197	com/tencent/mm/sdk/platformtools/v:i	(Ljava/lang/String;Ljava/lang/String;)V
    //   255: aload_0
    //   256: getfield 64	com/tencent/mm/app/d:fvL	Ljava/lang/Runnable;
    //   259: ldc2_w 220
    //   262: invokestatic 227	com/tencent/mm/sdk/platformtools/ae:f	(Ljava/lang/Runnable;J)V
    //   265: aload_1
    //   266: monitorexit
    //   267: ldc2_w 160
    //   270: ldc -94
    //   272: invokestatic 46	com/tencent/gmtrace/GMTrace:o	(JI)V
    //   275: return
    //   276: astore_1
    //   277: aload_0
    //   278: getfield 55	com/tencent/mm/app/d:fvI	Ljava/util/concurrent/locks/ReentrantLock;
    //   281: invokevirtual 184	java/util/concurrent/locks/ReentrantLock:unlock	()V
    //   284: aload_1
    //   285: athrow
    //   286: astore 4
    //   288: aload_1
    //   289: monitorexit
    //   290: aload 4
    //   292: athrow
    // Local variable table:
    //   start	length	slot	name	signature
    //   0	293	0	this	d
    //   18	84	2	bool1	boolean
    //   1	26	3	bool2	boolean
    //   177	11	4	localIntent	android.content.Intent
    //   286	5	4	localObject	Object
    // Exception table:
    //   from	to	target	type
    //   10	17	157	finally
    //   19	26	157	finally
    //   28	40	157	finally
    //   42	77	157	finally
    //   81	109	157	finally
    //   213	225	276	finally
    //   238	265	286	finally
    //   265	267	286	finally
    //   288	290	286	finally
  }
  
  /* Error */
  public final void onServiceConnected(ComponentName paramComponentName, IBinder paramIBinder)
  {
    // Byte code:
    //   0: ldc2_w 234
    //   3: ldc -20
    //   5: invokestatic 36	com/tencent/gmtrace/GMTrace:i	(JI)V
    //   8: ldc 108
    //   10: ldc -18
    //   12: invokestatic 240	com/tencent/mm/sdk/platformtools/v:w	(Ljava/lang/String;Ljava/lang/String;)V
    //   15: getstatic 43	com/tencent/mm/app/d:lock	Ljava/lang/Object;
    //   18: astore_1
    //   19: aload_1
    //   20: monitorenter
    //   21: ldc 108
    //   23: ldc -14
    //   25: invokestatic 197	com/tencent/mm/sdk/platformtools/v:i	(Ljava/lang/String;Ljava/lang/String;)V
    //   28: aload_0
    //   29: getfield 64	com/tencent/mm/app/d:fvL	Ljava/lang/Runnable;
    //   32: invokestatic 246	com/tencent/mm/sdk/platformtools/ae:I	(Ljava/lang/Runnable;)V
    //   35: iconst_0
    //   36: putstatic 38	com/tencent/mm/app/d:fvH	Z
    //   39: aload_1
    //   40: monitorexit
    //   41: aload_2
    //   42: ifnonnull +17 -> 59
    //   45: ldc -8
    //   47: iconst_0
    //   48: invokestatic 254	junit/framework/Assert:assertTrue	(Ljava/lang/String;Z)V
    //   51: ldc -8
    //   53: ldc_w 256
    //   56: invokestatic 260	com/tencent/mm/sdk/a/b:r	(Ljava/lang/String;Ljava/lang/String;)V
    //   59: aload_0
    //   60: getfield 55	com/tencent/mm/app/d:fvI	Ljava/util/concurrent/locks/ReentrantLock;
    //   63: invokevirtual 164	java/util/concurrent/locks/ReentrantLock:lock	()V
    //   66: aload_0
    //   67: iconst_0
    //   68: putfield 57	com/tencent/mm/app/d:fvJ	Z
    //   71: aload_0
    //   72: aload_2
    //   73: putfield 59	com/tencent/mm/app/d:fvK	Landroid/os/IBinder;
    //   76: aload_0
    //   77: getfield 55	com/tencent/mm/app/d:fvI	Ljava/util/concurrent/locks/ReentrantLock;
    //   80: invokevirtual 184	java/util/concurrent/locks/ReentrantLock:unlock	()V
    //   83: new 262	com/tencent/mm/y/p
    //   86: dup
    //   87: aload_2
    //   88: invokestatic 268	com/tencent/mm/network/f$a:B	(Landroid/os/IBinder;)Lcom/tencent/mm/network/f;
    //   91: invokespecial 271	com/tencent/mm/y/p:<init>	(Lcom/tencent/mm/network/f;)V
    //   94: astore_1
    //   95: new 8	com/tencent/mm/app/d$1
    //   98: dup
    //   99: aload_0
    //   100: invokespecial 272	com/tencent/mm/app/d$1:<init>	(Lcom/tencent/mm/app/d;)V
    //   103: astore_2
    //   104: aload_1
    //   105: getfield 276	com/tencent/mm/y/p:hsZ	Lcom/tencent/mm/network/f;
    //   108: aload_2
    //   109: invokeinterface 282 2 0
    //   114: new 10	com/tencent/mm/app/d$2
    //   117: dup
    //   118: aload_0
    //   119: invokespecial 283	com/tencent/mm/app/d$2:<init>	(Lcom/tencent/mm/app/d;)V
    //   122: astore_2
    //   123: aload_1
    //   124: getfield 276	com/tencent/mm/y/p:hsZ	Lcom/tencent/mm/network/f;
    //   127: aload_2
    //   128: invokeinterface 286 2 0
    //   133: invokestatic 292	com/tencent/mm/kernel/h:vJ	()Lcom/tencent/mm/kernel/h;
    //   136: pop
    //   137: invokestatic 296	com/tencent/mm/kernel/h:vH	()Lcom/tencent/mm/kernel/b;
    //   140: astore 7
    //   142: ldc_w 298
    //   145: new 300	java/lang/StringBuilder
    //   148: dup
    //   149: ldc_w 302
    //   152: invokespecial 303	java/lang/StringBuilder:<init>	(Ljava/lang/String;)V
    //   155: aload_1
    //   156: invokevirtual 307	java/lang/StringBuilder:append	(Ljava/lang/Object;)Ljava/lang/StringBuilder;
    //   159: invokevirtual 310	java/lang/StringBuilder:toString	()Ljava/lang/String;
    //   162: invokestatic 240	com/tencent/mm/sdk/platformtools/v:w	(Ljava/lang/String;Ljava/lang/String;)V
    //   165: aload 7
    //   167: getfield 316	com/tencent/mm/kernel/b:gXr	Lcom/tencent/mm/kernel/b$a;
    //   170: aload_1
    //   171: invokevirtual 322	com/tencent/mm/kernel/b$a:b	(Lcom/tencent/mm/network/e;)V
    //   174: aload_1
    //   175: invokeinterface 328 1 0
    //   180: ifnull +20 -> 200
    //   183: aload_1
    //   184: invokeinterface 328 1 0
    //   189: aload 7
    //   191: getfield 332	com/tencent/mm/kernel/b:gXu	Lcom/tencent/mm/network/m;
    //   194: invokeinterface 338 2 0
    //   199: pop
    //   200: aload_1
    //   201: new 340	com/tencent/mm/kernel/b$4
    //   204: dup
    //   205: aload 7
    //   207: invokespecial 343	com/tencent/mm/kernel/b$4:<init>	(Lcom/tencent/mm/kernel/b;)V
    //   210: invokeinterface 346 2 0
    //   215: aload_1
    //   216: invokeinterface 350 1 0
    //   221: astore_2
    //   222: aload_2
    //   223: ifnonnull +278 -> 501
    //   226: ldc_w 298
    //   229: ldc_w 352
    //   232: invokestatic 354	com/tencent/mm/sdk/platformtools/v:f	(Ljava/lang/String;Ljava/lang/String;)V
    //   235: aload 7
    //   237: getfield 358	com/tencent/mm/kernel/b:gXs	Lcom/tencent/mm/y/n;
    //   240: invokevirtual 363	com/tencent/mm/y/n:reset	()V
    //   243: aload 7
    //   245: getfield 358	com/tencent/mm/kernel/b:gXs	Lcom/tencent/mm/y/n;
    //   248: invokevirtual 366	com/tencent/mm/y/n:BU	()V
    //   251: invokestatic 371	com/tencent/mm/u/a:wI	()Z
    //   254: ifeq +94 -> 348
    //   257: invokestatic 292	com/tencent/mm/kernel/h:vJ	()Lcom/tencent/mm/kernel/h;
    //   260: pop
    //   261: invokestatic 375	com/tencent/mm/kernel/h:vG	()Lcom/tencent/mm/kernel/a;
    //   264: getfield 381	com/tencent/mm/kernel/a:gWZ	Lcom/tencent/mm/u/a;
    //   267: ifnull +1348 -> 1615
    //   270: invokestatic 292	com/tencent/mm/kernel/h:vJ	()Lcom/tencent/mm/kernel/h;
    //   273: pop
    //   274: invokestatic 296	com/tencent/mm/kernel/h:vH	()Lcom/tencent/mm/kernel/b;
    //   277: getfield 358	com/tencent/mm/kernel/b:gXs	Lcom/tencent/mm/y/n;
    //   280: getfield 385	com/tencent/mm/y/n:hsI	Lcom/tencent/mm/network/e;
    //   283: ifnull +1332 -> 1615
    //   286: invokestatic 292	com/tencent/mm/kernel/h:vJ	()Lcom/tencent/mm/kernel/h;
    //   289: pop
    //   290: invokestatic 375	com/tencent/mm/kernel/h:vG	()Lcom/tencent/mm/kernel/a;
    //   293: getfield 381	com/tencent/mm/kernel/a:gWZ	Lcom/tencent/mm/u/a;
    //   296: astore_1
    //   297: invokestatic 292	com/tencent/mm/kernel/h:vJ	()Lcom/tencent/mm/kernel/h;
    //   300: pop
    //   301: invokestatic 296	com/tencent/mm/kernel/h:vH	()Lcom/tencent/mm/kernel/b;
    //   304: getfield 358	com/tencent/mm/kernel/b:gXs	Lcom/tencent/mm/y/n;
    //   307: getfield 385	com/tencent/mm/y/n:hsI	Lcom/tencent/mm/network/e;
    //   310: invokeinterface 350 1 0
    //   315: astore_2
    //   316: invokestatic 389	com/tencent/mm/sdk/platformtools/bf:NA	()J
    //   319: lstore 4
    //   321: aload_2
    //   322: ifnonnull +972 -> 1294
    //   325: ldc_w 391
    //   328: ldc_w 393
    //   331: invokestatic 217	com/tencent/mm/sdk/platformtools/v:e	(Ljava/lang/String;Ljava/lang/String;)V
    //   334: getstatic 399	com/tencent/mm/plugin/report/c:oRz	Lcom/tencent/mm/plugin/report/c;
    //   337: ldc2_w 400
    //   340: ldc2_w 402
    //   343: lconst_1
    //   344: iconst_0
    //   345: invokevirtual 406	com/tencent/mm/plugin/report/c:a	(JJJZ)V
    //   348: invokestatic 375	com/tencent/mm/kernel/h:vG	()Lcom/tencent/mm/kernel/a;
    //   351: invokevirtual 409	com/tencent/mm/kernel/a:uV	()Z
    //   354: ifeq +51 -> 405
    //   357: invokestatic 292	com/tencent/mm/kernel/h:vJ	()Lcom/tencent/mm/kernel/h;
    //   360: pop
    //   361: invokestatic 296	com/tencent/mm/kernel/h:vH	()Lcom/tencent/mm/kernel/b;
    //   364: getfield 358	com/tencent/mm/kernel/b:gXs	Lcom/tencent/mm/y/n;
    //   367: ifnull +38 -> 405
    //   370: invokestatic 292	com/tencent/mm/kernel/h:vJ	()Lcom/tencent/mm/kernel/h;
    //   373: pop
    //   374: invokestatic 296	com/tencent/mm/kernel/h:vH	()Lcom/tencent/mm/kernel/b;
    //   377: getfield 358	com/tencent/mm/kernel/b:gXs	Lcom/tencent/mm/y/n;
    //   380: getfield 385	com/tencent/mm/y/n:hsI	Lcom/tencent/mm/network/e;
    //   383: ifnull +22 -> 405
    //   386: invokestatic 292	com/tencent/mm/kernel/h:vJ	()Lcom/tencent/mm/kernel/h;
    //   389: pop
    //   390: invokestatic 296	com/tencent/mm/kernel/h:vH	()Lcom/tencent/mm/kernel/b;
    //   393: getfield 358	com/tencent/mm/kernel/b:gXs	Lcom/tencent/mm/y/n;
    //   396: getfield 385	com/tencent/mm/y/n:hsI	Lcom/tencent/mm/network/e;
    //   399: iconst_1
    //   400: invokeinterface 413 2 0
    //   405: ldc2_w 234
    //   408: ldc -20
    //   410: invokestatic 46	com/tencent/gmtrace/GMTrace:o	(JI)V
    //   413: return
    //   414: astore_2
    //   415: aload_1
    //   416: monitorexit
    //   417: aload_2
    //   418: athrow
    //   419: astore_1
    //   420: aload_0
    //   421: getfield 55	com/tencent/mm/app/d:fvI	Ljava/util/concurrent/locks/ReentrantLock;
    //   424: invokevirtual 184	java/util/concurrent/locks/ReentrantLock:unlock	()V
    //   427: aload_1
    //   428: athrow
    //   429: astore_2
    //   430: ldc_w 415
    //   433: ldc_w 417
    //   436: iconst_1
    //   437: anewarray 4	java/lang/Object
    //   440: dup
    //   441: iconst_0
    //   442: aload_2
    //   443: invokestatic 421	com/tencent/mm/sdk/platformtools/bf:g	(Ljava/lang/Throwable;)Ljava/lang/String;
    //   446: aastore
    //   447: invokestatic 423	com/tencent/mm/sdk/platformtools/v:e	(Ljava/lang/String;Ljava/lang/String;[Ljava/lang/Object;)V
    //   450: goto -336 -> 114
    //   453: astore_2
    //   454: ldc_w 415
    //   457: ldc_w 417
    //   460: iconst_1
    //   461: anewarray 4	java/lang/Object
    //   464: dup
    //   465: iconst_0
    //   466: aload_2
    //   467: invokestatic 421	com/tencent/mm/sdk/platformtools/bf:g	(Ljava/lang/Throwable;)Ljava/lang/String;
    //   470: aastore
    //   471: invokestatic 423	com/tencent/mm/sdk/platformtools/v:e	(Ljava/lang/String;Ljava/lang/String;[Ljava/lang/Object;)V
    //   474: goto -341 -> 133
    //   477: astore_2
    //   478: ldc_w 298
    //   481: ldc_w 417
    //   484: iconst_1
    //   485: anewarray 4	java/lang/Object
    //   488: dup
    //   489: iconst_0
    //   490: aload_2
    //   491: invokestatic 421	com/tencent/mm/sdk/platformtools/bf:g	(Ljava/lang/Throwable;)Ljava/lang/String;
    //   494: aastore
    //   495: invokestatic 423	com/tencent/mm/sdk/platformtools/v:e	(Ljava/lang/String;Ljava/lang/String;[Ljava/lang/Object;)V
    //   498: goto -298 -> 200
    //   501: new 425	com/tencent/mm/kernel/b$5
    //   504: dup
    //   505: aload 7
    //   507: invokespecial 426	com/tencent/mm/kernel/b$5:<init>	(Lcom/tencent/mm/kernel/b;)V
    //   510: invokestatic 429	com/tencent/mm/sdk/a/b:a	(Lcom/tencent/mm/sdk/a/a;)V
    //   513: invokestatic 292	com/tencent/mm/kernel/h:vJ	()Lcom/tencent/mm/kernel/h;
    //   516: pop
    //   517: invokestatic 433	com/tencent/mm/kernel/h:vI	()Lcom/tencent/mm/kernel/e;
    //   520: getfield 439	com/tencent/mm/kernel/e:gXM	Lcom/tencent/mm/storage/s;
    //   523: astore 13
    //   525: new 300	java/lang/StringBuilder
    //   528: dup
    //   529: ldc_w 441
    //   532: invokespecial 303	java/lang/StringBuilder:<init>	(Ljava/lang/String;)V
    //   535: invokestatic 445	com/tencent/mm/sdk/platformtools/bf:bJP	()Lcom/tencent/mm/sdk/platformtools/ag;
    //   538: invokevirtual 307	java/lang/StringBuilder:append	(Ljava/lang/Object;)Ljava/lang/StringBuilder;
    //   541: invokevirtual 310	java/lang/StringBuilder:toString	()Ljava/lang/String;
    //   544: astore 8
    //   546: aload 13
    //   548: ifnull +485 -> 1033
    //   551: iconst_1
    //   552: istore 6
    //   554: aload 8
    //   556: iload 6
    //   558: invokestatic 254	junit/framework/Assert:assertTrue	(Ljava/lang/String;Z)V
    //   561: aload 13
    //   563: bipush 47
    //   565: invokevirtual 451	com/tencent/mm/storage/s:yv	(I)I
    //   568: istore_3
    //   569: aload 13
    //   571: iconst_2
    //   572: invokevirtual 455	com/tencent/mm/storage/s:get	(I)Ljava/lang/Object;
    //   575: checkcast 129	java/lang/String
    //   578: astore 8
    //   580: aload 13
    //   582: iconst_3
    //   583: invokevirtual 455	com/tencent/mm/storage/s:get	(I)Ljava/lang/Object;
    //   586: checkcast 129	java/lang/String
    //   589: astore 9
    //   591: aload 13
    //   593: bipush 6
    //   595: invokevirtual 455	com/tencent/mm/storage/s:get	(I)Ljava/lang/Object;
    //   598: checkcast 129	java/lang/String
    //   601: astore 10
    //   603: aload 13
    //   605: bipush 7
    //   607: invokevirtual 455	com/tencent/mm/storage/s:get	(I)Ljava/lang/Object;
    //   610: checkcast 129	java/lang/String
    //   613: astore 11
    //   615: aload 13
    //   617: bipush 25
    //   619: invokevirtual 455	com/tencent/mm/storage/s:get	(I)Ljava/lang/Object;
    //   622: checkcast 129	java/lang/String
    //   625: astore 12
    //   627: aload 13
    //   629: bipush 24
    //   631: invokevirtual 455	com/tencent/mm/storage/s:get	(I)Ljava/lang/Object;
    //   634: checkcast 129	java/lang/String
    //   637: astore 13
    //   639: aload 10
    //   641: aload 11
    //   643: invokestatic 461	com/tencent/mm/protocal/n:et	(Ljava/lang/String;Ljava/lang/String;)Lcom/tencent/mm/protocal/n$a;
    //   646: astore 14
    //   648: ldc_w 298
    //   651: ldc_w 463
    //   654: bipush 7
    //   656: anewarray 4	java/lang/Object
    //   659: dup
    //   660: iconst_0
    //   661: aload 13
    //   663: aastore
    //   664: dup
    //   665: iconst_1
    //   666: aload 12
    //   668: aastore
    //   669: dup
    //   670: iconst_2
    //   671: aload 8
    //   673: aastore
    //   674: dup
    //   675: iconst_3
    //   676: aload 9
    //   678: aastore
    //   679: dup
    //   680: iconst_4
    //   681: aload 10
    //   683: aastore
    //   684: dup
    //   685: iconst_5
    //   686: aload 11
    //   688: aastore
    //   689: dup
    //   690: bipush 6
    //   692: iload_3
    //   693: invokestatic 145	java/lang/Integer:valueOf	(I)Ljava/lang/Integer;
    //   696: aastore
    //   697: invokestatic 466	com/tencent/mm/sdk/platformtools/v:d	(Ljava/lang/String;Ljava/lang/String;[Ljava/lang/Object;)V
    //   700: new 300	java/lang/StringBuilder
    //   703: dup
    //   704: ldc_w 468
    //   707: invokespecial 303	java/lang/StringBuilder:<init>	(Ljava/lang/String;)V
    //   710: invokestatic 445	com/tencent/mm/sdk/platformtools/bf:bJP	()Lcom/tencent/mm/sdk/platformtools/ag;
    //   713: invokevirtual 307	java/lang/StringBuilder:append	(Ljava/lang/Object;)Ljava/lang/StringBuilder;
    //   716: invokevirtual 310	java/lang/StringBuilder:toString	()Ljava/lang/String;
    //   719: iconst_1
    //   720: invokestatic 254	junit/framework/Assert:assertTrue	(Ljava/lang/String;Z)V
    //   723: aload_1
    //   724: iconst_0
    //   725: aload 8
    //   727: aload 9
    //   729: aload 14
    //   731: getfield 474	com/tencent/mm/protocal/n$a:sYc	[I
    //   734: aload 14
    //   736: getfield 477	com/tencent/mm/protocal/n$a:sYd	[I
    //   739: aload 14
    //   741: getfield 480	com/tencent/mm/protocal/n$a:sYe	I
    //   744: aload 14
    //   746: getfield 483	com/tencent/mm/protocal/n$a:sYf	I
    //   749: aload 13
    //   751: aload 12
    //   753: invokeinterface 486 10 0
    //   758: iload_3
    //   759: iconst_1
    //   760: iand
    //   761: ifne +278 -> 1039
    //   764: iconst_1
    //   765: istore 6
    //   767: aload_1
    //   768: iload 6
    //   770: invokeinterface 489 2 0
    //   775: invokestatic 292	com/tencent/mm/kernel/h:vJ	()Lcom/tencent/mm/kernel/h;
    //   778: pop
    //   779: invokestatic 375	com/tencent/mm/kernel/h:vG	()Lcom/tencent/mm/kernel/a;
    //   782: pop
    //   783: new 300	java/lang/StringBuilder
    //   786: dup
    //   787: ldc_w 491
    //   790: invokespecial 303	java/lang/StringBuilder:<init>	(Ljava/lang/String;)V
    //   793: invokestatic 445	com/tencent/mm/sdk/platformtools/bf:bJP	()Lcom/tencent/mm/sdk/platformtools/ag;
    //   796: invokevirtual 307	java/lang/StringBuilder:append	(Ljava/lang/Object;)Ljava/lang/StringBuilder;
    //   799: invokevirtual 310	java/lang/StringBuilder:toString	()Ljava/lang/String;
    //   802: astore 8
    //   804: aload_2
    //   805: ifnull +240 -> 1045
    //   808: iconst_1
    //   809: istore 6
    //   811: aload 8
    //   813: iload 6
    //   815: invokestatic 254	junit/framework/Assert:assertTrue	(Ljava/lang/String;Z)V
    //   818: invokestatic 375	com/tencent/mm/kernel/h:vG	()Lcom/tencent/mm/kernel/a;
    //   821: invokevirtual 409	com/tencent/mm/kernel/a:uV	()Z
    //   824: ifeq +12 -> 836
    //   827: invokestatic 375	com/tencent/mm/kernel/h:vG	()Lcom/tencent/mm/kernel/a;
    //   830: getfield 494	com/tencent/mm/kernel/a:gXf	Z
    //   833: ifne +263 -> 1096
    //   836: ldc_w 298
    //   839: ldc_w 496
    //   842: iconst_2
    //   843: anewarray 4	java/lang/Object
    //   846: dup
    //   847: iconst_0
    //   848: invokestatic 375	com/tencent/mm/kernel/h:vG	()Lcom/tencent/mm/kernel/a;
    //   851: invokevirtual 409	com/tencent/mm/kernel/a:uV	()Z
    //   854: invokestatic 176	java/lang/Boolean:valueOf	(Z)Ljava/lang/Boolean;
    //   857: aastore
    //   858: dup
    //   859: iconst_1
    //   860: invokestatic 375	com/tencent/mm/kernel/h:vG	()Lcom/tencent/mm/kernel/a;
    //   863: getfield 494	com/tencent/mm/kernel/a:gXf	Z
    //   866: invokestatic 176	java/lang/Boolean:valueOf	(Z)Ljava/lang/Boolean;
    //   869: aastore
    //   870: invokestatic 181	com/tencent/mm/sdk/platformtools/v:w	(Ljava/lang/String;Ljava/lang/String;[Ljava/lang/Object;)V
    //   873: getstatic 399	com/tencent/mm/plugin/report/c:oRz	Lcom/tencent/mm/plugin/report/c;
    //   876: astore 8
    //   878: invokestatic 375	com/tencent/mm/kernel/h:vG	()Lcom/tencent/mm/kernel/a;
    //   881: invokevirtual 409	com/tencent/mm/kernel/a:uV	()Z
    //   884: ifeq +167 -> 1051
    //   887: ldc2_w 497
    //   890: lstore 4
    //   892: aload 8
    //   894: ldc2_w 499
    //   897: lload 4
    //   899: lconst_1
    //   900: iconst_0
    //   901: invokevirtual 406	com/tencent/mm/plugin/report/c:a	(JJJZ)V
    //   904: aload_2
    //   905: invokeinterface 503 1 0
    //   910: aload_1
    //   911: invokeinterface 504 1 0
    //   916: aload 7
    //   918: getfield 358	com/tencent/mm/kernel/b:gXs	Lcom/tencent/mm/y/n;
    //   921: aload_1
    //   922: invokevirtual 506	com/tencent/mm/y/n:d	(Lcom/tencent/mm/network/e;)V
    //   925: new 508	com/tencent/mm/kernel/b$6
    //   928: dup
    //   929: aload 7
    //   931: invokespecial 509	com/tencent/mm/kernel/b$6:<init>	(Lcom/tencent/mm/kernel/b;)V
    //   934: invokestatic 514	com/tencent/mm/network/b:a	(Lcom/tencent/mm/network/b$a;)V
    //   937: invokestatic 517	com/tencent/mm/kernel/a:uH	()I
    //   940: aload_2
    //   941: invokeinterface 518 1 0
    //   946: if_icmpeq +113 -> 1059
    //   949: getstatic 399	com/tencent/mm/plugin/report/c:oRz	Lcom/tencent/mm/plugin/report/c;
    //   952: ldc2_w 499
    //   955: ldc2_w 519
    //   958: lconst_1
    //   959: iconst_0
    //   960: invokevirtual 406	com/tencent/mm/plugin/report/c:a	(JJJZ)V
    //   963: ldc_w 298
    //   966: ldc_w 522
    //   969: iconst_4
    //   970: anewarray 4	java/lang/Object
    //   973: dup
    //   974: iconst_0
    //   975: aload_2
    //   976: invokeinterface 518 1 0
    //   981: invokestatic 145	java/lang/Integer:valueOf	(I)Ljava/lang/Integer;
    //   984: aastore
    //   985: dup
    //   986: iconst_1
    //   987: invokestatic 517	com/tencent/mm/kernel/a:uH	()I
    //   990: invokestatic 145	java/lang/Integer:valueOf	(I)Ljava/lang/Integer;
    //   993: aastore
    //   994: dup
    //   995: iconst_2
    //   996: invokestatic 375	com/tencent/mm/kernel/h:vG	()Lcom/tencent/mm/kernel/a;
    //   999: invokevirtual 409	com/tencent/mm/kernel/a:uV	()Z
    //   1002: invokestatic 176	java/lang/Boolean:valueOf	(Z)Ljava/lang/Boolean;
    //   1005: aastore
    //   1006: dup
    //   1007: iconst_3
    //   1008: invokestatic 375	com/tencent/mm/kernel/h:vG	()Lcom/tencent/mm/kernel/a;
    //   1011: getfield 494	com/tencent/mm/kernel/a:gXf	Z
    //   1014: invokestatic 176	java/lang/Boolean:valueOf	(Z)Ljava/lang/Boolean;
    //   1017: aastore
    //   1018: invokestatic 181	com/tencent/mm/sdk/platformtools/v:w	(Ljava/lang/String;Ljava/lang/String;[Ljava/lang/Object;)V
    //   1021: aload_2
    //   1022: invokestatic 517	com/tencent/mm/kernel/a:uH	()I
    //   1025: invokeinterface 526 2 0
    //   1030: goto -779 -> 251
    //   1033: iconst_0
    //   1034: istore 6
    //   1036: goto -482 -> 554
    //   1039: iconst_0
    //   1040: istore 6
    //   1042: goto -275 -> 767
    //   1045: iconst_0
    //   1046: istore 6
    //   1048: goto -237 -> 811
    //   1051: ldc2_w 527
    //   1054: lstore 4
    //   1056: goto -164 -> 892
    //   1059: ldc_w 298
    //   1062: ldc_w 530
    //   1065: iconst_2
    //   1066: anewarray 4	java/lang/Object
    //   1069: dup
    //   1070: iconst_0
    //   1071: aload_2
    //   1072: invokeinterface 518 1 0
    //   1077: invokestatic 145	java/lang/Integer:valueOf	(I)Ljava/lang/Integer;
    //   1080: aastore
    //   1081: dup
    //   1082: iconst_1
    //   1083: invokestatic 517	com/tencent/mm/kernel/a:uH	()I
    //   1086: invokestatic 145	java/lang/Integer:valueOf	(I)Ljava/lang/Integer;
    //   1089: aastore
    //   1090: invokestatic 148	com/tencent/mm/sdk/platformtools/v:i	(Ljava/lang/String;Ljava/lang/String;[Ljava/lang/Object;)V
    //   1093: goto -842 -> 251
    //   1096: aload 7
    //   1098: getfield 358	com/tencent/mm/kernel/b:gXs	Lcom/tencent/mm/y/n;
    //   1101: aload_1
    //   1102: invokevirtual 506	com/tencent/mm/y/n:d	(Lcom/tencent/mm/network/e;)V
    //   1105: new 532	com/tencent/mm/kernel/b$7
    //   1108: dup
    //   1109: aload 7
    //   1111: invokespecial 533	com/tencent/mm/kernel/b$7:<init>	(Lcom/tencent/mm/kernel/b;)V
    //   1114: invokestatic 514	com/tencent/mm/network/b:a	(Lcom/tencent/mm/network/b$a;)V
    //   1117: ldc_w 298
    //   1120: ldc_w 535
    //   1123: iconst_3
    //   1124: anewarray 4	java/lang/Object
    //   1127: dup
    //   1128: iconst_0
    //   1129: invokestatic 517	com/tencent/mm/kernel/a:uH	()I
    //   1132: invokestatic 145	java/lang/Integer:valueOf	(I)Ljava/lang/Integer;
    //   1135: aastore
    //   1136: dup
    //   1137: iconst_1
    //   1138: aload_2
    //   1139: invokeinterface 518 1 0
    //   1144: invokestatic 145	java/lang/Integer:valueOf	(I)Ljava/lang/Integer;
    //   1147: aastore
    //   1148: dup
    //   1149: iconst_2
    //   1150: invokestatic 375	com/tencent/mm/kernel/h:vG	()Lcom/tencent/mm/kernel/a;
    //   1153: invokevirtual 409	com/tencent/mm/kernel/a:uV	()Z
    //   1156: invokestatic 176	java/lang/Boolean:valueOf	(Z)Ljava/lang/Boolean;
    //   1159: aastore
    //   1160: invokestatic 148	com/tencent/mm/sdk/platformtools/v:i	(Ljava/lang/String;Ljava/lang/String;[Ljava/lang/Object;)V
    //   1163: invokestatic 517	com/tencent/mm/kernel/a:uH	()I
    //   1166: aload_2
    //   1167: invokeinterface 518 1 0
    //   1172: if_icmpeq -921 -> 251
    //   1175: ldc_w 298
    //   1178: new 300	java/lang/StringBuilder
    //   1181: dup
    //   1182: ldc_w 537
    //   1185: invokespecial 303	java/lang/StringBuilder:<init>	(Ljava/lang/String;)V
    //   1188: aload_2
    //   1189: invokeinterface 518 1 0
    //   1194: invokevirtual 540	java/lang/StringBuilder:append	(I)Ljava/lang/StringBuilder;
    //   1197: invokevirtual 310	java/lang/StringBuilder:toString	()Ljava/lang/String;
    //   1200: invokestatic 240	com/tencent/mm/sdk/platformtools/v:w	(Ljava/lang/String;Ljava/lang/String;)V
    //   1203: new 300	java/lang/StringBuilder
    //   1206: dup
    //   1207: ldc_w 542
    //   1210: invokespecial 303	java/lang/StringBuilder:<init>	(Ljava/lang/String;)V
    //   1213: invokestatic 445	com/tencent/mm/sdk/platformtools/bf:bJP	()Lcom/tencent/mm/sdk/platformtools/ag;
    //   1216: invokevirtual 307	java/lang/StringBuilder:append	(Ljava/lang/Object;)Ljava/lang/StringBuilder;
    //   1219: invokevirtual 310	java/lang/StringBuilder:toString	()Ljava/lang/String;
    //   1222: astore_1
    //   1223: invokestatic 292	com/tencent/mm/kernel/h:vJ	()Lcom/tencent/mm/kernel/h;
    //   1226: pop
    //   1227: invokestatic 433	com/tencent/mm/kernel/h:vI	()Lcom/tencent/mm/kernel/e;
    //   1230: invokevirtual 546	com/tencent/mm/kernel/e:vr	()Lcom/tencent/mm/storage/t;
    //   1233: ifnull +55 -> 1288
    //   1236: iconst_1
    //   1237: istore 6
    //   1239: aload_1
    //   1240: iload 6
    //   1242: invokestatic 254	junit/framework/Assert:assertTrue	(Ljava/lang/String;Z)V
    //   1245: invokestatic 292	com/tencent/mm/kernel/h:vJ	()Lcom/tencent/mm/kernel/h;
    //   1248: pop
    //   1249: invokestatic 433	com/tencent/mm/kernel/h:vI	()Lcom/tencent/mm/kernel/e;
    //   1252: invokevirtual 546	com/tencent/mm/kernel/e:vr	()Lcom/tencent/mm/storage/t;
    //   1255: iconst_2
    //   1256: aconst_null
    //   1257: invokevirtual 551	com/tencent/mm/storage/t:get	(ILjava/lang/Object;)Ljava/lang/Object;
    //   1260: checkcast 129	java/lang/String
    //   1263: astore_1
    //   1264: invokestatic 517	com/tencent/mm/kernel/a:uH	()I
    //   1267: istore_3
    //   1268: aload_2
    //   1269: iconst_0
    //   1270: newarray <illegal type>
    //   1272: iload_3
    //   1273: invokeinterface 554 3 0
    //   1278: aload_2
    //   1279: aload_1
    //   1280: invokeinterface 557 2 0
    //   1285: goto -1034 -> 251
    //   1288: iconst_0
    //   1289: istore 6
    //   1291: goto -52 -> 1239
    //   1294: ldc_w 391
    //   1297: ldc_w 559
    //   1300: iconst_2
    //   1301: anewarray 4	java/lang/Object
    //   1304: dup
    //   1305: iconst_0
    //   1306: aload_2
    //   1307: invokeinterface 562 1 0
    //   1312: invokestatic 176	java/lang/Boolean:valueOf	(Z)Ljava/lang/Boolean;
    //   1315: aastore
    //   1316: dup
    //   1317: iconst_1
    //   1318: aload_1
    //   1319: invokevirtual 565	com/tencent/mm/u/a:wH	()I
    //   1322: invokestatic 145	java/lang/Integer:valueOf	(I)Ljava/lang/Integer;
    //   1325: aastore
    //   1326: invokestatic 148	com/tencent/mm/sdk/platformtools/v:i	(Ljava/lang/String;Ljava/lang/String;[Ljava/lang/Object;)V
    //   1329: aload_2
    //   1330: invokeinterface 562 1 0
    //   1335: ifeq +128 -> 1463
    //   1338: aload_1
    //   1339: invokevirtual 565	com/tencent/mm/u/a:wH	()I
    //   1342: ifle +95 -> 1437
    //   1345: getstatic 399	com/tencent/mm/plugin/report/c:oRz	Lcom/tencent/mm/plugin/report/c;
    //   1348: ldc2_w 400
    //   1351: ldc2_w 566
    //   1354: lconst_1
    //   1355: iconst_0
    //   1356: invokevirtual 406	com/tencent/mm/plugin/report/c:a	(JJJZ)V
    //   1359: ldc_w 391
    //   1362: ldc_w 569
    //   1365: invokestatic 217	com/tencent/mm/sdk/platformtools/v:e	(Ljava/lang/String;Ljava/lang/String;)V
    //   1368: aload_1
    //   1369: aconst_null
    //   1370: putfield 573	com/tencent/mm/u/a:hko	[B
    //   1373: aload_1
    //   1374: aload_2
    //   1375: invokeinterface 577 1 0
    //   1380: putfield 573	com/tencent/mm/u/a:hko	[B
    //   1383: getstatic 399	com/tencent/mm/plugin/report/c:oRz	Lcom/tencent/mm/plugin/report/c;
    //   1386: astore_2
    //   1387: aload_1
    //   1388: invokevirtual 565	com/tencent/mm/u/a:wH	()I
    //   1391: ifle +271 -> 1662
    //   1394: ldc2_w 578
    //   1397: lstore 4
    //   1399: aload_2
    //   1400: ldc2_w 400
    //   1403: lload 4
    //   1405: lconst_1
    //   1406: iconst_0
    //   1407: invokevirtual 406	com/tencent/mm/plugin/report/c:a	(JJJZ)V
    //   1410: goto -1062 -> 348
    //   1413: astore_1
    //   1414: ldc_w 391
    //   1417: ldc_w 581
    //   1420: iconst_1
    //   1421: anewarray 4	java/lang/Object
    //   1424: dup
    //   1425: iconst_0
    //   1426: aload_1
    //   1427: invokestatic 421	com/tencent/mm/sdk/platformtools/bf:g	(Ljava/lang/Throwable;)Ljava/lang/String;
    //   1430: aastore
    //   1431: invokestatic 423	com/tencent/mm/sdk/platformtools/v:e	(Ljava/lang/String;Ljava/lang/String;[Ljava/lang/Object;)V
    //   1434: goto -1086 -> 348
    //   1437: ldc_w 391
    //   1440: ldc_w 583
    //   1443: invokestatic 240	com/tencent/mm/sdk/platformtools/v:w	(Ljava/lang/String;Ljava/lang/String;)V
    //   1446: getstatic 399	com/tencent/mm/plugin/report/c:oRz	Lcom/tencent/mm/plugin/report/c;
    //   1449: ldc2_w 400
    //   1452: ldc2_w 584
    //   1455: lconst_1
    //   1456: iconst_0
    //   1457: invokevirtual 406	com/tencent/mm/plugin/report/c:a	(JJJZ)V
    //   1460: goto -87 -> 1373
    //   1463: aload_1
    //   1464: invokevirtual 565	com/tencent/mm/u/a:wH	()I
    //   1467: ifgt +40 -> 1507
    //   1470: getstatic 399	com/tencent/mm/plugin/report/c:oRz	Lcom/tencent/mm/plugin/report/c;
    //   1473: ldc2_w 400
    //   1476: ldc2_w 586
    //   1479: lconst_1
    //   1480: iconst_0
    //   1481: invokevirtual 406	com/tencent/mm/plugin/report/c:a	(JJJZ)V
    //   1484: ldc_w 391
    //   1487: ldc_w 589
    //   1490: iconst_1
    //   1491: anewarray 4	java/lang/Object
    //   1494: dup
    //   1495: iconst_0
    //   1496: aload_1
    //   1497: invokevirtual 590	java/lang/Object:toString	()Ljava/lang/String;
    //   1500: aastore
    //   1501: invokestatic 181	com/tencent/mm/sdk/platformtools/v:w	(Ljava/lang/String;Ljava/lang/String;[Ljava/lang/Object;)V
    //   1504: goto -1156 -> 348
    //   1507: aload_2
    //   1508: aload_1
    //   1509: getfield 573	com/tencent/mm/u/a:hko	[B
    //   1512: invokeinterface 594 2 0
    //   1517: istore_3
    //   1518: ldc_w 391
    //   1521: ldc_w 596
    //   1524: iconst_3
    //   1525: anewarray 4	java/lang/Object
    //   1528: dup
    //   1529: iconst_0
    //   1530: iload_3
    //   1531: invokestatic 145	java/lang/Integer:valueOf	(I)Ljava/lang/Integer;
    //   1534: aastore
    //   1535: dup
    //   1536: iconst_1
    //   1537: lload 4
    //   1539: invokestatic 600	com/tencent/mm/sdk/platformtools/bf:aA	(J)J
    //   1542: invokestatic 605	java/lang/Long:valueOf	(J)Ljava/lang/Long;
    //   1545: aastore
    //   1546: dup
    //   1547: iconst_2
    //   1548: aload_1
    //   1549: invokevirtual 565	com/tencent/mm/u/a:wH	()I
    //   1552: invokestatic 145	java/lang/Integer:valueOf	(I)Ljava/lang/Integer;
    //   1555: aastore
    //   1556: invokestatic 148	com/tencent/mm/sdk/platformtools/v:i	(Ljava/lang/String;Ljava/lang/String;[Ljava/lang/Object;)V
    //   1559: iload_3
    //   1560: ifeq +47 -> 1607
    //   1563: ldc_w 391
    //   1566: ldc_w 607
    //   1569: iconst_1
    //   1570: anewarray 4	java/lang/Object
    //   1573: dup
    //   1574: iconst_0
    //   1575: iload_3
    //   1576: invokestatic 145	java/lang/Integer:valueOf	(I)Ljava/lang/Integer;
    //   1579: aastore
    //   1580: invokestatic 423	com/tencent/mm/sdk/platformtools/v:e	(Ljava/lang/String;Ljava/lang/String;[Ljava/lang/Object;)V
    //   1583: aload_1
    //   1584: aconst_null
    //   1585: putfield 573	com/tencent/mm/u/a:hko	[B
    //   1588: getstatic 399	com/tencent/mm/plugin/report/c:oRz	Lcom/tencent/mm/plugin/report/c;
    //   1591: ldc2_w 400
    //   1594: iload_3
    //   1595: bipush 20
    //   1597: iadd
    //   1598: i2l
    //   1599: lconst_1
    //   1600: iconst_0
    //   1601: invokevirtual 406	com/tencent/mm/plugin/report/c:a	(JJJZ)V
    //   1604: goto -1256 -> 348
    //   1607: aload_1
    //   1608: lconst_0
    //   1609: putfield 611	com/tencent/mm/u/a:hkp	J
    //   1612: goto -24 -> 1588
    //   1615: invokestatic 292	com/tencent/mm/kernel/h:vJ	()Lcom/tencent/mm/kernel/h;
    //   1618: pop
    //   1619: invokestatic 375	com/tencent/mm/kernel/h:vG	()Lcom/tencent/mm/kernel/a;
    //   1622: getfield 381	com/tencent/mm/kernel/a:gWZ	Lcom/tencent/mm/u/a;
    //   1625: astore_1
    //   1626: invokestatic 292	com/tencent/mm/kernel/h:vJ	()Lcom/tencent/mm/kernel/h;
    //   1629: pop
    //   1630: ldc_w 391
    //   1633: ldc_w 613
    //   1636: iconst_2
    //   1637: anewarray 4	java/lang/Object
    //   1640: dup
    //   1641: iconst_0
    //   1642: aload_1
    //   1643: aastore
    //   1644: dup
    //   1645: iconst_1
    //   1646: invokestatic 296	com/tencent/mm/kernel/h:vH	()Lcom/tencent/mm/kernel/b;
    //   1649: getfield 358	com/tencent/mm/kernel/b:gXs	Lcom/tencent/mm/y/n;
    //   1652: getfield 385	com/tencent/mm/y/n:hsI	Lcom/tencent/mm/network/e;
    //   1655: aastore
    //   1656: invokestatic 148	com/tencent/mm/sdk/platformtools/v:i	(Ljava/lang/String;Ljava/lang/String;[Ljava/lang/Object;)V
    //   1659: goto -1311 -> 348
    //   1662: ldc2_w 614
    //   1665: lstore 4
    //   1667: goto -268 -> 1399
    // Local variable table:
    //   start	length	slot	name	signature
    //   0	1670	0	this	d
    //   0	1670	1	paramComponentName	ComponentName
    //   0	1670	2	paramIBinder	IBinder
    //   568	1030	3	i	int
    //   319	1347	4	l	long
    //   552	738	6	bool	boolean
    //   140	970	7	localb	b
    //   544	349	8	localObject1	Object
    //   589	139	9	str1	String
    //   601	81	10	str2	String
    //   613	74	11	str3	String
    //   625	127	12	str4	String
    //   523	227	13	localObject2	Object
    //   646	99	14	locala	com.tencent.mm.protocal.n.a
    // Exception table:
    //   from	to	target	type
    //   21	41	414	finally
    //   415	417	414	finally
    //   59	76	419	finally
    //   104	114	429	java/lang/Exception
    //   123	133	453	java/lang/Exception
    //   174	200	477	android/os/RemoteException
    //   257	321	1413	java/lang/Throwable
    //   325	348	1413	java/lang/Throwable
    //   1294	1373	1413	java/lang/Throwable
    //   1373	1394	1413	java/lang/Throwable
    //   1399	1410	1413	java/lang/Throwable
    //   1437	1460	1413	java/lang/Throwable
    //   1463	1504	1413	java/lang/Throwable
    //   1507	1559	1413	java/lang/Throwable
    //   1563	1588	1413	java/lang/Throwable
    //   1588	1604	1413	java/lang/Throwable
    //   1607	1612	1413	java/lang/Throwable
    //   1615	1659	1413	java/lang/Throwable
  }
  
  public final void onServiceDisconnected(ComponentName paramComponentName)
  {
    GMTrace.i(13713562140672L, 102174);
    v.w("MicroMsg.CoreServiceConnection", "onServiceDisconnected ");
    try
    {
      this.fvI.lock();
      this.fvJ = false;
      this.fvK = null;
      this.fvI.unlock();
      h.vG();
      if ((a.uU()) && (!a.uP()))
      {
        h.vJ();
        h.vH().gXs.BT();
        ad(aa.getContext());
        GMTrace.o(13713562140672L, 102174);
        return;
      }
    }
    finally
    {
      this.fvI.unlock();
    }
    h.vJ();
    h.vH().gXs.BU();
    h.vJ();
    h.vH().gXs.reset();
    GMTrace.o(13713562140672L, 102174);
  }
}


/* Location:              /home/chengjian/weinxin/weinxin_1100/classes.jar!/com/tencent/mm/app/d.class
 * Java compiler version: 6 (50.0)
 * JD-Core Version:       0.7.1
 */