package com.google.android.gms.ads.internal.w.b;

import android.content.Context;
import com.google.android.gms.ads.internal.q.a.a;
import com.google.android.gms.ads.internal.util.e;
import com.google.android.gms.ads.internal.w.ad;
import java.io.File;
import java.text.DecimalFormat;
import java.util.Collections;
import java.util.HashSet;
import java.util.Set;

@a
public final class t
  extends k
{
  private static final DecimalFormat d = new DecimalFormat("#,###");
  private static final Set g = Collections.synchronizedSet(new HashSet());
  private boolean e;
  private File f;
  
  public t(ad paramad)
  {
    super(paramad);
    paramad = this.a.getCacheDir();
    if (paramad == null) {
      e.e("Context.getCacheDir() returned null");
    }
    do
    {
      return;
      this.f = new File(paramad, "admobVideoStreams");
      if ((!this.f.isDirectory()) && (!this.f.mkdirs()))
      {
        paramad = String.valueOf(this.f.getAbsolutePath());
        if (paramad.length() == 0) {}
        for (paramad = new String("Could not create preload cache directory at ");; paramad = "Could not create preload cache directory at ".concat(paramad))
        {
          e.e(paramad);
          this.f = null;
          return;
        }
      }
    } while ((this.f.setReadable(true, false)) && (this.f.setExecutable(true, false)));
    paramad = String.valueOf(this.f.getAbsolutePath());
    if (paramad.length() == 0) {}
    for (paramad = new String("Could not set cache file permissions at ");; paramad = "Could not set cache file permissions at ".concat(paramad))
    {
      e.e(paramad);
      this.f = null;
      return;
    }
  }
  
  private final File a(File paramFile)
  {
    return new File(this.f, String.valueOf(paramFile.getName()).concat(".done"));
  }
  
  public final void a()
  {
    this.e = true;
  }
  
  /* Error */
  public final boolean a(String paramString)
  {
    // Byte code:
    //   0: aload_0
    //   1: getfield 66	com/google/android/gms/ads/internal/w/b/t:f	Ljava/io/File;
    //   4: ifnull +1543 -> 1547
    //   7: aload_0
    //   8: getfield 66	com/google/android/gms/ads/internal/w/b/t:f	Ljava/io/File;
    //   11: astore 12
    //   13: aload 12
    //   15: ifnull +58 -> 73
    //   18: aload 12
    //   20: invokevirtual 122	java/io/File:listFiles	()[Ljava/io/File;
    //   23: astore 12
    //   25: aload 12
    //   27: arraylength
    //   28: istore 5
    //   30: iconst_0
    //   31: istore_2
    //   32: iconst_0
    //   33: istore_3
    //   34: iload_3
    //   35: iload 5
    //   37: if_icmpge +1949 -> 1986
    //   40: iload_2
    //   41: istore 4
    //   43: aload 12
    //   45: iload_3
    //   46: aaload
    //   47: invokevirtual 107	java/io/File:getName	()Ljava/lang/String;
    //   50: ldc 109
    //   52: invokevirtual 125	java/lang/String:endsWith	(Ljava/lang/String;)Z
    //   55: ifne +8 -> 63
    //   58: iload_2
    //   59: iconst_1
    //   60: iadd
    //   61: istore 4
    //   63: iload_3
    //   64: iconst_1
    //   65: iadd
    //   66: istore_3
    //   67: iload 4
    //   69: istore_2
    //   70: goto -36 -> 34
    //   73: iconst_0
    //   74: istore_2
    //   75: iload_2
    //   76: getstatic 131	com/google/android/gms/ads/internal/f/n:co	Lcom/google/android/gms/ads/internal/f/c;
    //   79: invokevirtual 136	com/google/android/gms/ads/internal/f/c:a	()Ljava/lang/Object;
    //   82: checkcast 138	java/lang/Integer
    //   85: invokevirtual 141	java/lang/Integer:intValue	()I
    //   88: if_icmpgt +1290 -> 1378
    //   91: aload_0
    //   92: aload_1
    //   93: invokevirtual 144	com/google/android/gms/ads/internal/w/b/k:b	(Ljava/lang/String;)Ljava/lang/String;
    //   96: astore 12
    //   98: new 59	java/io/File
    //   101: dup
    //   102: aload_0
    //   103: getfield 66	com/google/android/gms/ads/internal/w/b/t:f	Ljava/io/File;
    //   106: aload 12
    //   108: invokespecial 64	java/io/File:<init>	(Ljava/io/File;Ljava/lang/String;)V
    //   111: astore 18
    //   113: aload_0
    //   114: aload 18
    //   116: invokespecial 146	com/google/android/gms/ads/internal/w/b/t:a	(Ljava/io/File;)Ljava/io/File;
    //   119: astore 13
    //   121: aload 18
    //   123: invokevirtual 149	java/io/File:isFile	()Z
    //   126: ifeq +73 -> 199
    //   129: aload 13
    //   131: invokevirtual 149	java/io/File:isFile	()Z
    //   134: ifeq +65 -> 199
    //   137: aload 18
    //   139: invokevirtual 152	java/io/File:length	()J
    //   142: l2i
    //   143: istore_2
    //   144: aload_1
    //   145: invokestatic 83	java/lang/String:valueOf	(Ljava/lang/Object;)Ljava/lang/String;
    //   148: astore 12
    //   150: aload 12
    //   152: invokevirtual 87	java/lang/String:length	()I
    //   155: ifne +32 -> 187
    //   158: new 79	java/lang/String
    //   161: dup
    //   162: ldc -102
    //   164: invokespecial 90	java/lang/String:<init>	(Ljava/lang/String;)V
    //   167: astore 12
    //   169: aload 12
    //   171: invokestatic 156	com/google/android/gms/ads/internal/util/e:b	(Ljava/lang/String;)V
    //   174: aload_0
    //   175: aload_1
    //   176: aload 18
    //   178: invokevirtual 77	java/io/File:getAbsolutePath	()Ljava/lang/String;
    //   181: iload_2
    //   182: invokevirtual 159	com/google/android/gms/ads/internal/w/b/k:a	(Ljava/lang/String;Ljava/lang/String;I)V
    //   185: iconst_1
    //   186: ireturn
    //   187: ldc -102
    //   189: aload 12
    //   191: invokevirtual 94	java/lang/String:concat	(Ljava/lang/String;)Ljava/lang/String;
    //   194: astore 12
    //   196: goto -27 -> 169
    //   199: aload_0
    //   200: getfield 66	com/google/android/gms/ads/internal/w/b/t:f	Ljava/io/File;
    //   203: invokevirtual 77	java/io/File:getAbsolutePath	()Ljava/lang/String;
    //   206: invokestatic 83	java/lang/String:valueOf	(Ljava/lang/Object;)Ljava/lang/String;
    //   209: astore 12
    //   211: aload_1
    //   212: invokestatic 83	java/lang/String:valueOf	(Ljava/lang/Object;)Ljava/lang/String;
    //   215: astore 14
    //   217: aload 14
    //   219: invokevirtual 87	java/lang/String:length	()I
    //   222: ifne +1144 -> 1366
    //   225: new 79	java/lang/String
    //   228: dup
    //   229: aload 12
    //   231: invokespecial 90	java/lang/String:<init>	(Ljava/lang/String;)V
    //   234: astore 16
    //   236: getstatic 28	com/google/android/gms/ads/internal/w/b/t:g	Ljava/util/Set;
    //   239: astore 14
    //   241: aload 14
    //   243: monitorenter
    //   244: getstatic 28	com/google/android/gms/ads/internal/w/b/t:g	Ljava/util/Set;
    //   247: aload 16
    //   249: invokeinterface 165 2 0
    //   254: ifne +1049 -> 1303
    //   257: getstatic 28	com/google/android/gms/ads/internal/w/b/t:g	Ljava/util/Set;
    //   260: aload 16
    //   262: invokeinterface 168 2 0
    //   267: pop
    //   268: aload 14
    //   270: monitorexit
    //   271: getstatic 174	com/google/android/gms/ads/internal/bt:A	Lcom/google/android/gms/ads/internal/bt;
    //   274: getfield 178	com/google/android/gms/ads/internal/bt:r	Lcom/google/android/gms/ads/internal/util/b/a;
    //   277: astore 12
    //   279: aload_1
    //   280: getstatic 181	com/google/android/gms/ads/internal/f/n:cs	Lcom/google/android/gms/ads/internal/f/c;
    //   283: invokevirtual 136	com/google/android/gms/ads/internal/f/c:a	()Ljava/lang/Object;
    //   286: checkcast 138	java/lang/Integer
    //   289: invokevirtual 141	java/lang/Integer:intValue	()I
    //   292: invokestatic 186	com/google/android/gms/ads/internal/util/b/a:a	(Ljava/lang/String;I)Ljava/net/HttpURLConnection;
    //   295: astore 14
    //   297: aload 14
    //   299: instanceof 188
    //   302: ifne +874 -> 1176
    //   305: aload 14
    //   307: invokevirtual 193	java/net/URLConnection:getContentLength	()I
    //   310: istore 4
    //   312: iload 4
    //   314: iflt +791 -> 1105
    //   317: getstatic 37	com/google/android/gms/ads/internal/w/b/t:d	Ljava/text/DecimalFormat;
    //   320: iload 4
    //   322: i2l
    //   323: invokevirtual 197	java/text/DecimalFormat:format	(J)Ljava/lang/String;
    //   326: astore 12
    //   328: getstatic 200	com/google/android/gms/ads/internal/f/n:cp	Lcom/google/android/gms/ads/internal/f/c;
    //   331: invokevirtual 136	com/google/android/gms/ads/internal/f/c:a	()Ljava/lang/Object;
    //   334: checkcast 138	java/lang/Integer
    //   337: invokevirtual 141	java/lang/Integer:intValue	()I
    //   340: istore 5
    //   342: iload 4
    //   344: iload 5
    //   346: if_icmpgt +622 -> 968
    //   349: new 202	java/lang/StringBuilder
    //   352: dup
    //   353: aload 12
    //   355: invokestatic 83	java/lang/String:valueOf	(Ljava/lang/Object;)Ljava/lang/String;
    //   358: invokevirtual 87	java/lang/String:length	()I
    //   361: bipush 20
    //   363: iadd
    //   364: aload_1
    //   365: invokestatic 83	java/lang/String:valueOf	(Ljava/lang/Object;)Ljava/lang/String;
    //   368: invokevirtual 87	java/lang/String:length	()I
    //   371: iadd
    //   372: invokespecial 205	java/lang/StringBuilder:<init>	(I)V
    //   375: astore 15
    //   377: aload 15
    //   379: ldc -49
    //   381: invokevirtual 211	java/lang/StringBuilder:append	(Ljava/lang/String;)Ljava/lang/StringBuilder;
    //   384: pop
    //   385: aload 15
    //   387: aload 12
    //   389: invokevirtual 211	java/lang/StringBuilder:append	(Ljava/lang/String;)Ljava/lang/StringBuilder;
    //   392: pop
    //   393: aload 15
    //   395: ldc -43
    //   397: invokevirtual 211	java/lang/StringBuilder:append	(Ljava/lang/String;)Ljava/lang/StringBuilder;
    //   400: pop
    //   401: aload 15
    //   403: aload_1
    //   404: invokevirtual 211	java/lang/StringBuilder:append	(Ljava/lang/String;)Ljava/lang/StringBuilder;
    //   407: pop
    //   408: aload 15
    //   410: invokevirtual 216	java/lang/StringBuilder:toString	()Ljava/lang/String;
    //   413: invokestatic 156	com/google/android/gms/ads/internal/util/e:b	(Ljava/lang/String;)V
    //   416: aload 14
    //   418: invokevirtual 220	java/net/URLConnection:getInputStream	()Ljava/io/InputStream;
    //   421: invokestatic 226	java/nio/channels/Channels:newChannel	(Ljava/io/InputStream;)Ljava/nio/channels/ReadableByteChannel;
    //   424: astore 14
    //   426: new 228	java/io/FileOutputStream
    //   429: dup
    //   430: aload 18
    //   432: invokespecial 231	java/io/FileOutputStream:<init>	(Ljava/io/File;)V
    //   435: astore 12
    //   437: aload 12
    //   439: invokevirtual 235	java/io/FileOutputStream:getChannel	()Ljava/nio/channels/FileChannel;
    //   442: astore 15
    //   444: ldc -20
    //   446: invokestatic 242	java/nio/ByteBuffer:allocate	(I)Ljava/nio/ByteBuffer;
    //   449: astore 17
    //   451: getstatic 174	com/google/android/gms/ads/internal/bt:A	Lcom/google/android/gms/ads/internal/bt;
    //   454: getfield 246	com/google/android/gms/ads/internal/bt:l	Lcom/google/android/gms/common/util/b;
    //   457: astore 19
    //   459: aload 19
    //   461: invokeinterface 250 1 0
    //   466: lstore 6
    //   468: new 252	com/google/android/gms/ads/internal/util/bm
    //   471: dup
    //   472: getstatic 255	com/google/android/gms/ads/internal/f/n:cr	Lcom/google/android/gms/ads/internal/f/c;
    //   475: invokevirtual 136	com/google/android/gms/ads/internal/f/c:a	()Ljava/lang/Object;
    //   478: checkcast 257	java/lang/Long
    //   481: invokevirtual 260	java/lang/Long:longValue	()J
    //   484: invokespecial 263	com/google/android/gms/ads/internal/util/bm:<init>	(J)V
    //   487: astore 20
    //   489: getstatic 266	com/google/android/gms/ads/internal/f/n:cq	Lcom/google/android/gms/ads/internal/f/c;
    //   492: invokevirtual 136	com/google/android/gms/ads/internal/f/c:a	()Ljava/lang/Object;
    //   495: checkcast 257	java/lang/Long
    //   498: invokevirtual 260	java/lang/Long:longValue	()J
    //   501: lstore 8
    //   503: iconst_0
    //   504: istore_2
    //   505: aload 14
    //   507: aload 17
    //   509: invokeinterface 272 2 0
    //   514: istore_3
    //   515: iload_3
    //   516: iflt +291 -> 807
    //   519: iload_2
    //   520: iload_3
    //   521: iadd
    //   522: istore_3
    //   523: iload_3
    //   524: iload 5
    //   526: if_icmpgt +1059 -> 1585
    //   529: aload 17
    //   531: invokevirtual 276	java/nio/ByteBuffer:flip	()Ljava/nio/Buffer;
    //   534: pop
    //   535: aload 15
    //   537: aload 17
    //   539: invokevirtual 281	java/nio/channels/FileChannel:write	(Ljava/nio/ByteBuffer;)I
    //   542: ifgt -7 -> 535
    //   545: aload 17
    //   547: invokevirtual 284	java/nio/ByteBuffer:clear	()Ljava/nio/Buffer;
    //   550: pop
    //   551: aload 19
    //   553: invokeinterface 250 1 0
    //   558: lload 6
    //   560: lsub
    //   561: ldc2_w 285
    //   564: lload 8
    //   566: lmul
    //   567: lcmp
    //   568: ifgt +1079 -> 1647
    //   571: aload_0
    //   572: getfield 111	com/google/android/gms/ads/internal/w/b/t:e	Z
    //   575: ifne +1169 -> 1744
    //   578: iload_3
    //   579: istore_2
    //   580: aload 20
    //   582: invokevirtual 288	com/google/android/gms/ads/internal/util/bm:a	()Z
    //   585: ifeq -80 -> 505
    //   588: aload 18
    //   590: invokevirtual 77	java/io/File:getAbsolutePath	()Ljava/lang/String;
    //   593: astore 21
    //   595: getstatic 293	com/google/android/gms/ads/internal/util/client/a:g	Landroid/os/Handler;
    //   598: new 295	com/google/android/gms/ads/internal/w/b/l
    //   601: dup
    //   602: aload_0
    //   603: aload_1
    //   604: aload 21
    //   606: iload_3
    //   607: iload 4
    //   609: invokespecial 298	com/google/android/gms/ads/internal/w/b/l:<init>	(Lcom/google/android/gms/ads/internal/w/b/k;Ljava/lang/String;Ljava/lang/String;II)V
    //   612: invokevirtual 304	android/os/Handler:post	(Ljava/lang/Runnable;)Z
    //   615: pop
    //   616: iload_3
    //   617: istore_2
    //   618: goto -113 -> 505
    //   621: astore 13
    //   623: aconst_null
    //   624: astore 17
    //   626: ldc_w 306
    //   629: astore 15
    //   631: aload 13
    //   633: astore 14
    //   635: aload 12
    //   637: astore 13
    //   639: aload 17
    //   641: astore 12
    //   643: aload 14
    //   645: instanceof 116
    //   648: ifeq +17 -> 665
    //   651: getstatic 174	com/google/android/gms/ads/internal/bt:A	Lcom/google/android/gms/ads/internal/bt;
    //   654: getfield 310	com/google/android/gms/ads/internal/bt:i	Lcom/google/android/gms/ads/internal/v/f;
    //   657: aload 14
    //   659: ldc_w 312
    //   662: invokevirtual 317	com/google/android/gms/ads/internal/v/f:a	(Ljava/lang/Throwable;Ljava/lang/String;)V
    //   665: aload 13
    //   667: invokevirtual 320	java/io/FileOutputStream:close	()V
    //   670: aload_0
    //   671: getfield 111	com/google/android/gms/ads/internal/w/b/t:e	Z
    //   674: ifeq +1139 -> 1813
    //   677: new 202	java/lang/StringBuilder
    //   680: dup
    //   681: aload_1
    //   682: invokestatic 83	java/lang/String:valueOf	(Ljava/lang/Object;)Ljava/lang/String;
    //   685: invokevirtual 87	java/lang/String:length	()I
    //   688: bipush 26
    //   690: iadd
    //   691: invokespecial 205	java/lang/StringBuilder:<init>	(I)V
    //   694: astore 13
    //   696: aload 13
    //   698: ldc_w 322
    //   701: invokevirtual 211	java/lang/StringBuilder:append	(Ljava/lang/String;)Ljava/lang/StringBuilder;
    //   704: pop
    //   705: aload 13
    //   707: aload_1
    //   708: invokevirtual 211	java/lang/StringBuilder:append	(Ljava/lang/String;)Ljava/lang/StringBuilder;
    //   711: pop
    //   712: aload 13
    //   714: ldc_w 324
    //   717: invokevirtual 211	java/lang/StringBuilder:append	(Ljava/lang/String;)Ljava/lang/StringBuilder;
    //   720: pop
    //   721: aload 13
    //   723: invokevirtual 216	java/lang/StringBuilder:toString	()Ljava/lang/String;
    //   726: invokestatic 326	com/google/android/gms/ads/internal/util/e:d	(Ljava/lang/String;)V
    //   729: aload 18
    //   731: invokevirtual 329	java/io/File:exists	()Z
    //   734: ifeq +46 -> 780
    //   737: aload 18
    //   739: invokevirtual 332	java/io/File:delete	()Z
    //   742: ifne +38 -> 780
    //   745: aload 18
    //   747: invokevirtual 77	java/io/File:getAbsolutePath	()Ljava/lang/String;
    //   750: invokestatic 83	java/lang/String:valueOf	(Ljava/lang/Object;)Ljava/lang/String;
    //   753: astore 13
    //   755: aload 13
    //   757: invokevirtual 87	java/lang/String:length	()I
    //   760: ifne +1110 -> 1870
    //   763: new 79	java/lang/String
    //   766: dup
    //   767: ldc_w 334
    //   770: invokespecial 90	java/lang/String:<init>	(Ljava/lang/String;)V
    //   773: astore 13
    //   775: aload 13
    //   777: invokestatic 57	com/google/android/gms/ads/internal/util/e:e	(Ljava/lang/String;)V
    //   780: aload_0
    //   781: aload_1
    //   782: aload 18
    //   784: invokevirtual 77	java/io/File:getAbsolutePath	()Ljava/lang/String;
    //   787: aload 15
    //   789: aload 12
    //   791: invokevirtual 337	com/google/android/gms/ads/internal/w/b/k:a	(Ljava/lang/String;Ljava/lang/String;Ljava/lang/String;Ljava/lang/String;)V
    //   794: getstatic 28	com/google/android/gms/ads/internal/w/b/t:g	Ljava/util/Set;
    //   797: aload 16
    //   799: invokeinterface 340 2 0
    //   804: pop
    //   805: iconst_0
    //   806: ireturn
    //   807: aload 12
    //   809: invokevirtual 320	java/io/FileOutputStream:close	()V
    //   812: iconst_3
    //   813: invokestatic 343	com/google/android/gms/ads/internal/util/e:a	(I)Z
    //   816: ifne +66 -> 882
    //   819: aload 18
    //   821: iconst_1
    //   822: iconst_0
    //   823: invokevirtual 98	java/io/File:setReadable	(ZZ)Z
    //   826: pop
    //   827: aload 13
    //   829: invokevirtual 149	java/io/File:isFile	()Z
    //   832: ifeq +36 -> 868
    //   835: aload 13
    //   837: invokestatic 348	java/lang/System:currentTimeMillis	()J
    //   840: invokevirtual 352	java/io/File:setLastModified	(J)Z
    //   843: pop
    //   844: aload_0
    //   845: aload_1
    //   846: aload 18
    //   848: invokevirtual 77	java/io/File:getAbsolutePath	()Ljava/lang/String;
    //   851: iload_2
    //   852: invokevirtual 159	com/google/android/gms/ads/internal/w/b/k:a	(Ljava/lang/String;Ljava/lang/String;I)V
    //   855: getstatic 28	com/google/android/gms/ads/internal/w/b/t:g	Ljava/util/Set;
    //   858: aload 16
    //   860: invokeinterface 340 2 0
    //   865: pop
    //   866: iconst_1
    //   867: ireturn
    //   868: aload 13
    //   870: invokevirtual 355	java/io/File:createNewFile	()Z
    //   873: pop
    //   874: goto -30 -> 844
    //   877: astore 13
    //   879: goto -35 -> 844
    //   882: getstatic 37	com/google/android/gms/ads/internal/w/b/t:d	Ljava/text/DecimalFormat;
    //   885: iload_2
    //   886: i2l
    //   887: invokevirtual 197	java/text/DecimalFormat:format	(J)Ljava/lang/String;
    //   890: astore 14
    //   892: new 202	java/lang/StringBuilder
    //   895: dup
    //   896: aload 14
    //   898: invokestatic 83	java/lang/String:valueOf	(Ljava/lang/Object;)Ljava/lang/String;
    //   901: invokevirtual 87	java/lang/String:length	()I
    //   904: bipush 22
    //   906: iadd
    //   907: aload_1
    //   908: invokestatic 83	java/lang/String:valueOf	(Ljava/lang/Object;)Ljava/lang/String;
    //   911: invokevirtual 87	java/lang/String:length	()I
    //   914: iadd
    //   915: invokespecial 205	java/lang/StringBuilder:<init>	(I)V
    //   918: astore 15
    //   920: aload 15
    //   922: ldc_w 357
    //   925: invokevirtual 211	java/lang/StringBuilder:append	(Ljava/lang/String;)Ljava/lang/StringBuilder;
    //   928: pop
    //   929: aload 15
    //   931: aload 14
    //   933: invokevirtual 211	java/lang/StringBuilder:append	(Ljava/lang/String;)Ljava/lang/StringBuilder;
    //   936: pop
    //   937: aload 15
    //   939: ldc -43
    //   941: invokevirtual 211	java/lang/StringBuilder:append	(Ljava/lang/String;)Ljava/lang/StringBuilder;
    //   944: pop
    //   945: aload 15
    //   947: aload_1
    //   948: invokevirtual 211	java/lang/StringBuilder:append	(Ljava/lang/String;)Ljava/lang/StringBuilder;
    //   951: pop
    //   952: aload 15
    //   954: invokevirtual 216	java/lang/StringBuilder:toString	()Ljava/lang/String;
    //   957: invokestatic 156	com/google/android/gms/ads/internal/util/e:b	(Ljava/lang/String;)V
    //   960: goto -141 -> 819
    //   963: astore 13
    //   965: goto -342 -> 623
    //   968: new 202	java/lang/StringBuilder
    //   971: dup
    //   972: aload 12
    //   974: invokestatic 83	java/lang/String:valueOf	(Ljava/lang/Object;)Ljava/lang/String;
    //   977: invokevirtual 87	java/lang/String:length	()I
    //   980: bipush 33
    //   982: iadd
    //   983: aload_1
    //   984: invokestatic 83	java/lang/String:valueOf	(Ljava/lang/Object;)Ljava/lang/String;
    //   987: invokevirtual 87	java/lang/String:length	()I
    //   990: iadd
    //   991: invokespecial 205	java/lang/StringBuilder:<init>	(I)V
    //   994: astore 13
    //   996: aload 13
    //   998: ldc_w 359
    //   1001: invokevirtual 211	java/lang/StringBuilder:append	(Ljava/lang/String;)Ljava/lang/StringBuilder;
    //   1004: pop
    //   1005: aload 13
    //   1007: aload 12
    //   1009: invokevirtual 211	java/lang/StringBuilder:append	(Ljava/lang/String;)Ljava/lang/StringBuilder;
    //   1012: pop
    //   1013: aload 13
    //   1015: ldc_w 361
    //   1018: invokevirtual 211	java/lang/StringBuilder:append	(Ljava/lang/String;)Ljava/lang/StringBuilder;
    //   1021: pop
    //   1022: aload 13
    //   1024: aload_1
    //   1025: invokevirtual 211	java/lang/StringBuilder:append	(Ljava/lang/String;)Ljava/lang/StringBuilder;
    //   1028: pop
    //   1029: aload 13
    //   1031: invokevirtual 216	java/lang/StringBuilder:toString	()Ljava/lang/String;
    //   1034: invokestatic 57	com/google/android/gms/ads/internal/util/e:e	(Ljava/lang/String;)V
    //   1037: aload 12
    //   1039: invokestatic 83	java/lang/String:valueOf	(Ljava/lang/Object;)Ljava/lang/String;
    //   1042: astore 12
    //   1044: aload 12
    //   1046: invokevirtual 87	java/lang/String:length	()I
    //   1049: ifne +43 -> 1092
    //   1052: new 79	java/lang/String
    //   1055: dup
    //   1056: ldc_w 363
    //   1059: invokespecial 90	java/lang/String:<init>	(Ljava/lang/String;)V
    //   1062: astore 12
    //   1064: aload_0
    //   1065: aload_1
    //   1066: aload 18
    //   1068: invokevirtual 77	java/io/File:getAbsolutePath	()Ljava/lang/String;
    //   1071: ldc_w 365
    //   1074: aload 12
    //   1076: invokevirtual 337	com/google/android/gms/ads/internal/w/b/k:a	(Ljava/lang/String;Ljava/lang/String;Ljava/lang/String;Ljava/lang/String;)V
    //   1079: getstatic 28	com/google/android/gms/ads/internal/w/b/t:g	Ljava/util/Set;
    //   1082: aload 16
    //   1084: invokeinterface 340 2 0
    //   1089: pop
    //   1090: iconst_0
    //   1091: ireturn
    //   1092: ldc_w 363
    //   1095: aload 12
    //   1097: invokevirtual 94	java/lang/String:concat	(Ljava/lang/String;)Ljava/lang/String;
    //   1100: astore 12
    //   1102: goto -38 -> 1064
    //   1105: aload_1
    //   1106: invokestatic 83	java/lang/String:valueOf	(Ljava/lang/Object;)Ljava/lang/String;
    //   1109: astore 12
    //   1111: aload 12
    //   1113: invokevirtual 87	java/lang/String:length	()I
    //   1116: ifne +47 -> 1163
    //   1119: new 79	java/lang/String
    //   1122: dup
    //   1123: ldc_w 367
    //   1126: invokespecial 90	java/lang/String:<init>	(Ljava/lang/String;)V
    //   1129: astore 12
    //   1131: aload 12
    //   1133: invokestatic 57	com/google/android/gms/ads/internal/util/e:e	(Ljava/lang/String;)V
    //   1136: aload_0
    //   1137: aload_1
    //   1138: aload 18
    //   1140: invokevirtual 77	java/io/File:getAbsolutePath	()Ljava/lang/String;
    //   1143: ldc_w 369
    //   1146: aconst_null
    //   1147: invokevirtual 337	com/google/android/gms/ads/internal/w/b/k:a	(Ljava/lang/String;Ljava/lang/String;Ljava/lang/String;Ljava/lang/String;)V
    //   1150: getstatic 28	com/google/android/gms/ads/internal/w/b/t:g	Ljava/util/Set;
    //   1153: aload 16
    //   1155: invokeinterface 340 2 0
    //   1160: pop
    //   1161: iconst_0
    //   1162: ireturn
    //   1163: ldc_w 367
    //   1166: aload 12
    //   1168: invokevirtual 94	java/lang/String:concat	(Ljava/lang/String;)Ljava/lang/String;
    //   1171: astore 12
    //   1173: goto -42 -> 1131
    //   1176: aload 14
    //   1178: invokevirtual 372	java/net/HttpURLConnection:getResponseCode	()I
    //   1181: istore_2
    //   1182: iload_2
    //   1183: sipush 400
    //   1186: if_icmplt -881 -> 305
    //   1189: iload_2
    //   1190: invokestatic 375	java/lang/Integer:toString	(I)Ljava/lang/String;
    //   1193: invokestatic 83	java/lang/String:valueOf	(Ljava/lang/Object;)Ljava/lang/String;
    //   1196: astore 12
    //   1198: aload 12
    //   1200: invokevirtual 87	java/lang/String:length	()I
    //   1203: ifne +597 -> 1800
    //   1206: new 79	java/lang/String
    //   1209: dup
    //   1210: ldc_w 377
    //   1213: invokespecial 90	java/lang/String:<init>	(Ljava/lang/String;)V
    //   1216: astore 12
    //   1218: new 202	java/lang/StringBuilder
    //   1221: dup
    //   1222: aload_1
    //   1223: invokestatic 83	java/lang/String:valueOf	(Ljava/lang/Object;)Ljava/lang/String;
    //   1226: invokevirtual 87	java/lang/String:length	()I
    //   1229: bipush 32
    //   1231: iadd
    //   1232: invokespecial 205	java/lang/StringBuilder:<init>	(I)V
    //   1235: astore 13
    //   1237: aload 13
    //   1239: ldc_w 379
    //   1242: invokevirtual 211	java/lang/StringBuilder:append	(Ljava/lang/String;)Ljava/lang/StringBuilder;
    //   1245: pop
    //   1246: aload 13
    //   1248: iload_2
    //   1249: invokevirtual 382	java/lang/StringBuilder:append	(I)Ljava/lang/StringBuilder;
    //   1252: pop
    //   1253: aload 13
    //   1255: ldc_w 384
    //   1258: invokevirtual 211	java/lang/StringBuilder:append	(Ljava/lang/String;)Ljava/lang/StringBuilder;
    //   1261: pop
    //   1262: aload 13
    //   1264: aload_1
    //   1265: invokevirtual 211	java/lang/StringBuilder:append	(Ljava/lang/String;)Ljava/lang/StringBuilder;
    //   1268: pop
    //   1269: new 114	java/io/IOException
    //   1272: dup
    //   1273: aload 13
    //   1275: invokevirtual 216	java/lang/StringBuilder:toString	()Ljava/lang/String;
    //   1278: invokespecial 385	java/io/IOException:<init>	(Ljava/lang/String;)V
    //   1281: athrow
    //   1282: astore 13
    //   1284: ldc_w 387
    //   1287: astore 15
    //   1289: aconst_null
    //   1290: astore 17
    //   1292: aload 13
    //   1294: astore 14
    //   1296: aload 17
    //   1298: astore 13
    //   1300: goto -657 -> 643
    //   1303: aload_1
    //   1304: invokestatic 83	java/lang/String:valueOf	(Ljava/lang/Object;)Ljava/lang/String;
    //   1307: astore 12
    //   1309: aload 12
    //   1311: invokevirtual 87	java/lang/String:length	()I
    //   1314: ifne +39 -> 1353
    //   1317: new 79	java/lang/String
    //   1320: dup
    //   1321: ldc_w 389
    //   1324: invokespecial 90	java/lang/String:<init>	(Ljava/lang/String;)V
    //   1327: astore 12
    //   1329: aload 12
    //   1331: invokestatic 57	com/google/android/gms/ads/internal/util/e:e	(Ljava/lang/String;)V
    //   1334: aload_0
    //   1335: aload_1
    //   1336: aload 18
    //   1338: invokevirtual 77	java/io/File:getAbsolutePath	()Ljava/lang/String;
    //   1341: ldc_w 391
    //   1344: aconst_null
    //   1345: invokevirtual 337	com/google/android/gms/ads/internal/w/b/k:a	(Ljava/lang/String;Ljava/lang/String;Ljava/lang/String;Ljava/lang/String;)V
    //   1348: aload 14
    //   1350: monitorexit
    //   1351: iconst_0
    //   1352: ireturn
    //   1353: ldc_w 389
    //   1356: aload 12
    //   1358: invokevirtual 94	java/lang/String:concat	(Ljava/lang/String;)Ljava/lang/String;
    //   1361: astore 12
    //   1363: goto -34 -> 1329
    //   1366: aload 12
    //   1368: aload 14
    //   1370: invokevirtual 94	java/lang/String:concat	(Ljava/lang/String;)Ljava/lang/String;
    //   1373: astore 16
    //   1375: goto -1139 -> 236
    //   1378: aload_0
    //   1379: getfield 66	com/google/android/gms/ads/internal/w/b/t:f	Ljava/io/File;
    //   1382: astore 12
    //   1384: aload 12
    //   1386: ifnull +155 -> 1541
    //   1389: aload 12
    //   1391: invokevirtual 122	java/io/File:listFiles	()[Ljava/io/File;
    //   1394: astore 14
    //   1396: aload 14
    //   1398: arraylength
    //   1399: istore_3
    //   1400: aconst_null
    //   1401: astore 12
    //   1403: ldc2_w 392
    //   1406: lstore 6
    //   1408: iconst_0
    //   1409: istore_2
    //   1410: iload_2
    //   1411: iload_3
    //   1412: if_icmpge +58 -> 1470
    //   1415: aload 14
    //   1417: iload_2
    //   1418: aaload
    //   1419: astore 13
    //   1421: aload 13
    //   1423: invokevirtual 107	java/io/File:getName	()Ljava/lang/String;
    //   1426: ldc 109
    //   1428: invokevirtual 125	java/lang/String:endsWith	(Ljava/lang/String;)Z
    //   1431: ifne +36 -> 1467
    //   1434: aload 13
    //   1436: invokevirtual 396	java/io/File:lastModified	()J
    //   1439: lstore 8
    //   1441: lload 8
    //   1443: lload 6
    //   1445: lcmp
    //   1446: ifge +18 -> 1464
    //   1449: aload 13
    //   1451: astore 12
    //   1453: lload 8
    //   1455: lstore 6
    //   1457: iload_2
    //   1458: iconst_1
    //   1459: iadd
    //   1460: istore_2
    //   1461: goto -51 -> 1410
    //   1464: goto -7 -> 1457
    //   1467: goto -10 -> 1457
    //   1470: aload 12
    //   1472: ifnull +63 -> 1535
    //   1475: aload 12
    //   1477: invokevirtual 332	java/io/File:delete	()Z
    //   1480: istore 11
    //   1482: aload_0
    //   1483: aload 12
    //   1485: invokespecial 146	com/google/android/gms/ads/internal/w/b/t:a	(Ljava/io/File;)Ljava/io/File;
    //   1488: astore 12
    //   1490: iload 11
    //   1492: istore 10
    //   1494: aload 12
    //   1496: invokevirtual 149	java/io/File:isFile	()Z
    //   1499: ifeq +13 -> 1512
    //   1502: iload 11
    //   1504: aload 12
    //   1506: invokevirtual 332	java/io/File:delete	()Z
    //   1509: iand
    //   1510: istore 10
    //   1512: iload 10
    //   1514: ifne -1507 -> 7
    //   1517: ldc_w 398
    //   1520: invokestatic 57	com/google/android/gms/ads/internal/util/e:e	(Ljava/lang/String;)V
    //   1523: aload_0
    //   1524: aload_1
    //   1525: aconst_null
    //   1526: ldc_w 400
    //   1529: aconst_null
    //   1530: invokevirtual 337	com/google/android/gms/ads/internal/w/b/k:a	(Ljava/lang/String;Ljava/lang/String;Ljava/lang/String;Ljava/lang/String;)V
    //   1533: iconst_0
    //   1534: ireturn
    //   1535: iconst_0
    //   1536: istore 10
    //   1538: goto -26 -> 1512
    //   1541: iconst_0
    //   1542: istore 10
    //   1544: goto -32 -> 1512
    //   1547: aload_0
    //   1548: aload_1
    //   1549: aconst_null
    //   1550: ldc_w 402
    //   1553: aconst_null
    //   1554: invokevirtual 337	com/google/android/gms/ads/internal/w/b/k:a	(Ljava/lang/String;Ljava/lang/String;Ljava/lang/String;Ljava/lang/String;)V
    //   1557: iconst_0
    //   1558: ireturn
    //   1559: astore_1
    //   1560: aload 14
    //   1562: monitorexit
    //   1563: aload_1
    //   1564: athrow
    //   1565: astore 12
    //   1567: aconst_null
    //   1568: astore 13
    //   1570: aload 12
    //   1572: astore 14
    //   1574: aconst_null
    //   1575: astore 12
    //   1577: ldc_w 306
    //   1580: astore 15
    //   1582: goto -939 -> 643
    //   1585: ldc_w 365
    //   1588: astore 15
    //   1590: iload_3
    //   1591: invokestatic 375	java/lang/Integer:toString	(I)Ljava/lang/String;
    //   1594: invokestatic 83	java/lang/String:valueOf	(Ljava/lang/Object;)Ljava/lang/String;
    //   1597: astore 13
    //   1599: aload 13
    //   1601: invokevirtual 87	java/lang/String:length	()I
    //   1604: ifne +299 -> 1903
    //   1607: new 79	java/lang/String
    //   1610: dup
    //   1611: ldc_w 363
    //   1614: invokespecial 90	java/lang/String:<init>	(Ljava/lang/String;)V
    //   1617: astore 13
    //   1619: new 114	java/io/IOException
    //   1622: dup
    //   1623: ldc_w 404
    //   1626: invokespecial 385	java/io/IOException:<init>	(Ljava/lang/String;)V
    //   1629: athrow
    //   1630: astore 14
    //   1632: aload 12
    //   1634: astore 17
    //   1636: aload 13
    //   1638: astore 12
    //   1640: aload 17
    //   1642: astore 13
    //   1644: goto -1001 -> 643
    //   1647: ldc_w 406
    //   1650: astore 15
    //   1652: lload 8
    //   1654: invokestatic 408	java/lang/Long:toString	(J)Ljava/lang/String;
    //   1657: astore 13
    //   1659: new 202	java/lang/StringBuilder
    //   1662: dup
    //   1663: aload 13
    //   1665: invokestatic 83	java/lang/String:valueOf	(Ljava/lang/Object;)Ljava/lang/String;
    //   1668: invokevirtual 87	java/lang/String:length	()I
    //   1671: bipush 29
    //   1673: iadd
    //   1674: invokespecial 205	java/lang/StringBuilder:<init>	(I)V
    //   1677: astore 14
    //   1679: aload 14
    //   1681: ldc_w 410
    //   1684: invokevirtual 211	java/lang/StringBuilder:append	(Ljava/lang/String;)Ljava/lang/StringBuilder;
    //   1687: pop
    //   1688: aload 14
    //   1690: aload 13
    //   1692: invokevirtual 211	java/lang/StringBuilder:append	(Ljava/lang/String;)Ljava/lang/StringBuilder;
    //   1695: pop
    //   1696: aload 14
    //   1698: ldc_w 412
    //   1701: invokevirtual 211	java/lang/StringBuilder:append	(Ljava/lang/String;)Ljava/lang/StringBuilder;
    //   1704: pop
    //   1705: aload 14
    //   1707: invokevirtual 216	java/lang/StringBuilder:toString	()Ljava/lang/String;
    //   1710: astore 14
    //   1712: new 114	java/io/IOException
    //   1715: dup
    //   1716: ldc_w 414
    //   1719: invokespecial 385	java/io/IOException:<init>	(Ljava/lang/String;)V
    //   1722: athrow
    //   1723: astore 13
    //   1725: aload 13
    //   1727: astore 17
    //   1729: aload 12
    //   1731: astore 13
    //   1733: aload 14
    //   1735: astore 12
    //   1737: aload 17
    //   1739: astore 14
    //   1741: goto -1098 -> 643
    //   1744: ldc_w 416
    //   1747: astore 15
    //   1749: new 114	java/io/IOException
    //   1752: dup
    //   1753: ldc_w 418
    //   1756: invokespecial 385	java/io/IOException:<init>	(Ljava/lang/String;)V
    //   1759: athrow
    //   1760: astore 13
    //   1762: aconst_null
    //   1763: astore 17
    //   1765: aload 13
    //   1767: astore 14
    //   1769: aload 12
    //   1771: astore 13
    //   1773: aload 17
    //   1775: astore 12
    //   1777: goto -1134 -> 643
    //   1780: astore 12
    //   1782: ldc_w 387
    //   1785: astore 15
    //   1787: aconst_null
    //   1788: astore 13
    //   1790: aload 12
    //   1792: astore 14
    //   1794: aconst_null
    //   1795: astore 12
    //   1797: goto -1154 -> 643
    //   1800: ldc_w 377
    //   1803: aload 12
    //   1805: invokevirtual 94	java/lang/String:concat	(Ljava/lang/String;)Ljava/lang/String;
    //   1808: astore 12
    //   1810: goto -592 -> 1218
    //   1813: new 202	java/lang/StringBuilder
    //   1816: dup
    //   1817: aload_1
    //   1818: invokestatic 83	java/lang/String:valueOf	(Ljava/lang/Object;)Ljava/lang/String;
    //   1821: invokevirtual 87	java/lang/String:length	()I
    //   1824: bipush 25
    //   1826: iadd
    //   1827: invokespecial 205	java/lang/StringBuilder:<init>	(I)V
    //   1830: astore 13
    //   1832: aload 13
    //   1834: ldc_w 420
    //   1837: invokevirtual 211	java/lang/StringBuilder:append	(Ljava/lang/String;)Ljava/lang/StringBuilder;
    //   1840: pop
    //   1841: aload 13
    //   1843: aload_1
    //   1844: invokevirtual 211	java/lang/StringBuilder:append	(Ljava/lang/String;)Ljava/lang/StringBuilder;
    //   1847: pop
    //   1848: aload 13
    //   1850: ldc_w 324
    //   1853: invokevirtual 211	java/lang/StringBuilder:append	(Ljava/lang/String;)Ljava/lang/StringBuilder;
    //   1856: pop
    //   1857: aload 13
    //   1859: invokevirtual 216	java/lang/StringBuilder:toString	()Ljava/lang/String;
    //   1862: aload 14
    //   1864: invokestatic 423	com/google/android/gms/ads/internal/util/e:e	(Ljava/lang/String;Ljava/lang/Throwable;)V
    //   1867: goto -1138 -> 729
    //   1870: ldc_w 334
    //   1873: aload 13
    //   1875: invokevirtual 94	java/lang/String:concat	(Ljava/lang/String;)Ljava/lang/String;
    //   1878: astore 13
    //   1880: goto -1105 -> 775
    //   1883: astore 13
    //   1885: aconst_null
    //   1886: astore 17
    //   1888: aload 13
    //   1890: astore 14
    //   1892: aload 12
    //   1894: astore 13
    //   1896: aload 17
    //   1898: astore 12
    //   1900: goto -1257 -> 643
    //   1903: ldc_w 363
    //   1906: aload 13
    //   1908: invokevirtual 94	java/lang/String:concat	(Ljava/lang/String;)Ljava/lang/String;
    //   1911: astore 13
    //   1913: goto -294 -> 1619
    //   1916: astore 13
    //   1918: aconst_null
    //   1919: astore 17
    //   1921: aload 13
    //   1923: astore 14
    //   1925: aload 12
    //   1927: astore 13
    //   1929: aload 17
    //   1931: astore 12
    //   1933: goto -1290 -> 643
    //   1936: astore 13
    //   1938: goto -1268 -> 670
    //   1941: astore 13
    //   1943: goto -1273 -> 670
    //   1946: astore 13
    //   1948: goto -186 -> 1762
    //   1951: astore 13
    //   1953: goto -228 -> 1725
    //   1956: astore 13
    //   1958: goto -40 -> 1918
    //   1961: astore 14
    //   1963: goto -331 -> 1632
    //   1966: astore 13
    //   1968: goto -83 -> 1885
    //   1971: astore 13
    //   1973: goto -689 -> 1284
    //   1976: astore 12
    //   1978: goto -196 -> 1782
    //   1981: astore 12
    //   1983: goto -416 -> 1567
    //   1986: goto -1911 -> 75
    // Local variable table:
    //   start	length	slot	name	signature
    //   0	1989	0	this	t
    //   0	1989	1	paramString	String
    //   31	1430	2	i	int
    //   33	1558	3	j	int
    //   41	567	4	k	int
    //   28	499	5	m	int
    //   466	990	6	l1	long
    //   501	1152	8	l2	long
    //   1492	51	10	bool1	boolean
    //   1480	30	11	bool2	boolean
    //   11	1494	12	localObject1	Object
    //   1565	6	12	localRuntimeException1	RuntimeException
    //   1575	201	12	localObject2	Object
    //   1780	11	12	localRuntimeException2	RuntimeException
    //   1795	137	12	localObject3	Object
    //   1976	1	12	localIOException1	java.io.IOException
    //   1981	1	12	localIOException2	java.io.IOException
    //   119	11	13	localFile1	File
    //   621	11	13	localIOException3	java.io.IOException
    //   637	232	13	localObject4	Object
    //   877	1	13	localIOException4	java.io.IOException
    //   963	1	13	localRuntimeException3	RuntimeException
    //   994	280	13	localStringBuilder	StringBuilder
    //   1282	11	13	localIOException5	java.io.IOException
    //   1298	393	13	localObject5	Object
    //   1723	3	13	localIOException6	java.io.IOException
    //   1731	1	13	localObject6	Object
    //   1760	6	13	localIOException7	java.io.IOException
    //   1771	108	13	localObject7	Object
    //   1883	6	13	localRuntimeException4	RuntimeException
    //   1894	18	13	localObject8	Object
    //   1916	6	13	localRuntimeException5	RuntimeException
    //   1927	1	13	localObject9	Object
    //   1936	1	13	localIOException8	java.io.IOException
    //   1941	1	13	localNullPointerException	NullPointerException
    //   1946	1	13	localRuntimeException6	RuntimeException
    //   1951	1	13	localRuntimeException7	RuntimeException
    //   1956	1	13	localIOException9	java.io.IOException
    //   1966	1	13	localIOException10	java.io.IOException
    //   1971	1	13	localRuntimeException8	RuntimeException
    //   215	1358	14	localObject10	Object
    //   1630	1	14	localIOException11	java.io.IOException
    //   1677	247	14	localObject11	Object
    //   1961	1	14	localRuntimeException9	RuntimeException
    //   375	1411	15	localObject12	Object
    //   234	1140	16	str1	String
    //   449	1481	17	localObject13	Object
    //   111	1226	18	localFile2	File
    //   457	95	19	localb	com.google.android.gms.common.util.b
    //   487	94	20	localbm	com.google.android.gms.ads.internal.util.bm
    //   593	12	21	str2	String
    // Exception table:
    //   from	to	target	type
    //   437	503	621	java/io/IOException
    //   505	515	621	java/io/IOException
    //   529	535	621	java/io/IOException
    //   535	578	621	java/io/IOException
    //   580	616	621	java/io/IOException
    //   807	819	621	java/io/IOException
    //   819	844	621	java/io/IOException
    //   844	866	621	java/io/IOException
    //   882	960	621	java/io/IOException
    //   868	874	877	java/io/IOException
    //   437	503	963	java/lang/RuntimeException
    //   505	515	963	java/lang/RuntimeException
    //   529	535	963	java/lang/RuntimeException
    //   535	578	963	java/lang/RuntimeException
    //   580	616	963	java/lang/RuntimeException
    //   807	819	963	java/lang/RuntimeException
    //   819	844	963	java/lang/RuntimeException
    //   844	866	963	java/lang/RuntimeException
    //   868	874	963	java/lang/RuntimeException
    //   882	960	963	java/lang/RuntimeException
    //   1218	1282	1282	java/io/IOException
    //   244	271	1559	finally
    //   1303	1329	1559	finally
    //   1329	1351	1559	finally
    //   1353	1363	1559	finally
    //   1560	1563	1559	finally
    //   271	305	1565	java/lang/RuntimeException
    //   305	312	1565	java/lang/RuntimeException
    //   317	342	1565	java/lang/RuntimeException
    //   349	437	1565	java/lang/RuntimeException
    //   968	1064	1565	java/lang/RuntimeException
    //   1064	1090	1565	java/lang/RuntimeException
    //   1092	1102	1565	java/lang/RuntimeException
    //   1105	1131	1565	java/lang/RuntimeException
    //   1131	1161	1565	java/lang/RuntimeException
    //   1163	1173	1565	java/lang/RuntimeException
    //   1176	1182	1565	java/lang/RuntimeException
    //   1619	1630	1630	java/io/IOException
    //   1712	1723	1723	java/io/IOException
    //   1749	1760	1760	java/io/IOException
    //   1189	1218	1780	java/lang/RuntimeException
    //   1800	1810	1780	java/lang/RuntimeException
    //   1590	1619	1883	java/lang/RuntimeException
    //   1903	1913	1883	java/lang/RuntimeException
    //   1652	1712	1916	java/lang/RuntimeException
    //   665	670	1936	java/io/IOException
    //   665	670	1941	java/lang/NullPointerException
    //   1749	1760	1946	java/lang/RuntimeException
    //   1712	1723	1951	java/lang/RuntimeException
    //   1652	1712	1956	java/io/IOException
    //   1619	1630	1961	java/lang/RuntimeException
    //   1590	1619	1966	java/io/IOException
    //   1903	1913	1966	java/io/IOException
    //   1218	1282	1971	java/lang/RuntimeException
    //   1189	1218	1976	java/io/IOException
    //   1800	1810	1976	java/io/IOException
    //   271	305	1981	java/io/IOException
    //   305	312	1981	java/io/IOException
    //   317	342	1981	java/io/IOException
    //   349	437	1981	java/io/IOException
    //   968	1064	1981	java/io/IOException
    //   1064	1090	1981	java/io/IOException
    //   1092	1102	1981	java/io/IOException
    //   1105	1131	1981	java/io/IOException
    //   1131	1161	1981	java/io/IOException
    //   1163	1173	1981	java/io/IOException
    //   1176	1182	1981	java/io/IOException
  }
}


/* Location:              /home/chengjian/CM_test/gp/apk/a.jar!/com/google/android/gms/ads/internal/w/b/t.class
 * Java compiler version: 6 (50.0)
 * JD-Core Version:       0.7.1
 */