package com.google.android.finsky.be;

import android.os.Bundle;
import com.google.android.finsky.bo.f;

public final class p
{
  private static final byte[] b = { 10, 77, 10, 3, 97, 112, 99, 18, 70, 10, 0, 18, 4, 10, 2, 26, 0, 26, 0, 32, -68, 5, 58, 55, -94, -83, -41, -73, 4, 49, 114, 47, 10, 6, 34, 4, 10, 2, 97, 112, 18, 35, -94, -83, -41, -73, 4, 29, 114, 27, 10, 7, 34, 5, 10, 3, 98, 112, 116, 18, 14, 18, 8, 26, 6, 8, -84, 2, 16, -83, 2, 58, 2, 8, 10, 42, 0, 50, 0, 10, -47, 2, 10, 2, 97, 112, 18, -54, 2, 10, 3, 8, -105, 6, 18, 4, 10, 2, 26, 0, 26, 15, 53, 0, 0, 82, 67, -22, -60, -36, -105, 5, 4, 10, 2, 8, 0, 32, -106, 6, -54, -48, -81, -97, 5, -92, 2, 10, 3, -62, 2, 0, 18, 46, -70, 2, 43, 18, 35, -94, -83, -41, -73, 4, 29, 114, 27, 10, 7, 34, 5, 10, 3, 98, 112, 116, 18, 14, 18, 8, 26, 6, 8, -84, 2, 16, -83, 2, 58, 2, 8, 10, 42, 0, 26, 2, 26, 0, 50, 0, 26, -20, 1, -70, 1, -24, 1, 10, 56, 8, 0, 18, 52, 34, 19, 29, 0, 0, 64, 66, 96, -40, -70, -66, -8, -1, -1, -1, -1, -1, 1, -40, 1, 4, 42, 29, 16, -1, -1, -1, -1, -1, -1, -1, -1, -1, 1, 24, 7, -112, 1, 1, -115, 2, 10, -41, -93, 60, -104, 2, -1, -1, -1, -113, 6, 10, 94, 8, 1, 18, 90, 34, 57, 37, 0, 0, Byte.MIN_VALUE, 65, 53, 0, 0, Byte.MIN_VALUE, 65, 61, 0, 0, Byte.MIN_VALUE, 65, 69, 0, 0, Byte.MIN_VALUE, 65, 77, 0, 0, 32, 65, 85, 0, 0, Byte.MIN_VALUE, 65, 93, 0, 0, 32, 65, 96, -40, -70, -66, -8, -1, -1, -1, -1, -1, 1, 125, 0, 0, -80, 66, -112, 1, 1, -72, 1, 7, 42, 29, 16, -1, -1, -1, -1, -1, -1, -1, -1, -1, 1, 24, 7, -112, 1, 1, -115, 2, 10, -41, -93, 60, -104, 2, -1, -1, -1, -113, 6, 10, 76, 8, 2, 18, 72, 34, 52, 37, 0, 0, Byte.MIN_VALUE, 65, 61, 0, 0, Byte.MIN_VALUE, 65, 69, 0, 0, 0, 65, 77, 0, 0, 32, 65, 85, 0, 0, 0, 65, 93, 0, 0, 32, 65, 96, -1, -1, -1, -1, -1, -1, -1, -1, -1, 1, 125, 0, 0, -80, 66, -112, 1, 1, -72, 1, 7, 42, 16, 16, -40, -70, -66, -8, -1, -1, -1, -1, -1, 1, 24, 7, -112, 1, 1, 10, -46, 2, 10, 3, 98, 112, 116, 18, -54, 2, 10, 3, 8, -24, 7, 26, 15, 53, 0, 0, 40, 67, -22, -60, -36, -105, 5, 4, 10, 2, 8, 0, 32, -68, 5, -54, -48, -81, -97, 5, -86, 2, 10, 78, 18, 20, 69, 0, 0, Byte.MIN_VALUE, 65, 77, 0, 0, Byte.MIN_VALUE, 65, 85, 0, 0, Byte.MIN_VALUE, 65, 93, 0, 0, Byte.MIN_VALUE, 65, -94, 1, 53, 10, 51, 10, 22, 67, 111, 109, 112, 108, 101, 116, 101, 32, 97, 99, 99, 111, 117, 110, 116, 32, 115, 101, 116, 117, 112, 34, 25, 13, 0, 0, -96, 65, 16, -95, -62, -124, -7, -1, -1, -1, -1, -1, 1, 24, 6, 32, 1, 48, 2, -120, 1, 4, 18, 114, -94, 1, 111, 10, 109, 10, 62, 82, 101, 118, 105, 101, 119, 32, 121, 111, 117, 114, 32, 97, 99, 99, 111, 117, 110, 116, 32, 116, 111, 32, 99, 111, 110, 116, 105, 110, 117, 101, 32, 105, 110, 115, 116, 97, 108, 108, 105, 110, 103, 32, 97, 112, 112, 115, 32, 111, 110, 32, 71, 111, 111, 103, 108, 101, 32, 80, 108, 97, 121, 26, 20, 69, 0, 0, Byte.MIN_VALUE, 65, 77, 0, 0, 0, 0, 85, 0, 0, Byte.MIN_VALUE, 65, 93, 0, 0, 0, 65, 34, 21, 13, 0, 0, 96, 65, 16, -31, -62, -123, -5, -1, -1, -1, -1, -1, 1, 24, 0, -96, 2, 5, 26, 100, -78, 1, 97, 10, 95, 10, 8, 67, 79, 78, 84, 73, 78, 85, 69, 18, 21, 18, 10, 26, 8, 8, -41, 2, 16, -40, 2, 24, 2, 58, 7, 8, 2, -118, 2, 2, 8, 2, 34, 29, 29, 0, 0, 64, 66, 96, -40, -70, -66, -8, -1, -1, -1, -1, -1, 1, 114, 8, 67, 79, 78, 84, 73, 78, 85, 69, -40, 1, 4, 42, 29, 16, -1, -1, -1, -1, -1, -1, -1, -1, -1, 1, 24, 7, -112, 1, 1, -115, 2, 10, -41, -93, 60, -104, 2, -1, -1, -1, -113, 6, 66, 24, 104, 1, -94, -83, -41, -73, 4, 16, -118, 1, 13, 10, 7, 34, 5, 10, 3, 97, 112, 99, 18, 2, 26, 0 };
  private static final byte[] c = { 10, 56, 10, 3, 97, 112, 99, 18, 49, 10, 0, 18, 4, 10, 2, 26, 0, 26, 0, 32, -68, 5, 58, 34, -94, -83, -41, -73, 4, 28, 114, 26, 10, 6, 34, 4, 10, 2, 97, 112, 18, 14, 18, 8, 26, 6, 8, -82, 2, 16, -81, 2, 58, 2, 8, 3, 50, 0, 10, -68, 2, 10, 2, 97, 112, 18, -75, 2, 10, 3, 8, -105, 6, 18, 4, 10, 2, 26, 0, 26, 15, 53, 0, 0, 82, 67, -22, -60, -36, -105, 5, 4, 10, 2, 8, 0, 32, -106, 6, -54, -48, -81, -97, 5, -113, 2, 10, 3, -62, 2, 0, 18, 25, -70, 2, 22, 18, 14, 18, 8, 26, 6, 8, -82, 2, 16, -81, 2, 58, 2, 8, 3, 26, 2, 26, 0, 50, 0, 26, -20, 1, -70, 1, -24, 1, 10, 56, 8, 0, 18, 52, 34, 19, 29, 0, 0, 64, 66, 96, -40, -70, -66, -8, -1, -1, -1, -1, -1, 1, -40, 1, 4, 42, 29, 16, -1, -1, -1, -1, -1, -1, -1, -1, -1, 1, 24, 7, -112, 1, 1, -115, 2, 10, -41, -93, 60, -104, 2, -1, -1, -1, -113, 6, 10, 94, 8, 1, 18, 90, 34, 57, 37, 0, 0, Byte.MIN_VALUE, 65, 53, 0, 0, Byte.MIN_VALUE, 65, 61, 0, 0, Byte.MIN_VALUE, 65, 69, 0, 0, Byte.MIN_VALUE, 65, 77, 0, 0, 32, 65, 85, 0, 0, Byte.MIN_VALUE, 65, 93, 0, 0, 32, 65, 96, -40, -70, -66, -8, -1, -1, -1, -1, -1, 1, 125, 0, 0, -80, 66, -112, 1, 1, -72, 1, 7, 42, 29, 16, -1, -1, -1, -1, -1, -1, -1, -1, -1, 1, 24, 7, -112, 1, 1, -115, 2, 10, -41, -93, 60, -104, 2, -1, -1, -1, -113, 6, 10, 76, 8, 2, 18, 72, 34, 52, 37, 0, 0, Byte.MIN_VALUE, 65, 61, 0, 0, Byte.MIN_VALUE, 65, 69, 0, 0, 0, 65, 77, 0, 0, 32, 65, 85, 0, 0, 0, 65, 93, 0, 0, 32, 65, 96, -1, -1, -1, -1, -1, -1, -1, -1, -1, 1, 125, 0, 0, -80, 66, -112, 1, 1, -72, 1, 7, 42, 16, 16, -40, -70, -66, -8, -1, -1, -1, -1, -1, 1, 24, 7, -112, 1, 1, 66, 24, 104, 1, -94, -83, -41, -73, 4, 16, -118, 1, 13, 10, 7, 34, 5, 10, 3, 97, 112, 99, 18, 2, 26, 0 };
  private static final byte[] d = { 10, 76, 10, 4, 97, 100, 119, 99, 18, 68, 10, 0, 18, 6, 10, 4, 26, 2, 16, 1, 26, 0, 32, -68, 5, 58, 51, -94, -83, -41, -73, 4, 45, 114, 43, 10, 8, 34, 6, 10, 4, 97, 100, 110, 119, 18, 29, -94, -83, -41, -73, 4, 23, 114, 21, 10, 8, 34, 6, 10, 4, 97, 100, 115, 119, 18, 7, 34, 5, 10, 3, 117, 109, 118, 66, 0, 74, 0, 10, -71, 3, 10, 4, 97, 100, 110, 119, 18, -80, 3, 10, 3, 8, -80, 49, 18, 6, 10, 4, 26, 2, 16, 1, 26, 15, 53, 0, 0, 82, 67, -22, -60, -36, -105, 5, 4, 10, 2, 8, 0, 32, -68, 5, -54, -48, -81, -97, 5, -120, 3, 10, Byte.MIN_VALUE, 1, 18, 20, 69, 0, 0, Byte.MIN_VALUE, 65, 77, 0, 0, Byte.MIN_VALUE, 65, 85, 0, 0, Byte.MIN_VALUE, 65, 93, 0, 0, Byte.MIN_VALUE, 65, -62, 2, 103, 10, 72, 18, 47, 21, 0, 0, 64, 66, 29, 0, 0, 64, 66, 37, 0, 0, Byte.MIN_VALUE, -63, 45, 0, 0, Byte.MIN_VALUE, -63, 53, 0, 0, -64, 65, 69, 0, 0, 64, 65, 77, 0, 0, -96, 65, 114, 0, -94, 1, 4, 26, 2, 16, 1, -16, 1, 14, 42, 21, 8, 21, 26, 17, 8, -31, -62, -123, -5, -1, -1, -1, -1, -1, 1, 24, -64, 1, 32, -64, 1, 18, 27, 34, 25, 13, 0, 0, -96, 65, 16, -95, -62, -124, -7, -1, -1, -1, -1, -1, 1, 24, 6, 32, 1, 48, 2, -120, 1, 4, 18, 20, -70, 2, 17, 18, 7, 34, 5, 10, 3, 117, 109, 118, 26, 4, 26, 2, 16, 1, 82, 0, 26, -20, 1, -70, 1, -24, 1, 10, 56, 8, 0, 18, 52, 34, 19, 29, 0, 0, 64, 66, 96, -40, -70, -66, -8, -1, -1, -1, -1, -1, 1, -40, 1, 4, 42, 29, 16, -1, -1, -1, -1, -1, -1, -1, -1, -1, 1, 24, 7, -112, 1, 1, -115, 2, 10, -41, -93, 60, -104, 2, -1, -1, -1, -113, 6, 10, 94, 8, 1, 18, 90, 34, 57, 37, 0, 0, Byte.MIN_VALUE, 65, 53, 0, 0, Byte.MIN_VALUE, 65, 61, 0, 0, Byte.MIN_VALUE, 65, 69, 0, 0, Byte.MIN_VALUE, 65, 77, 0, 0, 32, 65, 85, 0, 0, Byte.MIN_VALUE, 65, 93, 0, 0, 32, 65, 96, -40, -70, -66, -8, -1, -1, -1, -1, -1, 1, 125, 0, 0, -80, 66, -112, 1, 1, -72, 1, 7, 42, 29, 16, -1, -1, -1, -1, -1, -1, -1, -1, -1, 1, 24, 7, -112, 1, 1, -115, 2, 10, -41, -93, 60, -104, 2, -1, -1, -1, -113, 6, 10, 76, 8, 2, 18, 72, 34, 52, 37, 0, 0, Byte.MIN_VALUE, 65, 61, 0, 0, Byte.MIN_VALUE, 65, 69, 0, 0, 0, 65, 77, 0, 0, 32, 65, 85, 0, 0, 0, 65, 93, 0, 0, 32, 65, 96, -1, -1, -1, -1, -1, -1, -1, -1, -1, 1, 125, 0, 0, -80, 66, -112, 1, 1, -72, 1, 7, 42, 16, 16, -40, -70, -66, -8, -1, -1, -1, -1, -1, 1, 24, 7, -112, 1, 1, 10, -71, 3, 10, 4, 97, 100, 115, 119, 18, -80, 3, 10, 3, 8, -66, 49, 18, 6, 10, 4, 26, 2, 16, 1, 26, 15, 53, 0, 0, 82, 67, -22, -60, -36, -105, 5, 4, 10, 2, 8, 0, 32, -68, 5, -54, -48, -81, -97, 5, -120, 3, 10, Byte.MIN_VALUE, 1, 18, 20, 69, 0, 0, Byte.MIN_VALUE, 65, 77, 0, 0, Byte.MIN_VALUE, 65, 85, 0, 0, Byte.MIN_VALUE, 65, 93, 0, 0, Byte.MIN_VALUE, 65, -62, 2, 103, 10, 72, 18, 47, 21, 0, 0, 64, 66, 29, 0, 0, 64, 66, 37, 0, 0, Byte.MIN_VALUE, -63, 45, 0, 0, Byte.MIN_VALUE, -63, 53, 0, 0, -64, 65, 69, 0, 0, 64, 65, 77, 0, 0, -96, 65, 114, 0, -94, 1, 4, 26, 2, 16, 1, -16, 1, 14, 42, 21, 8, 21, 26, 17, 8, -31, -62, -123, -5, -1, -1, -1, -1, -1, 1, 24, -64, 1, 32, -64, 1, 18, 27, 34, 25, 13, 0, 0, -96, 65, 16, -95, -62, -124, -7, -1, -1, -1, -1, -1, 1, 24, 6, 32, 1, 48, 2, -120, 1, 4, 18, 20, -70, 2, 17, 18, 7, 34, 5, 10, 3, 117, 109, 118, 26, 4, 26, 2, 16, 1, 74, 0, 26, -20, 1, -70, 1, -24, 1, 10, 56, 8, 0, 18, 52, 34, 19, 29, 0, 0, 64, 66, 96, -40, -70, -66, -8, -1, -1, -1, -1, -1, 1, -40, 1, 4, 42, 29, 16, -1, -1, -1, -1, -1, -1, -1, -1, -1, 1, 24, 7, -112, 1, 1, -115, 2, 10, -41, -93, 60, -104, 2, -1, -1, -1, -113, 6, 10, 94, 8, 1, 18, 90, 34, 57, 37, 0, 0, Byte.MIN_VALUE, 65, 53, 0, 0, Byte.MIN_VALUE, 65, 61, 0, 0, Byte.MIN_VALUE, 65, 69, 0, 0, Byte.MIN_VALUE, 65, 77, 0, 0, 32, 65, 85, 0, 0, Byte.MIN_VALUE, 65, 93, 0, 0, 32, 65, 96, -40, -70, -66, -8, -1, -1, -1, -1, -1, 1, 125, 0, 0, -80, 66, -112, 1, 1, -72, 1, 7, 42, 29, 16, -1, -1, -1, -1, -1, -1, -1, -1, -1, 1, 24, 7, -112, 1, 1, -115, 2, 10, -41, -93, 60, -104, 2, -1, -1, -1, -113, 6, 10, 76, 8, 2, 18, 72, 34, 52, 37, 0, 0, Byte.MIN_VALUE, 65, 61, 0, 0, Byte.MIN_VALUE, 65, 69, 0, 0, 0, 65, 77, 0, 0, 32, 65, 85, 0, 0, 0, 65, 93, 0, 0, 32, 65, 96, -1, -1, -1, -1, -1, -1, -1, -1, -1, 1, 125, 0, 0, -80, 66, -112, 1, 1, -72, 1, 7, 42, 16, 16, -40, -70, -66, -8, -1, -1, -1, -1, -1, 1, 24, 7, -112, 1, 1, 10, 50, 10, 3, 97, 112, 99, 18, 43, 10, 0, 18, 4, 10, 2, 26, 0, 26, 0, 32, -68, 5, 58, 28, -94, -83, -41, -73, 4, 22, 114, 20, 10, 6, 34, 4, 10, 2, 97, 112, 18, 8, 34, 6, 10, 4, 97, 100, 119, 99, 50, 0, 10, -74, 2, 10, 2, 97, 112, 18, -81, 2, 10, 3, 8, -105, 6, 18, 4, 10, 2, 26, 0, 26, 15, 53, 0, 0, 82, 67, -22, -60, -36, -105, 5, 4, 10, 2, 8, 0, 32, -106, 6, -54, -48, -81, -97, 5, -119, 2, 10, 3, -62, 2, 0, 18, 19, -70, 2, 16, 18, 8, 34, 6, 10, 4, 97, 100, 119, 99, 26, 2, 26, 0, 50, 0, 26, -20, 1, -70, 1, -24, 1, 10, 56, 8, 0, 18, 52, 34, 19, 29, 0, 0, 64, 66, 96, -40, -70, -66, -8, -1, -1, -1, -1, -1, 1, -40, 1, 4, 42, 29, 16, -1, -1, -1, -1, -1, -1, -1, -1, -1, 1, 24, 7, -112, 1, 1, -115, 2, 10, -41, -93, 60, -104, 2, -1, -1, -1, -113, 6, 10, 94, 8, 1, 18, 90, 34, 57, 37, 0, 0, Byte.MIN_VALUE, 65, 53, 0, 0, Byte.MIN_VALUE, 65, 61, 0, 0, Byte.MIN_VALUE, 65, 69, 0, 0, Byte.MIN_VALUE, 65, 77, 0, 0, 32, 65, 85, 0, 0, Byte.MIN_VALUE, 65, 93, 0, 0, 32, 65, 96, -40, -70, -66, -8, -1, -1, -1, -1, -1, 1, 125, 0, 0, -80, 66, -112, 1, 1, -72, 1, 7, 42, 29, 16, -1, -1, -1, -1, -1, -1, -1, -1, -1, 1, 24, 7, -112, 1, 1, -115, 2, 10, -41, -93, 60, -104, 2, -1, -1, -1, -113, 6, 10, 76, 8, 2, 18, 72, 34, 52, 37, 0, 0, Byte.MIN_VALUE, 65, 61, 0, 0, Byte.MIN_VALUE, 65, 69, 0, 0, 0, 65, 77, 0, 0, 32, 65, 85, 0, 0, 0, 65, 93, 0, 0, 32, 65, 96, -1, -1, -1, -1, -1, -1, -1, -1, -1, 1, 125, 0, 0, -80, 66, -112, 1, 1, -72, 1, 7, 42, 16, 16, -40, -70, -66, -8, -1, -1, -1, -1, -1, 1, 24, 7, -112, 1, 1, 10, 53, 10, 3, 117, 109, 118, 18, 46, 10, 0, 18, 6, 10, 4, 26, 2, 16, 1, 26, 0, 32, -68, 5, 58, 29, -94, -83, -41, -73, 4, 23, 114, 21, 10, 6, 34, 4, 10, 2, 117, 109, 18, 9, -126, 1, 6, 18, 4, 26, 2, 16, 1, 58, 0, 10, -72, 2, 10, 2, 117, 109, 18, -79, 2, 10, 0, 18, 6, 10, 4, 26, 2, 16, 1, 26, 15, 53, 0, 0, 82, 67, -22, -60, -36, -105, 5, 4, 10, 2, 8, 0, 32, -68, 5, -54, -48, -81, -97, 5, -116, 2, 10, 3, -62, 2, 0, 18, 22, -70, 2, 19, 18, 9, -126, 1, 6, 18, 4, 26, 2, 16, 1, 26, 4, 26, 2, 16, 1, 58, 0, 26, -20, 1, -70, 1, -24, 1, 10, 56, 8, 0, 18, 52, 34, 19, 29, 0, 0, 64, 66, 96, -40, -70, -66, -8, -1, -1, -1, -1, -1, 1, -40, 1, 4, 42, 29, 16, -1, -1, -1, -1, -1, -1, -1, -1, -1, 1, 24, 7, -112, 1, 1, -115, 2, 10, -41, -93, 60, -104, 2, -1, -1, -1, -113, 6, 10, 94, 8, 1, 18, 90, 34, 57, 37, 0, 0, Byte.MIN_VALUE, 65, 53, 0, 0, Byte.MIN_VALUE, 65, 61, 0, 0, Byte.MIN_VALUE, 65, 69, 0, 0, Byte.MIN_VALUE, 65, 77, 0, 0, 32, 65, 85, 0, 0, Byte.MIN_VALUE, 65, 93, 0, 0, 32, 65, 96, -40, -70, -66, -8, -1, -1, -1, -1, -1, 1, 125, 0, 0, -80, 66, -112, 1, 1, -72, 1, 7, 42, 29, 16, -1, -1, -1, -1, -1, -1, -1, -1, -1, 1, 24, 7, -112, 1, 1, -115, 2, 10, -41, -93, 60, -104, 2, -1, -1, -1, -113, 6, 10, 76, 8, 2, 18, 72, 34, 52, 37, 0, 0, Byte.MIN_VALUE, 65, 61, 0, 0, Byte.MIN_VALUE, 65, 69, 0, 0, 0, 65, 77, 0, 0, 32, 65, 85, 0, 0, 0, 65, 93, 0, 0, 32, 65, 96, -1, -1, -1, -1, -1, -1, -1, -1, -1, 1, 125, 0, 0, -80, 66, -112, 1, 1, -72, 1, 7, 42, 16, 16, -40, -70, -66, -8, -1, -1, -1, -1, -1, 1, 24, 7, -112, 1, 1, 66, 24, 104, 1, -94, -83, -41, -73, 4, 16, -118, 1, 13, 10, 7, 34, 5, 10, 3, 97, 112, 99, 18, 2, 26, 0 };
  public boolean a = false;
  private final boolean e;
  private final boolean f;
  private final boolean g;
  
  public p(f paramf, Bundle paramBundle)
  {
    this.e = (paramf.a(12660138L) ^ true);
    this.f = (paramf.a(12660139L) ^ true);
    this.g = (paramf.a(12660372L) ^ true);
    if (paramBundle != null) {
      this.a = paramBundle.getBoolean("DialogInitialScreenInstructionsModel.isInstructionsAlreadyFetched");
    }
  }
  
  /* Error */
  public final com.google.common.base.u a(com.google.wireless.android.finsky.dfe.e.a.ak paramak)
  {
    // Byte code:
    //   0: aload_0
    //   1: getfield 28	com/google/android/finsky/be/p:a	Z
    //   4: ifne +12 -> 16
    //   7: aload_1
    //   8: getfield 61	com/google/wireless/android/finsky/dfe/e/a/ak:e	I
    //   11: iconst_1
    //   12: iand
    //   13: ifeq +7 -> 20
    //   16: getstatic 66	com/google/common/base/a:a	Lcom/google/common/base/a;
    //   19: areturn
    //   20: aload_1
    //   21: getfield 69	com/google/wireless/android/finsky/dfe/e/a/ak:i	I
    //   24: iconst_2
    //   25: if_icmpne +141 -> 166
    //   28: aload_1
    //   29: getfield 72	com/google/wireless/android/finsky/dfe/e/a/ak:b	Lcom/google/wireless/android/finsky/dfe/e/a/ae;
    //   32: astore_2
    //   33: aload_2
    //   34: ifnull +128 -> 162
    //   37: aload_2
    //   38: getfield 76	com/google/wireless/android/finsky/dfe/e/a/ae:d	Z
    //   41: ifne +121 -> 162
    //   44: aload_2
    //   45: getfield 79	com/google/wireless/android/finsky/dfe/e/a/ae:c	Lcom/google/android/finsky/ds/a/bp;
    //   48: astore_2
    //   49: aload_2
    //   50: ifnull +112 -> 162
    //   53: aload_2
    //   54: getfield 83	com/google/android/finsky/ds/a/bp:c	I
    //   57: iconst_1
    //   58: if_icmpne +104 -> 162
    //   61: aload_1
    //   62: getfield 86	com/google/wireless/android/finsky/dfe/e/a/ak:n	Z
    //   65: ifne +69 -> 134
    //   68: aload_0
    //   69: getfield 37	com/google/android/finsky/be/p:e	Z
    //   72: ifne +38 -> 110
    //   75: aload_0
    //   76: getfield 41	com/google/android/finsky/be/p:f	Z
    //   79: ifeq +27 -> 106
    //   82: aload_1
    //   83: getfield 89	com/google/wireless/android/finsky/dfe/e/a/ak:t	Z
    //   86: ifne +20 -> 106
    //   89: aload_0
    //   90: iconst_1
    //   91: putfield 28	com/google/android/finsky/be/p:a	Z
    //   94: getstatic 17	com/google/android/finsky/be/p:c	[B
    //   97: invokestatic 94	com/google/wireless/android/finsky/dfe/e/a/am:a	([B)Lcom/google/wireless/android/finsky/dfe/e/a/am;
    //   100: invokestatic 99	com/google/common/base/u:b	(Ljava/lang/Object;)Lcom/google/common/base/u;
    //   103: astore_1
    //   104: aload_1
    //   105: areturn
    //   106: getstatic 66	com/google/common/base/a:a	Lcom/google/common/base/a;
    //   109: areturn
    //   110: aload_1
    //   111: getfield 89	com/google/wireless/android/finsky/dfe/e/a/ak:t	Z
    //   114: ifeq -39 -> 75
    //   117: aload_0
    //   118: iconst_1
    //   119: putfield 28	com/google/android/finsky/be/p:a	Z
    //   122: getstatic 19	com/google/android/finsky/be/p:b	[B
    //   125: invokestatic 94	com/google/wireless/android/finsky/dfe/e/a/am:a	([B)Lcom/google/wireless/android/finsky/dfe/e/a/am;
    //   128: invokestatic 99	com/google/common/base/u:b	(Ljava/lang/Object;)Lcom/google/common/base/u;
    //   131: astore_1
    //   132: aload_1
    //   133: areturn
    //   134: aload_0
    //   135: getfield 45	com/google/android/finsky/be/p:g	Z
    //   138: ifeq +20 -> 158
    //   141: aload_0
    //   142: iconst_1
    //   143: putfield 28	com/google/android/finsky/be/p:a	Z
    //   146: getstatic 21	com/google/android/finsky/be/p:d	[B
    //   149: invokestatic 94	com/google/wireless/android/finsky/dfe/e/a/am:a	([B)Lcom/google/wireless/android/finsky/dfe/e/a/am;
    //   152: invokestatic 99	com/google/common/base/u:b	(Ljava/lang/Object;)Lcom/google/common/base/u;
    //   155: astore_1
    //   156: aload_1
    //   157: areturn
    //   158: getstatic 66	com/google/common/base/a:a	Lcom/google/common/base/a;
    //   161: areturn
    //   162: getstatic 66	com/google/common/base/a:a	Lcom/google/common/base/a;
    //   165: areturn
    //   166: getstatic 66	com/google/common/base/a:a	Lcom/google/common/base/a;
    //   169: areturn
    //   170: astore_1
    //   171: getstatic 66	com/google/common/base/a:a	Lcom/google/common/base/a;
    //   174: areturn
    //   175: astore_1
    //   176: getstatic 66	com/google/common/base/a:a	Lcom/google/common/base/a;
    //   179: areturn
    //   180: astore_1
    //   181: getstatic 66	com/google/common/base/a:a	Lcom/google/common/base/a;
    //   184: areturn
    // Local variable table:
    //   start	length	slot	name	signature
    //   0	185	0	this	p
    //   0	185	1	paramak	com.google.wireless.android.finsky.dfe.e.a.ak
    //   32	22	2	localObject	Object
    // Exception table:
    //   from	to	target	type
    //   89	104	170	java/lang/Exception
    //   117	132	175	java/lang/Exception
    //   141	156	180	java/lang/Exception
  }
}


/* Location:              /home/chengjian/CM_test/gp/apk/a.jar!/com/google/android/finsky/be/p.class
 * Java compiler version: 6 (50.0)
 * JD-Core Version:       0.7.1
 */