package android.support.f;

final class au
{
  /* Error */
  static void a(android.view.ViewGroup paramViewGroup, boolean paramBoolean)
  {
    // Byte code:
    //   0: iconst_0
    //   1: istore_2
    //   2: getstatic 20	android/os/Build$VERSION:SDK_INT	I
    //   5: bipush 18
    //   7: if_icmpge +269 -> 276
    //   10: getstatic 26	android/support/f/av:c	Landroid/animation/LayoutTransition;
    //   13: ifnonnull +53 -> 66
    //   16: new 28	android/support/f/aw
    //   19: dup
    //   20: invokespecial 32	android/support/f/aw:<init>	()V
    //   23: astore_3
    //   24: aload_3
    //   25: putstatic 26	android/support/f/av:c	Landroid/animation/LayoutTransition;
    //   28: aload_3
    //   29: iconst_2
    //   30: aconst_null
    //   31: invokevirtual 38	android/animation/LayoutTransition:setAnimator	(ILandroid/animation/Animator;)V
    //   34: getstatic 26	android/support/f/av:c	Landroid/animation/LayoutTransition;
    //   37: iconst_0
    //   38: aconst_null
    //   39: invokevirtual 38	android/animation/LayoutTransition:setAnimator	(ILandroid/animation/Animator;)V
    //   42: getstatic 26	android/support/f/av:c	Landroid/animation/LayoutTransition;
    //   45: iconst_1
    //   46: aconst_null
    //   47: invokevirtual 38	android/animation/LayoutTransition:setAnimator	(ILandroid/animation/Animator;)V
    //   50: getstatic 26	android/support/f/av:c	Landroid/animation/LayoutTransition;
    //   53: iconst_3
    //   54: aconst_null
    //   55: invokevirtual 38	android/animation/LayoutTransition:setAnimator	(ILandroid/animation/Animator;)V
    //   58: getstatic 26	android/support/f/av:c	Landroid/animation/LayoutTransition;
    //   61: iconst_4
    //   62: aconst_null
    //   63: invokevirtual 38	android/animation/LayoutTransition:setAnimator	(ILandroid/animation/Animator;)V
    //   66: iload_1
    //   67: ifne +103 -> 170
    //   70: aload_0
    //   71: aconst_null
    //   72: invokevirtual 44	android/view/ViewGroup:setLayoutTransition	(Landroid/animation/LayoutTransition;)V
    //   75: getstatic 48	android/support/f/av:e	Z
    //   78: ifne +24 -> 102
    //   81: ldc 40
    //   83: ldc 50
    //   85: invokevirtual 56	java/lang/Class:getDeclaredField	(Ljava/lang/String;)Ljava/lang/reflect/Field;
    //   88: astore_3
    //   89: aload_3
    //   90: putstatic 60	android/support/f/av:d	Ljava/lang/reflect/Field;
    //   93: aload_3
    //   94: iconst_1
    //   95: invokevirtual 66	java/lang/reflect/Field:setAccessible	(Z)V
    //   98: iconst_1
    //   99: putstatic 48	android/support/f/av:e	Z
    //   102: getstatic 60	android/support/f/av:d	Ljava/lang/reflect/Field;
    //   105: ifnull +31 -> 136
    //   108: getstatic 60	android/support/f/av:d	Ljava/lang/reflect/Field;
    //   111: aload_0
    //   112: invokevirtual 70	java/lang/reflect/Field:getBoolean	(Ljava/lang/Object;)Z
    //   115: istore_1
    //   116: iload_1
    //   117: istore_2
    //   118: iload_1
    //   119: ifeq +13 -> 132
    //   122: getstatic 60	android/support/f/av:d	Ljava/lang/reflect/Field;
    //   125: aload_0
    //   126: iconst_0
    //   127: invokevirtual 74	java/lang/reflect/Field:setBoolean	(Ljava/lang/Object;Z)V
    //   130: iload_1
    //   131: istore_2
    //   132: iload_2
    //   133: ifne +30 -> 163
    //   136: aload_0
    //   137: ldc 75
    //   139: invokevirtual 79	android/view/ViewGroup:getTag	(I)Ljava/lang/Object;
    //   142: checkcast 34	android/animation/LayoutTransition
    //   145: astore_3
    //   146: aload_3
    //   147: ifnull +15 -> 162
    //   150: aload_0
    //   151: ldc 75
    //   153: aconst_null
    //   154: invokevirtual 83	android/view/ViewGroup:setTag	(ILjava/lang/Object;)V
    //   157: aload_0
    //   158: aload_3
    //   159: invokevirtual 44	android/view/ViewGroup:setLayoutTransition	(Landroid/animation/LayoutTransition;)V
    //   162: return
    //   163: aload_0
    //   164: invokevirtual 86	android/view/ViewGroup:requestLayout	()V
    //   167: goto -31 -> 136
    //   170: aload_0
    //   171: invokevirtual 90	android/view/ViewGroup:getLayoutTransition	()Landroid/animation/LayoutTransition;
    //   174: astore_3
    //   175: aload_3
    //   176: ifnull +24 -> 200
    //   179: aload_3
    //   180: invokevirtual 94	android/animation/LayoutTransition:isRunning	()Z
    //   183: ifne +25 -> 208
    //   186: aload_3
    //   187: getstatic 26	android/support/f/av:c	Landroid/animation/LayoutTransition;
    //   190: if_acmpeq +10 -> 200
    //   193: aload_0
    //   194: ldc 75
    //   196: aload_3
    //   197: invokevirtual 83	android/view/ViewGroup:setTag	(ILjava/lang/Object;)V
    //   200: aload_0
    //   201: getstatic 26	android/support/f/av:c	Landroid/animation/LayoutTransition;
    //   204: invokevirtual 44	android/view/ViewGroup:setLayoutTransition	(Landroid/animation/LayoutTransition;)V
    //   207: return
    //   208: getstatic 97	android/support/f/av:b	Z
    //   211: ifne +31 -> 242
    //   214: ldc 34
    //   216: ldc 99
    //   218: iconst_0
    //   219: anewarray 52	java/lang/Class
    //   222: invokevirtual 103	java/lang/Class:getDeclaredMethod	(Ljava/lang/String;[Ljava/lang/Class;)Ljava/lang/reflect/Method;
    //   225: astore 4
    //   227: aload 4
    //   229: putstatic 106	android/support/f/av:a	Ljava/lang/reflect/Method;
    //   232: aload 4
    //   234: iconst_1
    //   235: invokevirtual 109	java/lang/reflect/Method:setAccessible	(Z)V
    //   238: iconst_1
    //   239: putstatic 97	android/support/f/av:b	Z
    //   242: getstatic 106	android/support/f/av:a	Ljava/lang/reflect/Method;
    //   245: ifnull -59 -> 186
    //   248: getstatic 106	android/support/f/av:a	Ljava/lang/reflect/Method;
    //   251: aload_3
    //   252: iconst_0
    //   253: anewarray 4	java/lang/Object
    //   256: invokevirtual 113	java/lang/reflect/Method:invoke	(Ljava/lang/Object;[Ljava/lang/Object;)Ljava/lang/Object;
    //   259: pop
    //   260: goto -74 -> 186
    //   263: astore 4
    //   265: ldc 115
    //   267: ldc 117
    //   269: invokestatic 123	android/util/Log:i	(Ljava/lang/String;Ljava/lang/String;)I
    //   272: pop
    //   273: goto -87 -> 186
    //   276: getstatic 126	android/support/f/ax:b	Z
    //   279: ifne +34 -> 313
    //   282: ldc 40
    //   284: ldc -128
    //   286: iconst_1
    //   287: anewarray 52	java/lang/Class
    //   290: dup
    //   291: iconst_0
    //   292: getstatic 134	java/lang/Boolean:TYPE	Ljava/lang/Class;
    //   295: aastore
    //   296: invokevirtual 103	java/lang/Class:getDeclaredMethod	(Ljava/lang/String;[Ljava/lang/Class;)Ljava/lang/reflect/Method;
    //   299: astore_3
    //   300: aload_3
    //   301: putstatic 135	android/support/f/ax:a	Ljava/lang/reflect/Method;
    //   304: aload_3
    //   305: iconst_1
    //   306: invokevirtual 109	java/lang/reflect/Method:setAccessible	(Z)V
    //   309: iconst_1
    //   310: putstatic 126	android/support/f/ax:b	Z
    //   313: getstatic 135	android/support/f/ax:a	Ljava/lang/reflect/Method;
    //   316: ifnull -154 -> 162
    //   319: getstatic 135	android/support/f/ax:a	Ljava/lang/reflect/Method;
    //   322: aload_0
    //   323: iconst_1
    //   324: anewarray 4	java/lang/Object
    //   327: dup
    //   328: iconst_0
    //   329: iload_1
    //   330: invokestatic 139	java/lang/Boolean:valueOf	(Z)Ljava/lang/Boolean;
    //   333: aastore
    //   334: invokevirtual 113	java/lang/reflect/Method:invoke	(Ljava/lang/Object;[Ljava/lang/Object;)Ljava/lang/Object;
    //   337: pop
    //   338: return
    //   339: astore_0
    //   340: ldc -115
    //   342: ldc -113
    //   344: aload_0
    //   345: invokestatic 146	android/util/Log:i	(Ljava/lang/String;Ljava/lang/String;Ljava/lang/Throwable;)I
    //   348: pop
    //   349: return
    //   350: astore_3
    //   351: ldc 115
    //   353: ldc -108
    //   355: invokestatic 123	android/util/Log:i	(Ljava/lang/String;Ljava/lang/String;)I
    //   358: pop
    //   359: goto -261 -> 98
    //   362: astore_3
    //   363: ldc 115
    //   365: ldc -106
    //   367: invokestatic 123	android/util/Log:i	(Ljava/lang/String;Ljava/lang/String;)I
    //   370: pop
    //   371: iload_1
    //   372: istore_2
    //   373: goto -241 -> 132
    //   376: astore 4
    //   378: ldc 115
    //   380: ldc 117
    //   382: invokestatic 123	android/util/Log:i	(Ljava/lang/String;Ljava/lang/String;)I
    //   385: pop
    //   386: goto -148 -> 238
    //   389: astore 4
    //   391: ldc 115
    //   393: ldc -104
    //   395: invokestatic 123	android/util/Log:i	(Ljava/lang/String;Ljava/lang/String;)I
    //   398: pop
    //   399: goto -213 -> 186
    //   402: astore_3
    //   403: ldc -115
    //   405: ldc -102
    //   407: aload_3
    //   408: invokestatic 146	android/util/Log:i	(Ljava/lang/String;Ljava/lang/String;Ljava/lang/Throwable;)I
    //   411: pop
    //   412: goto -103 -> 309
    //   415: astore_0
    //   416: ldc -115
    //   418: ldc -100
    //   420: aload_0
    //   421: invokestatic 146	android/util/Log:i	(Ljava/lang/String;Ljava/lang/String;Ljava/lang/Throwable;)I
    //   424: pop
    //   425: return
    //   426: astore_3
    //   427: iload_2
    //   428: istore_1
    //   429: goto -66 -> 363
    // Local variable table:
    //   start	length	slot	name	signature
    //   0	432	0	paramViewGroup	android.view.ViewGroup
    //   0	432	1	paramBoolean	boolean
    //   1	427	2	bool	boolean
    //   23	282	3	localObject	Object
    //   350	1	3	localNoSuchFieldException	NoSuchFieldException
    //   362	1	3	localIllegalAccessException1	IllegalAccessException
    //   402	6	3	localNoSuchMethodException1	NoSuchMethodException
    //   426	1	3	localIllegalAccessException2	IllegalAccessException
    //   225	8	4	localMethod	java.lang.reflect.Method
    //   263	1	4	localIllegalAccessException3	IllegalAccessException
    //   376	1	4	localNoSuchMethodException2	NoSuchMethodException
    //   389	1	4	localInvocationTargetException	java.lang.reflect.InvocationTargetException
    // Exception table:
    //   from	to	target	type
    //   248	260	263	java/lang/IllegalAccessException
    //   319	338	339	java/lang/IllegalAccessException
    //   81	98	350	java/lang/NoSuchFieldException
    //   122	130	362	java/lang/IllegalAccessException
    //   214	238	376	java/lang/NoSuchMethodException
    //   248	260	389	java/lang/reflect/InvocationTargetException
    //   282	309	402	java/lang/NoSuchMethodException
    //   319	338	415	java/lang/reflect/InvocationTargetException
    //   108	116	426	java/lang/IllegalAccessException
  }
}


/* Location:              /home/chengjian/CM_test/gp/apk/a.jar!/android/support/f/au.class
 * Java compiler version: 6 (50.0)
 * JD-Core Version:       0.7.1
 */