package com.google.android.gms.ads.internal.reward.mediation;

import android.content.Context;
import android.text.TextUtils;
import com.google.android.gms.ads.internal.client.AdRequestParcel;
import com.google.android.gms.ads.internal.client.AdSizeParcel;
import com.google.android.gms.ads.internal.f.n;
import com.google.android.gms.ads.internal.request.AdRequestInfoParcel;
import com.google.android.gms.ads.internal.request.AdResponseParcel;
import com.google.android.gms.ads.internal.reward.mediation.client.RewardItemParcel;
import java.util.ArrayList;
import java.util.HashSet;
import java.util.Iterator;
import java.util.List;
import org.json.JSONObject;

@com.google.android.gms.ads.internal.q.a.a
public final class j
  extends com.google.android.gms.ads.internal.util.a
  implements i
{
  public final com.google.android.gms.ads.internal.reward.a a;
  private final Context b;
  private final ArrayList c = new ArrayList();
  private final HashSet d = new HashSet();
  private final Object e = new Object();
  private final com.google.android.gms.ads.internal.v.b f;
  private final List g = new ArrayList();
  private final long h;
  
  public j(Context paramContext, com.google.android.gms.ads.internal.v.b paramb, com.google.android.gms.ads.internal.reward.a parama)
  {
    this(paramContext, paramb, parama, ((Long)n.bx.a()).longValue());
  }
  
  private j(Context paramContext, com.google.android.gms.ads.internal.v.b paramb, com.google.android.gms.ads.internal.reward.a parama, long paramLong)
  {
    this.b = paramContext;
    this.f = paramb;
    this.a = parama;
    this.h = paramLong;
  }
  
  private final com.google.android.gms.ads.internal.v.a a(int paramInt, String paramString, com.google.android.gms.ads.internal.mediation.b paramb)
  {
    Object localObject3 = this.f;
    Object localObject2 = ((com.google.android.gms.ads.internal.v.b)localObject3).d;
    AdRequestParcel localAdRequestParcel = ((AdRequestInfoParcel)localObject2).b;
    Object localObject1 = ((com.google.android.gms.ads.internal.v.b)localObject3).e;
    List localList1 = ((AdResponseParcel)localObject1).g;
    List localList2 = ((AdResponseParcel)localObject1).q;
    List localList3 = ((AdResponseParcel)localObject1).F;
    int j = ((AdResponseParcel)localObject1).K;
    long l1 = ((AdResponseParcel)localObject1).M;
    localObject2 = ((AdRequestInfoParcel)localObject2).X;
    boolean bool1 = ((AdResponseParcel)localObject1).y;
    com.google.android.gms.ads.internal.mediation.c localc = ((com.google.android.gms.ads.internal.v.b)localObject3).i;
    long l2 = ((AdResponseParcel)localObject1).G;
    AdSizeParcel localAdSizeParcel = ((com.google.android.gms.ads.internal.v.b)localObject3).g;
    l2 = ((AdResponseParcel)localObject1).r;
    l2 = ((com.google.android.gms.ads.internal.v.b)localObject3).f;
    long l3 = ((AdResponseParcel)localObject1).o;
    String str1 = ((AdResponseParcel)localObject1).k;
    localObject3 = ((com.google.android.gms.ads.internal.v.b)localObject3).a;
    RewardItemParcel localRewardItemParcel = ((AdResponseParcel)localObject1).P;
    List localList4 = ((AdResponseParcel)localObject1).Q;
    List localList5 = ((AdResponseParcel)localObject1).O;
    boolean bool2 = ((AdResponseParcel)localObject1).E;
    localObject1 = ((AdResponseParcel)localObject1).d;
    localObject1 = new StringBuilder("");
    Object localObject4 = this.g;
    if (localObject4 == null) {}
    for (localObject1 = ((StringBuilder)localObject1).toString();; localObject1 = ((StringBuilder)localObject1).substring(0, Math.max(0, ((StringBuilder)localObject1).length() - 1)))
    {
      Object localObject7 = this.f;
      localObject4 = ((com.google.android.gms.ads.internal.v.b)localObject7).e;
      Object localObject5 = ((AdResponseParcel)localObject4).H;
      Object localObject6 = ((AdResponseParcel)localObject4).l;
      com.google.android.gms.ads.internal.d.a locala = ((com.google.android.gms.ads.internal.v.b)localObject7).c;
      boolean bool3 = ((AdResponseParcel)localObject4).u;
      boolean bool4 = ((com.google.android.gms.ads.internal.v.b)localObject7).j;
      boolean bool5 = ((AdResponseParcel)localObject4).C;
      localObject7 = ((AdResponseParcel)localObject4).m;
      boolean bool6 = ((AdResponseParcel)localObject4).t;
      String str2 = ((AdResponseParcel)localObject4).J;
      return new com.google.android.gms.ads.internal.v.a(localAdRequestParcel, null, localList1, paramInt, localList2, localList3, j, l1, (String)localObject2, bool1, paramb, null, paramString, localc, null, localAdSizeParcel, l2, l3, str1, (JSONObject)localObject3, null, localRewardItemParcel, localList4, localList5, bool2, (String)localObject1, (List)localObject5, (String)localObject6, locala, bool3, bool4, bool5, (List)localObject7, bool6, ((AdResponseParcel)localObject4).S);
      localObject4 = ((List)localObject4).iterator();
      while (((Iterator)localObject4).hasNext())
      {
        localObject6 = (d)((Iterator)localObject4).next();
        if ((localObject6 != null) && (!TextUtils.isEmpty(((d)localObject6).a)))
        {
          localObject5 = ((d)localObject6).a;
          int i;
          switch (((d)localObject6).b)
          {
          default: 
            i = 6;
          }
          for (;;)
          {
            long l4 = ((d)localObject6).c;
            localObject6 = new StringBuilder(String.valueOf(localObject5).length() + 33);
            ((StringBuilder)localObject6).append((String)localObject5);
            ((StringBuilder)localObject6).append(".");
            ((StringBuilder)localObject6).append(i);
            ((StringBuilder)localObject6).append(".");
            ((StringBuilder)localObject6).append(l4);
            ((StringBuilder)localObject1).append(String.valueOf(((StringBuilder)localObject6).toString()).concat("_"));
            break;
            i = 1;
            continue;
            i = 3;
            continue;
            i = 0;
            continue;
            i = 4;
            continue;
            i = 2;
          }
        }
      }
    }
  }
  
  /* Error */
  public final void a()
  {
    // Byte code:
    //   0: aload_0
    //   1: getfield 70	com/google/android/gms/ads/internal/reward/mediation/j:f	Lcom/google/android/gms/ads/internal/v/b;
    //   4: getfield 116	com/google/android/gms/ads/internal/v/b:i	Lcom/google/android/gms/ads/internal/mediation/c;
    //   7: getfield 278	com/google/android/gms/ads/internal/mediation/c:a	Ljava/util/List;
    //   10: invokeinterface 203 1 0
    //   15: astore 4
    //   17: aload 4
    //   19: invokeinterface 209 1 0
    //   24: ifeq +249 -> 273
    //   27: aload 4
    //   29: invokeinterface 212 1 0
    //   34: checkcast 280	com/google/android/gms/ads/internal/mediation/b
    //   37: astore 5
    //   39: aload 5
    //   41: getfield 283	com/google/android/gms/ads/internal/mediation/b:s	Ljava/lang/String;
    //   44: astore 6
    //   46: aload 5
    //   48: getfield 285	com/google/android/gms/ads/internal/mediation/b:f	Ljava/util/List;
    //   51: invokeinterface 203 1 0
    //   56: astore 7
    //   58: aload 7
    //   60: invokeinterface 209 1 0
    //   65: ifeq -48 -> 17
    //   68: aload 7
    //   70: invokeinterface 212 1 0
    //   75: checkcast 228	java/lang/String
    //   78: astore_3
    //   79: ldc_w 287
    //   82: aload_3
    //   83: invokevirtual 291	java/lang/String:equals	(Ljava/lang/Object;)Z
    //   86: ifne +13 -> 99
    //   89: ldc_w 293
    //   92: aload_3
    //   93: invokevirtual 291	java/lang/String:equals	(Ljava/lang/Object;)Z
    //   96: ifeq +174 -> 270
    //   99: new 295	org/json/JSONObject
    //   102: dup
    //   103: aload 6
    //   105: invokespecial 296	org/json/JSONObject:<init>	(Ljava/lang/String;)V
    //   108: ldc_w 298
    //   111: invokevirtual 301	org/json/JSONObject:getString	(Ljava/lang/String;)Ljava/lang/String;
    //   114: astore_3
    //   115: aload_0
    //   116: getfield 66	com/google/android/gms/ads/internal/reward/mediation/j:e	Ljava/lang/Object;
    //   119: astore 8
    //   121: aload 8
    //   123: monitorenter
    //   124: aload_0
    //   125: getfield 72	com/google/android/gms/ads/internal/reward/mediation/j:a	Lcom/google/android/gms/ads/internal/reward/a;
    //   128: aload_3
    //   129: invokevirtual 306	com/google/android/gms/ads/internal/reward/a:a	(Ljava/lang/String;)Lcom/google/android/gms/ads/internal/reward/mediation/n;
    //   132: astore 9
    //   134: aload 9
    //   136: ifnonnull +64 -> 200
    //   139: aload_0
    //   140: getfield 56	com/google/android/gms/ads/internal/reward/mediation/j:g	Ljava/util/List;
    //   143: astore_3
    //   144: new 308	com/google/android/gms/ads/internal/reward/mediation/e
    //   147: dup
    //   148: invokespecial 309	com/google/android/gms/ads/internal/reward/mediation/e:<init>	()V
    //   151: astore 9
    //   153: aload 9
    //   155: aload 5
    //   157: getfield 311	com/google/android/gms/ads/internal/mediation/b:g	Ljava/lang/String;
    //   160: putfield 312	com/google/android/gms/ads/internal/reward/mediation/e:a	Ljava/lang/String;
    //   163: aload 9
    //   165: lconst_0
    //   166: putfield 313	com/google/android/gms/ads/internal/reward/mediation/e:c	J
    //   169: aload 9
    //   171: bipush 7
    //   173: putfield 314	com/google/android/gms/ads/internal/reward/mediation/e:b	I
    //   176: aload_3
    //   177: aload 9
    //   179: invokevirtual 317	com/google/android/gms/ads/internal/reward/mediation/e:a	()Lcom/google/android/gms/ads/internal/reward/mediation/d;
    //   182: invokeinterface 320 2 0
    //   187: pop
    //   188: aload 8
    //   190: monitorexit
    //   191: goto -133 -> 58
    //   194: astore_3
    //   195: aload 8
    //   197: monitorexit
    //   198: aload_3
    //   199: athrow
    //   200: aload 9
    //   202: getfield 325	com/google/android/gms/ads/internal/reward/mediation/n:b	Lcom/google/android/gms/ads/internal/reward/mediation/h;
    //   205: ifnull -66 -> 139
    //   208: aload 9
    //   210: getfield 328	com/google/android/gms/ads/internal/reward/mediation/n:a	Lcom/google/android/gms/ads/internal/mediation/client/e;
    //   213: ifnull -74 -> 139
    //   216: new 330	com/google/android/gms/ads/internal/reward/mediation/a
    //   219: dup
    //   220: aload_0
    //   221: getfield 68	com/google/android/gms/ads/internal/reward/mediation/j:b	Landroid/content/Context;
    //   224: aload_3
    //   225: aload 6
    //   227: aload 5
    //   229: aload_0
    //   230: getfield 70	com/google/android/gms/ads/internal/reward/mediation/j:f	Lcom/google/android/gms/ads/internal/v/b;
    //   233: aload 9
    //   235: aload_0
    //   236: aload_0
    //   237: getfield 74	com/google/android/gms/ads/internal/reward/mediation/j:h	J
    //   240: invokespecial 333	com/google/android/gms/ads/internal/reward/mediation/a:<init>	(Landroid/content/Context;Ljava/lang/String;Ljava/lang/String;Lcom/google/android/gms/ads/internal/mediation/b;Lcom/google/android/gms/ads/internal/v/b;Lcom/google/android/gms/ads/internal/reward/mediation/n;Lcom/google/android/gms/ads/internal/reward/mediation/i;J)V
    //   243: astore_3
    //   244: aload_3
    //   245: aload_0
    //   246: getfield 72	com/google/android/gms/ads/internal/reward/mediation/j:a	Lcom/google/android/gms/ads/internal/reward/a;
    //   249: getfield 336	com/google/android/gms/ads/internal/reward/a:a	Lcom/google/android/gms/ads/internal/gmsg/b;
    //   252: putfield 337	com/google/android/gms/ads/internal/reward/mediation/a:a	Lcom/google/android/gms/ads/internal/gmsg/b;
    //   255: aload_0
    //   256: getfield 54	com/google/android/gms/ads/internal/reward/mediation/j:c	Ljava/util/ArrayList;
    //   259: aload_3
    //   260: invokevirtual 338	java/util/ArrayList:add	(Ljava/lang/Object;)Z
    //   263: pop
    //   264: aload 8
    //   266: monitorexit
    //   267: goto -209 -> 58
    //   270: goto -155 -> 115
    //   273: new 58	java/util/HashSet
    //   276: dup
    //   277: invokespecial 59	java/util/HashSet:<init>	()V
    //   280: astore_3
    //   281: aload_0
    //   282: getfield 54	com/google/android/gms/ads/internal/reward/mediation/j:c	Ljava/util/ArrayList;
    //   285: astore 4
    //   287: aload 4
    //   289: invokevirtual 341	java/util/ArrayList:size	()I
    //   292: istore_2
    //   293: iconst_0
    //   294: istore_1
    //   295: iload_1
    //   296: iload_2
    //   297: if_icmpge +44 -> 341
    //   300: aload 4
    //   302: iload_1
    //   303: invokevirtual 345	java/util/ArrayList:get	(I)Ljava/lang/Object;
    //   306: checkcast 330	com/google/android/gms/ads/internal/reward/mediation/a
    //   309: astore 5
    //   311: aload_3
    //   312: aload 5
    //   314: getfield 347	com/google/android/gms/ads/internal/reward/mediation/a:b	Ljava/lang/String;
    //   317: invokeinterface 350 2 0
    //   322: ifne +10 -> 332
    //   325: iload_1
    //   326: iconst_1
    //   327: iadd
    //   328: istore_1
    //   329: goto -34 -> 295
    //   332: aload 5
    //   334: invokevirtual 353	com/google/android/gms/ads/internal/reward/mediation/a:d	()Ljava/util/concurrent/Future;
    //   337: pop
    //   338: goto -13 -> 325
    //   341: aload_0
    //   342: getfield 54	com/google/android/gms/ads/internal/reward/mediation/j:c	Ljava/util/ArrayList;
    //   345: astore 4
    //   347: aload 4
    //   349: invokevirtual 341	java/util/ArrayList:size	()I
    //   352: istore_2
    //   353: iconst_0
    //   354: istore_1
    //   355: iload_1
    //   356: iload_2
    //   357: if_icmplt +28 -> 385
    //   360: aload_0
    //   361: iconst_3
    //   362: aconst_null
    //   363: aconst_null
    //   364: invokespecial 355	com/google/android/gms/ads/internal/reward/mediation/j:a	(ILjava/lang/String;Lcom/google/android/gms/ads/internal/mediation/b;)Lcom/google/android/gms/ads/internal/v/a;
    //   367: astore_3
    //   368: getstatic 360	com/google/android/gms/ads/internal/util/client/a:g	Landroid/os/Handler;
    //   371: new 362	com/google/android/gms/ads/internal/reward/mediation/l
    //   374: dup
    //   375: aload_0
    //   376: aload_3
    //   377: invokespecial 365	com/google/android/gms/ads/internal/reward/mediation/l:<init>	(Lcom/google/android/gms/ads/internal/reward/mediation/j;Lcom/google/android/gms/ads/internal/v/a;)V
    //   380: invokevirtual 371	android/os/Handler:post	(Ljava/lang/Runnable;)Z
    //   383: pop
    //   384: return
    //   385: aload 4
    //   387: iload_1
    //   388: invokevirtual 345	java/util/ArrayList:get	(I)Ljava/lang/Object;
    //   391: checkcast 330	com/google/android/gms/ads/internal/reward/mediation/a
    //   394: astore_3
    //   395: aload_3
    //   396: invokevirtual 353	com/google/android/gms/ads/internal/reward/mediation/a:d	()Ljava/util/concurrent/Future;
    //   399: invokeinterface 375 1 0
    //   404: pop
    //   405: aload_0
    //   406: getfield 66	com/google/android/gms/ads/internal/reward/mediation/j:e	Ljava/lang/Object;
    //   409: astore 5
    //   411: aload 5
    //   413: monitorenter
    //   414: aload_3
    //   415: getfield 347	com/google/android/gms/ads/internal/reward/mediation/a:b	Ljava/lang/String;
    //   418: invokestatic 222	android/text/TextUtils:isEmpty	(Ljava/lang/CharSequence;)Z
    //   421: ifne +17 -> 438
    //   424: aload_0
    //   425: getfield 56	com/google/android/gms/ads/internal/reward/mediation/j:g	Ljava/util/List;
    //   428: aload_3
    //   429: invokevirtual 377	com/google/android/gms/ads/internal/reward/mediation/a:e	()Lcom/google/android/gms/ads/internal/reward/mediation/d;
    //   432: invokeinterface 320 2 0
    //   437: pop
    //   438: aload 5
    //   440: monitorexit
    //   441: aload_0
    //   442: getfield 66	com/google/android/gms/ads/internal/reward/mediation/j:e	Ljava/lang/Object;
    //   445: astore 5
    //   447: aload 5
    //   449: monitorenter
    //   450: aload_0
    //   451: getfield 61	com/google/android/gms/ads/internal/reward/mediation/j:d	Ljava/util/HashSet;
    //   454: aload_3
    //   455: getfield 347	com/google/android/gms/ads/internal/reward/mediation/a:b	Ljava/lang/String;
    //   458: invokevirtual 380	java/util/HashSet:contains	(Ljava/lang/Object;)Z
    //   461: ifeq +44 -> 505
    //   464: aload_0
    //   465: bipush -2
    //   467: aload_3
    //   468: getfield 347	com/google/android/gms/ads/internal/reward/mediation/a:b	Ljava/lang/String;
    //   471: aload_3
    //   472: getfield 383	com/google/android/gms/ads/internal/reward/mediation/a:d	Lcom/google/android/gms/ads/internal/mediation/b;
    //   475: invokespecial 355	com/google/android/gms/ads/internal/reward/mediation/j:a	(ILjava/lang/String;Lcom/google/android/gms/ads/internal/mediation/b;)Lcom/google/android/gms/ads/internal/v/a;
    //   478: astore_3
    //   479: getstatic 360	com/google/android/gms/ads/internal/util/client/a:g	Landroid/os/Handler;
    //   482: new 385	com/google/android/gms/ads/internal/reward/mediation/k
    //   485: dup
    //   486: aload_0
    //   487: aload_3
    //   488: invokespecial 386	com/google/android/gms/ads/internal/reward/mediation/k:<init>	(Lcom/google/android/gms/ads/internal/reward/mediation/j;Lcom/google/android/gms/ads/internal/v/a;)V
    //   491: invokevirtual 371	android/os/Handler:post	(Ljava/lang/Runnable;)Z
    //   494: pop
    //   495: aload 5
    //   497: monitorexit
    //   498: return
    //   499: astore_3
    //   500: aload 5
    //   502: monitorexit
    //   503: aload_3
    //   504: athrow
    //   505: aload 5
    //   507: monitorexit
    //   508: iload_1
    //   509: iconst_1
    //   510: iadd
    //   511: istore_1
    //   512: goto -157 -> 355
    //   515: astore_3
    //   516: ldc_w 388
    //   519: aload_3
    //   520: invokestatic 393	com/google/android/gms/ads/internal/util/e:c	(Ljava/lang/String;Ljava/lang/Throwable;)V
    //   523: goto -465 -> 58
    //   526: astore 4
    //   528: invokestatic 399	java/lang/Thread:currentThread	()Ljava/lang/Thread;
    //   531: invokevirtual 402	java/lang/Thread:interrupt	()V
    //   534: aload_0
    //   535: getfield 66	com/google/android/gms/ads/internal/reward/mediation/j:e	Ljava/lang/Object;
    //   538: astore 4
    //   540: aload 4
    //   542: monitorenter
    //   543: aload_3
    //   544: getfield 347	com/google/android/gms/ads/internal/reward/mediation/a:b	Ljava/lang/String;
    //   547: invokestatic 222	android/text/TextUtils:isEmpty	(Ljava/lang/CharSequence;)Z
    //   550: ifne +17 -> 567
    //   553: aload_0
    //   554: getfield 56	com/google/android/gms/ads/internal/reward/mediation/j:g	Ljava/util/List;
    //   557: aload_3
    //   558: invokevirtual 377	com/google/android/gms/ads/internal/reward/mediation/a:e	()Lcom/google/android/gms/ads/internal/reward/mediation/d;
    //   561: invokeinterface 320 2 0
    //   566: pop
    //   567: aload 4
    //   569: monitorexit
    //   570: goto -210 -> 360
    //   573: astore_3
    //   574: aload 4
    //   576: monitorexit
    //   577: aload_3
    //   578: athrow
    //   579: astore 5
    //   581: ldc_w 404
    //   584: aload 5
    //   586: invokestatic 406	com/google/android/gms/ads/internal/util/e:e	(Ljava/lang/String;Ljava/lang/Throwable;)V
    //   589: aload_0
    //   590: getfield 66	com/google/android/gms/ads/internal/reward/mediation/j:e	Ljava/lang/Object;
    //   593: astore 5
    //   595: aload 5
    //   597: monitorenter
    //   598: aload_3
    //   599: getfield 347	com/google/android/gms/ads/internal/reward/mediation/a:b	Ljava/lang/String;
    //   602: invokestatic 222	android/text/TextUtils:isEmpty	(Ljava/lang/CharSequence;)Z
    //   605: ifne +17 -> 622
    //   608: aload_0
    //   609: getfield 56	com/google/android/gms/ads/internal/reward/mediation/j:g	Ljava/util/List;
    //   612: aload_3
    //   613: invokevirtual 377	com/google/android/gms/ads/internal/reward/mediation/a:e	()Lcom/google/android/gms/ads/internal/reward/mediation/d;
    //   616: invokeinterface 320 2 0
    //   621: pop
    //   622: aload 5
    //   624: monitorexit
    //   625: goto -117 -> 508
    //   628: astore_3
    //   629: aload 5
    //   631: monitorexit
    //   632: aload_3
    //   633: athrow
    //   634: astore 5
    //   636: aload_0
    //   637: getfield 66	com/google/android/gms/ads/internal/reward/mediation/j:e	Ljava/lang/Object;
    //   640: astore 4
    //   642: aload 4
    //   644: monitorenter
    //   645: aload_3
    //   646: getfield 347	com/google/android/gms/ads/internal/reward/mediation/a:b	Ljava/lang/String;
    //   649: invokestatic 222	android/text/TextUtils:isEmpty	(Ljava/lang/CharSequence;)Z
    //   652: ifne +17 -> 669
    //   655: aload_0
    //   656: getfield 56	com/google/android/gms/ads/internal/reward/mediation/j:g	Ljava/util/List;
    //   659: aload_3
    //   660: invokevirtual 377	com/google/android/gms/ads/internal/reward/mediation/a:e	()Lcom/google/android/gms/ads/internal/reward/mediation/d;
    //   663: invokeinterface 320 2 0
    //   668: pop
    //   669: aload 4
    //   671: monitorexit
    //   672: aload 5
    //   674: athrow
    //   675: astore_3
    //   676: aload 5
    //   678: monitorexit
    //   679: aload_3
    //   680: athrow
    //   681: astore_3
    //   682: aload 4
    //   684: monitorexit
    //   685: aload_3
    //   686: athrow
    // Local variable table:
    //   start	length	slot	name	signature
    //   0	687	0	this	j
    //   294	218	1	i	int
    //   292	66	2	j	int
    //   78	99	3	localObject1	Object
    //   194	31	3	str1	String
    //   243	245	3	localObject2	Object
    //   499	5	3	localObject3	Object
    //   515	43	3	localJSONException	org.json.JSONException
    //   573	40	3	localObject4	Object
    //   628	32	3	localObject5	Object
    //   675	5	3	localObject6	Object
    //   681	5	3	localObject7	Object
    //   15	371	4	localObject8	Object
    //   526	1	4	localInterruptedException	InterruptedException
    //   579	6	5	localException	Exception
    //   634	43	5	localObject12	Object
    //   44	182	6	str2	String
    //   56	13	7	localIterator	Iterator
    //   119	146	8	localObject13	Object
    //   132	102	9	localObject14	Object
    // Exception table:
    //   from	to	target	type
    //   124	134	194	finally
    //   139	191	194	finally
    //   195	198	194	finally
    //   200	267	194	finally
    //   450	498	499	finally
    //   500	503	499	finally
    //   505	508	499	finally
    //   99	115	515	org/json/JSONException
    //   395	405	526	java/lang/InterruptedException
    //   543	567	573	finally
    //   567	570	573	finally
    //   574	577	573	finally
    //   395	405	579	java/lang/Exception
    //   598	622	628	finally
    //   622	625	628	finally
    //   629	632	628	finally
    //   395	405	634	finally
    //   528	534	634	finally
    //   581	589	634	finally
    //   414	438	675	finally
    //   438	441	675	finally
    //   676	679	675	finally
    //   645	669	681	finally
    //   669	672	681	finally
    //   682	685	681	finally
  }
  
  public final void a(int paramInt) {}
  
  public final void a(String paramString)
  {
    synchronized (this.e)
    {
      this.d.add(paramString);
      return;
    }
  }
  
  public final void be_() {}
}


/* Location:              /home/chengjian/CM_test/gp/apk/a.jar!/com/google/android/gms/ads/internal/reward/mediation/j.class
 * Java compiler version: 6 (50.0)
 * JD-Core Version:       0.7.1
 */