package com.google.android.finsky.as;

public final class c
{
  /* Error */
  public static n a(String paramString, j paramj)
  {
    // Byte code:
    //   0: invokestatic 19	android/os/Environment:getExternalStorageDirectory	()Ljava/io/File;
    //   3: astore 4
    //   5: new 21	java/io/File
    //   8: dup
    //   9: aload 4
    //   11: aload_0
    //   12: invokespecial 24	java/io/File:<init>	(Ljava/io/File;Ljava/lang/String;)V
    //   15: astore_3
    //   16: aload_3
    //   17: astore_2
    //   18: aload_3
    //   19: invokevirtual 28	java/io/File:exists	()Z
    //   22: ifne +23 -> 45
    //   25: new 21	java/io/File
    //   28: dup
    //   29: new 21	java/io/File
    //   32: dup
    //   33: aload 4
    //   35: ldc 30
    //   37: invokespecial 24	java/io/File:<init>	(Ljava/io/File;Ljava/lang/String;)V
    //   40: aload_0
    //   41: invokespecial 24	java/io/File:<init>	(Ljava/io/File;Ljava/lang/String;)V
    //   44: astore_2
    //   45: new 32	java/io/BufferedReader
    //   48: dup
    //   49: new 34	java/io/FileReader
    //   52: dup
    //   53: aload_2
    //   54: invokespecial 37	java/io/FileReader:<init>	(Ljava/io/File;)V
    //   57: invokespecial 40	java/io/BufferedReader:<init>	(Ljava/io/Reader;)V
    //   60: astore_0
    //   61: new 42	com/google/android/finsky/as/n
    //   64: dup
    //   65: invokespecial 43	com/google/android/finsky/as/n:<init>	()V
    //   68: astore_2
    //   69: aload_0
    //   70: invokevirtual 47	java/io/BufferedReader:readLine	()Ljava/lang/String;
    //   73: astore_3
    //   74: aload_3
    //   75: ifnull +173 -> 248
    //   78: aload_3
    //   79: invokevirtual 52	java/lang/String:trim	()Ljava/lang/String;
    //   82: astore 4
    //   84: aload 4
    //   86: ldc 54
    //   88: invokevirtual 58	java/lang/String:startsWith	(Ljava/lang/String;)Z
    //   91: ifne -22 -> 69
    //   94: aload 4
    //   96: invokestatic 64	android/text/TextUtils:isEmpty	(Ljava/lang/CharSequence;)Z
    //   99: ifne -30 -> 69
    //   102: aload 4
    //   104: invokestatic 69	com/google/android/finsky/utils/j:a	(Ljava/lang/String;)[Ljava/lang/String;
    //   107: astore 5
    //   109: aload 5
    //   111: iconst_0
    //   112: aaload
    //   113: astore_3
    //   114: aload_3
    //   115: invokestatic 64	android/text/TextUtils:isEmpty	(Ljava/lang/CharSequence;)Z
    //   118: ifeq +49 -> 167
    //   121: ldc 71
    //   123: iconst_1
    //   124: anewarray 4	java/lang/Object
    //   127: dup
    //   128: iconst_0
    //   129: aload 4
    //   131: aastore
    //   132: invokestatic 76	com/google/android/finsky/utils/FinskyLog:a	(Ljava/lang/String;[Ljava/lang/Object;)V
    //   135: goto -66 -> 69
    //   138: astore_1
    //   139: ldc 78
    //   141: iconst_1
    //   142: anewarray 4	java/lang/Object
    //   145: dup
    //   146: iconst_0
    //   147: aload_1
    //   148: invokevirtual 81	java/lang/Exception:getMessage	()Ljava/lang/String;
    //   151: aastore
    //   152: invokestatic 84	com/google/android/finsky/utils/FinskyLog:d	(Ljava/lang/String;[Ljava/lang/Object;)V
    //   155: aload_0
    //   156: invokestatic 88	com/google/common/io/i:a	(Ljava/io/Reader;)V
    //   159: new 42	com/google/android/finsky/as/n
    //   162: dup
    //   163: invokespecial 43	com/google/android/finsky/as/n:<init>	()V
    //   166: areturn
    //   167: aload_1
    //   168: aload 5
    //   170: invokeinterface 93 2 0
    //   175: ifne +27 -> 202
    //   178: ldc 95
    //   180: iconst_1
    //   181: anewarray 4	java/lang/Object
    //   184: dup
    //   185: iconst_0
    //   186: aload 4
    //   188: aastore
    //   189: invokestatic 76	com/google/android/finsky/utils/FinskyLog:a	(Ljava/lang/String;[Ljava/lang/Object;)V
    //   192: goto -123 -> 69
    //   195: astore_1
    //   196: aload_0
    //   197: invokestatic 88	com/google/common/io/i:a	(Ljava/io/Reader;)V
    //   200: aload_1
    //   201: athrow
    //   202: aload_1
    //   203: aload 5
    //   205: invokeinterface 99 2 0
    //   210: astore 4
    //   212: aload_2
    //   213: aload_3
    //   214: aload 4
    //   216: invokevirtual 102	com/google/android/finsky/as/n:a	(Ljava/lang/String;Ljava/lang/Object;)V
    //   219: aload_1
    //   220: aload 4
    //   222: invokeinterface 105 2 0
    //   227: ifeq -158 -> 69
    //   230: aload_2
    //   231: aload_2
    //   232: invokevirtual 108	com/google/android/finsky/as/n:a	()Ljava/util/List;
    //   235: invokeinterface 114 1 0
    //   240: iconst_1
    //   241: isub
    //   242: putfield 117	com/google/android/finsky/as/n:b	I
    //   245: goto -176 -> 69
    //   248: aload_0
    //   249: invokestatic 88	com/google/common/io/i:a	(Ljava/io/Reader;)V
    //   252: aload_2
    //   253: areturn
    //   254: astore_1
    //   255: aconst_null
    //   256: astore_0
    //   257: goto -118 -> 139
    //   260: astore_1
    //   261: aconst_null
    //   262: astore_0
    //   263: goto -67 -> 196
    //   266: astore_1
    //   267: goto -71 -> 196
    // Local variable table:
    //   start	length	slot	name	signature
    //   0	270	0	paramString	String
    //   0	270	1	paramj	j
    //   17	236	2	localObject1	Object
    //   15	199	3	localObject2	Object
    //   3	218	4	localObject3	Object
    //   107	97	5	arrayOfString	String[]
    // Exception table:
    //   from	to	target	type
    //   61	69	138	java/lang/Exception
    //   69	74	138	java/lang/Exception
    //   78	109	138	java/lang/Exception
    //   114	135	138	java/lang/Exception
    //   167	192	138	java/lang/Exception
    //   202	245	138	java/lang/Exception
    //   61	69	195	finally
    //   69	74	195	finally
    //   78	109	195	finally
    //   114	135	195	finally
    //   167	192	195	finally
    //   202	245	195	finally
    //   0	16	254	java/lang/Exception
    //   18	45	254	java/lang/Exception
    //   45	61	254	java/lang/Exception
    //   0	16	260	finally
    //   18	45	260	finally
    //   45	61	260	finally
    //   139	155	266	finally
  }
}


/* Location:              /home/chengjian/CM_test/gp/apk/a.jar!/com/google/android/finsky/as/c.class
 * Java compiler version: 6 (50.0)
 * JD-Core Version:       0.7.1
 */